Workbook

Sheet README
A1: G1 economics model v2 - Borut, Bomet. Rebuilt 2026-10-15 from owner intake update 2. v1 is kept as G1-model-v1.xlsx. All amounts KES; USD at CBK rate on Inputs.
A2: Low = adverse case, Base, High = favourable. Every calculated cell is a live formula; change blue cells on Inputs (or Overhead).
A3: Tags: SOURCED (published figure with URL), BENCHMARK (published but undated/other area, or standard convention), ASSUMED (no source), OWNER-REPORTED (supplied by owner; no documents seen).
A4: Sheets: Inputs > Cattle, Sheep, Goats, Poultry (one block per breed/species), Mix, Labour, Lorry, Capital, Overhead > Farm_PnL > Cash_18m > B12 > Breakeven > Scenarios > Collect_8wk.
A5: Changes from v1: poultry 2,270 birds by breed (v1 ~1,000; intake file shows 2,770 which is an arithmetic error: 4 x 500 + 270 = 2,270); 23 acres, no rent or rates; staff 3 x 22,000; weekly vet; lorry; structures KES 2m; 6-month stores; owner >300 km.
A6: Land has no cash cost. B12 charges no land rent; its opportunity cost appears through lease rent, sale proceeds and g x L, as the PLAN convention requires.
A7: No farm accounts exist. This is a benchmark screen, not a forecast. Crops (and tea) are not modelled. Lorry hire income is zero in all headline cases.
A8: Stress limit gate uses literal B12 cash basis (depreciation added back); the v1 basis (OMBM) is shown as a memo on B12.
A10: Input counts by tag (live):
A11: SOURCED | B11: =COUNTIF(Inputs!$F$3:$F$306,"SOURCED") -> 8
A12: BENCHMARK | B12: =COUNTIF(Inputs!$F$3:$F$306,"BENCHMARK") -> 40
A13: ASSUMED | B13: =COUNTIF(Inputs!$F$3:$F$306,"ASSUMED") -> 217
A14: OWNER-REPORTED | B14: =COUNTIF(Inputs!$F$3:$F$306,"OWNER-REPORTED") -> 19
A15: Total inputs | B15: =SUM(B11:B14) -> 284
A16: Poultry check: standing birds (should be 2,270) | B16: =Poultry!D244 -> 2270
A17: Poultry slot-margin check (should be 0) | B17: =Poultry!D263 -> 0

Sheet Scenarios
A1: Scenario summary: Low (adverse) / Base / High (favourable). KES with USD for base. Poultry corrected to 2,270 birds.
A2: Line | B2: Unit | C2: Low (adverse) | D2: Base | E2: High (favourable) | F2: Base in USD | G2: Note
A3: Revenue and margin
A4: Revenue | B4: KES | C4: =Farm_PnL!C15 -> 3249336 | D4: =Farm_PnL!D15 -> 4854130 | E4: =Farm_PnL!E15 -> 6996262.8 | F4: =D4/Inputs!$D$4 -> 37371.083
A5: Variable costs | B5: KES | C5: =Farm_PnL!C31 -> 5011545.2 | D5: =Farm_PnL!D31 -> 4035305.2 | E5: =Farm_PnL!E31 -> 3404828 | F5: =D5/Inputs!$D$4 -> 31067.097
A6: Gross margin | B6: KES | C6: =Farm_PnL!C30 -> -1762209.2 | D6: =Farm_PnL!D30 -> 818824.81 | E6: =Farm_PnL!E30 -> 3591434.8 | F6: =D6/Inputs!$D$4 -> 6303.9865
A7: Hired labour (3 x 22,000 + statutory + casuals) | B7: KES | C7: =Farm_PnL!C33 -> 911684.38 | D7: =Farm_PnL!D33 -> 868200 | E7: =Farm_PnL!E33 -> 865700 | F7: =D7/Inputs!$D$4 -> 6684.1173
A8: Weekly vet fees | B8: KES | C8: =Farm_PnL!C34 -> 208000 | D8: =Farm_PnL!D34 -> 156000 | E8: =Farm_PnL!E34 -> 104000 | F8: =D8/Inputs!$D$4 -> 1201.0162
A9: Lorry net cost (incl. depreciation) | B9: KES | C9: =Farm_PnL!C43 -> 1384475 | D9: =Farm_PnL!D43 -> 949433.33 | E9: =Farm_PnL!E43 -> 691622.73 | F9: =D9/Inputs!$D$4 -> 7309.5183
A10: Labour + fixed costs (all) | B10: KES | C10: =Farm_PnL!C44 -> 2919159.4 | D10: =Farm_PnL!D44 -> 2351633.3 | E10: =Farm_PnL!E44 -> 2001322.7 | F10: =D10/Inputs!$D$4 -> 18104.807
A11: OMBM (lorry as owned) | B11: KES | C11: =Farm_PnL!C46 -> -4681368.6 | D11: =Farm_PnL!D46 -> -1532808.5 | E11: =Farm_PnL!E46 -> 1590112.1 | F11: =D11/Inputs!$D$4 -> -11800.82
A12: OMBM % of revenue | B12: % | C12: =Farm_PnL!C47 -> -1.4407155 | D12: =Farm_PnL!D47 -> -0.3157741 | E12: =Farm_PnL!E47 -> 0.22728021
A13: OMBM if there were no lorry | B13: KES | C13: =Farm_PnL!C48 -> -3296893.6 | D13: =Farm_PnL!D48 -> -583375.19 | E13: =Farm_PnL!E48 -> 2281734.8 | F13: =D13/Inputs!$D$4 -> -4491.3018
A14: Cash margin (before controls) | B14: KES | C14: =Farm_PnL!C49 -> -4059493.6 | D14: =Farm_PnL!D49 -> -995308.52 | E14: =Farm_PnL!E49 -> 2071362.1 | F14: =D14/Inputs!$D$4 -> -7662.7032
A15: Cash margin after controls, stipend and owner travel | B15: KES | C15: =Farm_PnL!C49-B12!C17-B12!C18-B12!C19 -> -4559493.6 | D15: =Farm_PnL!D49-B12!D17-B12!D18-B12!D19 -> -1351308.5 | E15: =Farm_PnL!E49-B12!E17-B12!E18-B12!E19 -> 1763362.1 | F15: =D15/Inputs!$D$4 -> -10403.484
A16: v1 comparison (static values from G1-model-v1.xlsx; v1 had 1,000 birds, 12 acres, KES 533k labour)
A17: v1 revenue | B17: KES | C17: 2158161.9 | D17: 2776511.8 | E17: 3568790
A18: v1 gross margin | B18: KES | C18: -387335.25 | D18: 527232.23 | E18: 1517089.9
A19: v1 hired labour | B19: KES | C19: 535300 | D19: 532800 | E19: 530300
A20: v1 OMBM | B20: KES | C20: -1175635.2 | D20: -233567.77 | E20: 784789.85
A21: v1 owner-operator B12 value | B21: KES | C21: -1894395.2 | D21: -710748.56 | E21: 511654.85
A22: Gross margin by enterprise
A23: Cattle and dairy | B23: KES | C23: =Farm_PnL!C19 -> -63160 | D23: =Farm_PnL!D19 -> 107600 | E23: =Farm_PnL!E19 -> 329400 | F23: =D23/Inputs!$D$4 -> 828.39326
A24: Sheep | B24: KES | C24: =Farm_PnL!C20 -> 17179.04 | D24: =Farm_PnL!D20 -> 119340.8 | E24: =Farm_PnL!E20 -> 255260.48 | F24: =D24/Inputs!$D$4 -> 918.78359
A25: Goats | B25: KES | C25: =Farm_PnL!C21 -> 17532.8 | D25: =Farm_PnL!D21 -> 39904 | E25: =Farm_PnL!E21 -> 69280.336 | F25: =D25/Inputs!$D$4 -> 307.2138
A26: Sasso | B26: KES | C26: =Farm_PnL!C22 -> -427996.43 | D26: =Farm_PnL!D22 -> 86169.503 | E26: =Farm_PnL!E22 -> 600246.61 | F26: =D26/Inputs!$D$4 -> 663.40367
A27: Kuroiler | B27: KES | C27: =Farm_PnL!C23 -> -427996.43 | D27: =Farm_PnL!D23 -> 86169.503 | E27: =Farm_PnL!E23 -> 600246.61 | F27: =D27/Inputs!$D$4 -> 663.40367
A28: Rainbow | B28: KES | C28: =Farm_PnL!C24 -> -427996.43 | D28: =Farm_PnL!D24 -> 86169.503 | E28: =Farm_PnL!E24 -> 600246.61 | F28: =D28/Inputs!$D$4 -> 663.40367
A29: Kebro | B29: KES | C29: =Farm_PnL!C25 -> -427996.43 | D29: =Farm_PnL!D25 -> 86169.503 | E29: =Farm_PnL!E25 -> 600246.61 | F29: =D29/Inputs!$D$4 -> 663.40367
A30: Ducks | B30: KES | C30: =Farm_PnL!C26 -> -26320 | D30: =Farm_PnL!D26 -> 45560 | E30: =Farm_PnL!E26 -> 147613.14 | F30: =D30/Inputs!$D$4 -> 350.75833
A31: Geese | B31: KES | C31: =Farm_PnL!C27 -> 11471.429 | D31: =Farm_PnL!D27 -> 65622 | E31: =Farm_PnL!E27 -> 133068.57 | F31: =D31/Inputs!$D$4 -> 505.2121
A32: Turkeys | B32: KES | C32: =Farm_PnL!C28 -> 3454.2857 | D32: =Farm_PnL!D28 -> 36030 | E32: =Farm_PnL!E28 -> 72258 | F32: =D32/Inputs!$D$4 -> 277.38856
A33: Guinea fowl | B33: KES | C33: =Farm_PnL!C29 -> -10381.071 | D33: =Farm_PnL!D29 -> 60090 | E33: =Farm_PnL!E29 -> 183567.86 | F33: =D33/Inputs!$D$4 -> 462.62222
A34: Gross margin per task hour
A35: Cattle and dairy | B35: KES/h | C35: =Farm_PnL!C52 -> -43.260274 | D35: =Farm_PnL!D52 -> 84.227006 | E35: =Farm_PnL!E52 -> 282.02055
A36: Sheep | B36: KES/h | C36: =Farm_PnL!C53 -> 26.147702 | D36: =Farm_PnL!D53 -> 217.97406 | E36: =Farm_PnL!E53 -> 537.95675
A37: Goats | B37: KES/h | C37: =Farm_PnL!C54 -> 80.058447 | D37: =Farm_PnL!D54 -> 218.65205 | E37: =Farm_PnL!E54 -> 421.79809
A38: Four chicken breeds | B38: KES/h | C38: =Farm_PnL!C55 -> -469.03718 | D38: =Farm_PnL!D55 -> 118.04042 | E38: =Farm_PnL!E55 -> 996.6735
A39: Ducks, geese, turkeys, guinea fowl | B39: KES/h | C39: =Farm_PnL!C56 -> -44.191491 | D39: =Farm_PnL!D56 -> 525.88026 | E39: =Farm_PnL!E56 -> 1649.7012
A40: Poultry volumes
A41: Standing birds | B41: birds | C41: =Poultry!C244 -> 2270 | D41: =Poultry!D244 -> 2270 | E41: =Poultry!E244 -> 2270
A42: Egg trays to sell per day | B42: trays/day | C42: =Poultry!C248 -> 7.7150685 | D42: =Poultry!D248 -> 10.630137 | E42: =Poultry!E248 -> 12.821918
A43: Live birds to sell per week | B43: birds/wk | C43: =Poultry!C250 -> 53.815385 | D43: =Poultry!D250 -> 59.951923 | E43: =Poultry!E250 -> 70.053846
A44: Purchased feed % of revenue | B44: % | C44: =Farm_PnL!C60 -> 1.1341327 | D44: =Farm_PnL!D60 -> 0.58108264 | E44: =Farm_PnL!E60 -> 0.32234405
A45: Egg share of poultry revenue | B45: % | C45: =Poultry!C262 -> 0.36763469 | D45: =Poultry!D262 -> 0.4239459 | E45: =Poultry!E262 -> 0.42979007
A46: Labour
A47: FTE required | B47: FTE | C47: =Labour!C15 -> 3.303588 | D47: =Labour!D15 -> 2.7172222 | E47: =Labour!E15 -> 2.3219745
A48: Utilisation of 3 staff | B48: % | C48: =Labour!C16 -> 1.101196 | D48: =Labour!D16 -> 0.90574074 | E48: =Labour!E16 -> 0.77399151
A49: Labour % of revenue | B49: % | C49: =Labour!C24 -> 0.28057559 | D49: =Labour!D24 -> 0.178858 | E49: =Labour!E24 -> 0.12373749
A50: Gross margin / (labour + fixed costs) | B50: x | C50: =Labour!C26 -> -0.6036701 | D50: =Labour!D26 -> 0.34819408 | E50: =Labour!E26 -> 1.7945306
A51: Capital and working capital
A52: Total capital | B52: KES | C52: =Capital!C14 -> 18800122 | D52: =Capital!D14 -> 21772156 | E52: =Capital!E14 -> 26061931 | F52: =D52/Inputs!$D$4 -> 167619.95
A53: Capital excl. land | B53: KES | C53: =Capital!C15 -> 10750122 | D53: =Capital!D15 -> 10272156 | E53: =Capital!E15 -> 9961930.6 | F53: =D53/Inputs!$D$4 -> 79083.5
A54: Land value (opportunity cost) | B54: KES | C54: =Farm_PnL!C65 -> 8050000 | D54: =Farm_PnL!D65 -> 11500000 | E54: =Farm_PnL!E65 -> 16100000 | F54: =D54/Inputs!$D$4 -> 88536.454
A55: K (operating capital at risk) | B55: KES | C55: =Farm_PnL!C63 -> 11119670 | D55: =Farm_PnL!D63 -> 10564511 | E55: =Farm_PnL!E63 -> 10208609 | F55: =D55/Inputs!$D$4 -> 81334.293
A56: Peak funding need over 18 months (cash sheet) | B56: KES | C56: =Cash_18m!C43 -> 4784118 | D56: =Cash_18m!D43 -> 449807 | E56: =Cash_18m!E43 -> 0 | F56: =D56/Inputs!$D$4 -> 3462.9841
A57: Cumulative cash after 18 months | B57: KES | C57: =Cash_18m!C44 -> -4784118 | D57: =Cash_18m!D44 -> -449807 | E57: =Cash_18m!E44 -> 3911973.7 | F57: =D57/Inputs!$D$4 -> -3462.9841
A58: B12 values (annual after-risk income)
A59: Self-run (PLAN generic) | B59: KES | C59: =B12!C14 -> -7183852.1 | D59: =B12!D14 -> -3723889 | E59: =B12!E14 -> -243146.17 | F59: =D59/Inputs!$D$4 -> -28669.559
A60: Owner-operator, lorry kept | B60: KES | C60: =B12!C21 -> -6152352.1 | D60: =B12!D21 -> -2378189 | E60: =B12!E21 -> 1196353.8 | F60: =D60/Inputs!$D$4 -> -18309.254
A61: Owner-operator, lorry sold | B61: KES | C61: =B12!C26 -> -4457377.1 | D61: =B12!D26 -> -1163255.6 | E61: =B12!E26 -> 2108476.6 | F61: =D61/Inputs!$D$4 -> -8955.6982
A62: Lease | B62: KES | C62: =B12!C33 -> 100767.5 | D62: =B12!D33 -> 268767.5 | E62: =B12!E33 -> 525767.5 | F62: =D62/Inputs!$D$4 -> 2069.1932
A63: Sale | B63: KES | C63: =B12!C36 -> 318155 | D63: =B12!D36 -> 383705 | E63: =B12!E36 -> 471105 | F63: =D63/Inputs!$D$4 -> 2954.0765
A64: Winner, ranking A (all options) | B64: text | C64: =B12!C60 -> Sale (conditional exit) | D64: =B12!D60 -> Sale (conditional exit) | E64: =B12!E60 -> Owner-operator, sell lorry
A65: Winner, ranking B (executable now) | B65: text | C65: =B12!C65 -> No viable option (hold, simplify or fix title first) | D65: =B12!D65 -> No viable option (hold, simplify or fix title first) | E65: =B12!E65 -> Owner-operator, sell lorry
A66: B12 outcome | B66: text | C66: =B12!C66 -> No viable option: do not proceed as designed | D66: =B12!D66 -> No viable option: do not proceed as designed | E66: =B12!E66 -> Proceed
A67: Stress: option 2 worst-case net cash flow | B67: KES | C67: =B12!C46 -> -5812379.9 | D67: =B12!D46 -> -2360134.8 | E67: =B12!E46 -> 364109.55 | F67: =D67/Inputs!$D$4 -> -18170.258
A68: Stress limit (-10% K) | B68: KES | C68: =B12!C42 -> -1111967 | D68: =B12!D42 -> -1056451.1 | E68: =B12!E42 -> -1020860.9 | F68: =D68/Inputs!$D$4 -> -8133.4293
A69: Option 2 passes stress (1/0) | B69: flag | C69: =B12!C50 -> 0 | D69: =B12!D50 -> 0 | E69: =B12!E50 -> 1
A70: Memo: stress, v1 basis, passes (1/0) | B70: flag | C70: =B12!C52 -> 0 | D70: =B12!D52 -> 0 | E70: =B12!E52 -> 1
A71: Break-even
A72: OMBM shortfall to B12 value = 0 | B72: KES | C72: =Breakeven!C4 -> 6152352.1 | D72: =Breakeven!D4 -> 2378189 | E72: =Breakeven!E4 -> 0 | F72: =D72/Inputs!$D$4 -> 18309.254
A73: OMBM shortfall to cash break-even | B73: KES | C73: =Breakeven!C5 -> 5181368.6 | D73: =Breakeven!D5 -> 1888808.5 | E73: =Breakeven!E5 -> 0 | F73: =D73/Inputs!$D$4 -> 14541.601
A74: Egg price needed (KES/egg) | B74: KES/egg | C74: =Breakeven!C8 -> 87.86056 | D74: =Breakeven!D8 -> 36.063069 | E74: =Breakeven!E8 -> 18
A75: Live-bird price needed | B75: KES/bird | C75: =Breakeven!C11 -> 2937.3642 | D75: =Breakeven!D11 -> 1555.6472 | E75: =Breakeven!E11 -> 920.41287
A76: Feed price cut needed | B76: % | C76: =Breakeven!C13 -> 1.6694856 | D76: =Breakeven!D13 -> 0.84313488 | E76: =Breakeven!E13 -> 0
A77: Gain from selling lorry | B77: KES | C77: =Breakeven!C19 -> 1694975 | D77: =Breakeven!D19 -> 1214933.3 | E77: =Breakeven!E19 -> 912122.73 | F77: =D77/Inputs!$D$4 -> 9353.5556
A78: Lorry hire days to cover its own cost | B78: days | C78: =Lorry!C29 -> 317.35817 | D78: =Lorry!D29 -> 73.033333 | E78: =Lorry!E29 -> 31.456895
A79: Owner hours/yr, option 2 | B79: h | C79: =B12!C16 -> 1000 | D79: =B12!D16 -> 556 | E79: =B12!E16 -> 346
A80: Owner hours/week, option 2 | B80: h/wk | C80: =B12!C16/52 -> 19.230769 | D80: =B12!D16/52 -> 10.692308 | E80: =B12!E16/52 -> 6.6538462

Sheet Inputs
A1: INPUTS - KES unless stated. Blue = editable input. Tags: SOURCED / BENCHMARK / ASSUMED / OWNER-REPORTED. Low = adverse, High = favourable.
A2: Parameter | B2: Unit | C2: Low (adverse) | D2: Base | E2: High (favourable) | F2: Tag | G2: Source / note (accessed 2026-10-15 unless stated)
A3: General
A4: Exchange rate | B4: KES per USD | C4: 129.89 | D4: 129.89 | E4: 129.89 | F4: SOURCED | G4: CBK indicative rate posted 7 Oct 2026 (centralbank.go.ke via web search; confirm daily rate). Unchanged from v1
A5: Declared real return on cash proceeds | B5: % p.a. | C5: 0.02 | D5: 0.02 | E5: 0.02 | F5: ASSUMED | G5: B12 default 2%
A6: Real change in land value g | B6: % p.a. | C6: 0 | D6: 0.01 | E6: 0.02 | F6: ASSUMED | G6: B12 default +1%; no local land-value series found
A7: Risk charge on capital at risk | B7: % | C7: 0.05 | D7: 0.04 | E7: 0.03 | F7: BENCHMARK | G7: B12 default 3-5%
A8: Owner hourly shadow price p | B8: KES/h | C8: 400 | D8: 300 | E8: 250 | F8: ASSUMED | G8: Owner's occupation unknown. Test sensitivity
A9: Selling cost + tax on sale | B9: % | C9: 0.05 | D9: 0.05 | E9: 0.05 | F9: BENCHMARK | G9: B12 default 5%; accountant to quantify
A10: Land, structures, water (owner intake update 2)
A11: Farm area | B11: acres | C11: 23 | D11: 23 | E11: 23 | F11: OWNER-REPORTED | G11: Intake update 2: 23 acres, altitude 1,765-1,790 m. v1 guessed 12. No documents seen
A12: Land value per acre (opportunity cost / sale value, NOT a cash cost) | B12: KES/acre | C12: 350000 | D12: 500000 | E12: 700000 | F12: ASSUMED | G12: No Bomet price found again in v2 search. Only a low-authority blog (graduatefarmer.co.ke, 2025) gives 150k remote to 800k+ near Nairobi/main roads. Unchanged from v1; get a valuer figure
A13: Farm structures, replacement value (houses, stores, fencing, equipment) | B13: KES | C13: 2000000 | D13: 2000000 | E13: 2000000 | F13: OWNER-REPORTED | G13: Owner: structures "valued at about KES 2m". AMBIGUOUS whether this is structures only or total capital. Capital sheet shows 2m cannot be total (animals alone exceed it). Treated as structures only
A14: Depreciation life of structures | B14: years | C14: 10 | D14: 10 | E14: 10 | F14: ASSUMED | G14: Unchanged from v1. Mixed timber/iron-sheet/block structures likely 10-20 years
A15: Repairs and maintenance | B15: % of structures | C15: 0.04 | D15: 0.03 | E15: 0.02 | F15: ASSUMED | G15: Unchanged from v1
A16: Land rent and county land rates | B16: KES/yr | C16: 0 | D16: 0 | E16: 0 | F16: OWNER-REPORTED | G16: Owner: no land rent or rates payable. Land has opportunity cost only (see B12: lease rent, sale proceeds, g x L)
A17: Water pans: separate value counted in asset base | B17: KES | C17: 0 | D17: 0 | E17: 0 | F17: ASSUMED | G17: Pans are sunk earthworks; treated as part of the land value to avoid double counting. Owner says "about 8m litres" each: ambiguous (8 million L = 8,000 m3 or 8 m3). Strong water security reported; upkeep inside Water line below
A18: Lease/sale legally executable now? (1 yes, 0 no/unknown) | B18: flag | C18: 0 | D18: 0 | E18: 0 | F18: ASSUMED | G18: Land searchers confirmed ownership (owner-reported) but title document, freehold status and any Land Control Board consent not seen. 0 keeps lease/sale out of Ranking B; set 1 once a lawyer confirms
A19: Herd (owner intake; counts confirmed by owner-reported independent count)
A20: Cattle | B20: head | C20: 10 | D20: 10 | E20: 10 | F20: OWNER-REPORTED | G20: Intake update 2 (who counted and when not stated)
A21: Sheep (tagged) | B21: head | C21: 50 | D21: 50 | E21: 50 | F21: OWNER-REPORTED | G21: Intake update 2
A22: Goats | B22: head | C22: 10 | D22: 10 | E22: 10 | F22: OWNER-REPORTED | G22: Intake update 2
A23: TLU factor cattle | B23: TLU/head | C23: 0.7 | D23: 0.7 | E23: 0.7 | F23: BENCHMARK | G23: Standard convention
A24: TLU factor sheep/goat | B24: TLU/head | C24: 0.1 | D24: 0.1 | E24: 0.1 | F24: BENCHMARK | G24: Standard convention
A25: TLU factor poultry | B25: TLU/bird | C25: 0.01 | D25: 0.01 | E25: 0.01 | F25: BENCHMARK | G25: Standard convention
A26: Cattle (assumed dairy-type, 4 cows in milk of 10 head; unchanged from v1)
A27: Cows in milk | B27: head | C27: 4 | D27: 4 | E27: 5 | F27: ASSUMED | G27: Herd structure unknown
A28: Milk per cow per day | B28: L | C28: 7 | D28: 8 | E28: 9 | F28: ASSUMED | G28: Measure
A29: Days in milk per year per cow | B29: days | C29: 290 | D29: 300 | E29: 305 | F29: ASSUMED
A30: Farm-gate milk price | B30: KES/L | C30: 34 | D30: 38 | E30: 42 | F30: BENCHMARK | G30: Brookside/New KCC ~37 (Business Daily, undated); KCC Sotik 41-43 (KNA). Dates unconfirmed
A31: Cooling, transport, levies | B31: KES/L | C31: 3 | D31: 2.5 | E31: 2 | F31: ASSUMED
A32: Dairy meal per cow in milk per day | B32: kg | C32: 3 | D32: 3 | E32: 3 | F32: ASSUMED
A33: Dairy meal price | B33: KES/kg | C33: 56 | D33: 52 | E33: 48 | F33: BENCHMARK | G33: Derived from layers mash 3,900/70 kg (Capital FM Nov 25)
A34: Purchased hay/forage per head | B34: KES/head/yr | C34: 4000 | D34: 3000 | E34: 2000 | F34: ASSUMED | G34: Depends on own fodder; 23 acres may allow more own fodder than v1 assumed 12
A35: Minerals and salt per head | B35: KES/head/yr | C35: 1800 | D35: 1800 | E35: 1800 | F35: ASSUMED
A36: Drugs, AI, acaricide per head (excl. weekly vet visit fee) | B36: KES/head/yr | C36: 7000 | D36: 6000 | E36: 5000 | F36: ASSUMED | G36: Replace with vet quote
A37: Cattle sold per year | B37: head | C37: 1 | D37: 2 | E37: 2 | F37: ASSUMED
A38: Price per head sold | B38: KES | C38: 32000 | D38: 40000 | E38: 50000 | F38: BENCHMARK | G38: KMC 140-180 KES/kg live (kenyanews.go.ke Feb 2026) x ~250 kg
A39: Mortality/loss | B39: % of herd value | C39: 0.04 | D39: 0.03 | E39: 0.02 | F39: ASSUMED
A40: Value per head (capital) | B40: KES | C40: 60000 | D40: 60000 | E40: 60000 | F40: ASSUMED
A41: Sheep (40 breeding ewes of 50; unchanged from v1)
A42: Breeding ewes | B42: head | C42: 40 | D42: 40 | E42: 40 | F42: ASSUMED
A43: Lambs weaned per ewe per year | B43: no. | C43: 0.8 | D43: 1 | E43: 1.2 | F43: ASSUMED
A44: Replacement rate of ewes | B44: % | C44: 0.18 | D44: 0.15 | E44: 0.12 | F44: ASSUMED
A45: Sale weight | B45: kg live | C45: 27 | D45: 28 | E45: 29 | F45: BENCHMARK | G45: ~30 kg avg (Springer Pastoralism study); older data
A46: Price | B46: KES/kg live | C46: 210 | D46: 240 | E46: 280 | F46: BENCHMARK | G46: KMC 200-210/kg (Garissa, Feb 2026); Selina Wamucii ~280/kg aggregated
A47: Supplement/feed per head | B47: KES/head/yr | C47: 1200 | D47: 1000 | E47: 800 | F47: ASSUMED
A48: Drugs, deworm, dip, vaccines per head (sheep and goats) | B48: KES/head/yr | C48: 900 | D48: 800 | E48: 700 | F48: ASSUMED
A49: Minerals per head | B49: KES/head/yr | C49: 200 | D49: 200 | E49: 200 | F49: ASSUMED
A50: Selling cost (transport, commission) | B50: % of revenue | C50: 0.06 | D50: 0.04 | E50: 0.03 | F50: ASSUMED
A51: Value per head | B51: KES | C51: 6000 | D51: 6000 | E51: 6000 | F51: ASSUMED
A52: Goats (8 does of 10; unchanged from v1)
A53: Breeding does | B53: head | C53: 8 | D53: 8 | E53: 8 | F53: ASSUMED
A54: Kids weaned per doe per year | B54: no. | C54: 1.2 | D54: 1.4 | E54: 1.6 | F54: ASSUMED
A55: Replacement rate | B55: % | C55: 0.22 | D55: 0.2 | E55: 0.18 | F55: ASSUMED
A56: Sale weight | B56: kg live | C56: 25 | D56: 26 | E56: 27 | F56: BENCHMARK | G56: ~30 kg adult avg (Springer)
A57: Price | B57: KES/kg live | C57: 220 | D57: 250 | E57: 290 | F57: BENCHMARK | G57: KMC 210-220/kg (Feb 2026 Garissa offer)
A58: Supplement per head | B58: KES/head/yr | C58: 1200 | D58: 1000 | E58: 800 | F58: ASSUMED
A59: Value per head | B59: KES | C59: 6500 | D59: 6500 | E59: 6500 | F59: ASSUMED
A60: Poultry: shared prices and costs
A61: Layers mash (used for adult hens) per 70 kg bag | B61: KES/bag | C61: 4300 | D61: 3900 | E61: 3600 | F61: BENCHMARK | G61: Sh3,900-4,000 (Capital FM / Kenyan Wall Street, ~Nov 2025); Sh4,500 in Feb 2023 (The Star). No 2026 price found in v2 search
A62: Chick/grower mash per 70 kg bag (growers, replacement pullets) | B62: KES/bag | C62: 4500 | D62: 4200 | E62: 3900 | F62: BENCHMARK | G62: Chick mash 3,900 to 4,600 (Capital FM Nov 25); Sh4,940 Feb 2023 (The Star). Grower assumed between
A63: Egg transport and marketing | B63: % of egg revenue | C63: 0.04 | D63: 0.03 | E63: 0.02 | F63: ASSUMED
A64: Egg packaging/handling per tray of 30 | B64: KES/tray | C64: 25 | D64: 25 | E64: 25 | F64: ASSUMED
A65: Live-bird and spent-hen selling cost | B65: % of revenue | C65: 0.05 | D65: 0.04 | E65: 0.03 | F65: ASSUMED
A66: Brooding fuel/bedding per chick started | B66: KES/chick | C66: 20 | D66: 15 | E66: 12 | F66: ASSUMED | G66: New in v2: charcoal/gas/bedding for brooding
A67: Months of feed and drug stores on hand at start | B67: months | C67: 6 | D67: 6 | E67: 6 | F67: OWNER-REPORTED | G67: Owner: feed and drug stores last 6 months for each breed. Quantities not verified
A68: Poultry: Sasso
A69: Sasso: standing birds | B69: birds | C69: 500 | D69: 500 | E69: 500 | F69: OWNER-REPORTED | G69: Intake update 2 (poultry total 2,270 after coordinator arithmetic correction; intake file says 2,770). Age/production stage not stated
A70: Sasso: share of standing flock kept as laying hens | B70: % | C70: 0.4 | D70: 0.4 | E70: 0.4 | F70: ASSUMED | G70: Structure choice, not a forecast. Age/stage unknown. See Mix sheet for 0-100%. No breed-specific source found for Sasso/Kuroiler/Rainbow/Kebro; the four breeds carry IDENTICAL parameters until breed-level data are measured. Age/stage not stated by owner
A71: Sasso: eggs per hen per year | B71: eggs | C71: 110 | D71: 150 | E71: 180 | F71: ASSUMED | G71: Improved kienyeji semi-intensive; breeder claims higher, not verified
A72: Sasso: breakage/rejects | B72: % | C72: 0.04 | D72: 0.03 | E72: 0.025 | F72: ASSUMED
A73: Sasso: farm-gate price per egg | B73: KES/egg | C73: 12 | D73: 15 | E73: 18 | F73: BENCHMARK | G73: Indigenous egg retail Sh540-750/tray (Business Daily, ~2024), exotic Sh400-600; farm gate ~400/tray exotic (Nation); Nation ~Jul 2026 retail spot Sh504-720/tray. Base 450/tray = 25% haircut on indigenous retail floor
A74: Sasso: feed per laying hen per day (full ration) | B74: g | C74: 120 | D74: 110 | E74: 105 | F74: BENCHMARK | G74: Standard layer intake 110-120 g
A75: Sasso: share of hen ration supplied by forage/scavenging | B75: % | C75: 0.25 | D75: 0.35 | E75: 0.45 | F75: ASSUMED | G75: Depends on range, stocking density and season
A76: Sasso: hens culled per year (share of hen slots) | B76: % | C76: 0.8 | D76: 0.8 | E76: 0.8 | F76: ASSUMED | G76: About 15-month laying cycle
A77: Sasso: spent hen price | B77: KES/bird | C77: 300 | D77: 400 | E77: 500 | F77: ASSUMED | G77: v1 used 350 for exotic layers
A78: Sasso: hen mortality per year | B78: % | C78: 0.09 | D78: 0.07 | E78: 0.06 | F78: ASSUMED
A79: Sasso: rearing mortality of replacement chicks | B79: % | C79: 0.1 | D79: 0.08 | E79: 0.06 | F79: ASSUMED
A80: Sasso: feed per replacement pullet to point of lay (full ration) | B80: kg | C80: 11 | D80: 10 | E80: 9 | F80: ASSUMED
A81: Sasso: drugs/vaccines per laying hen per year | B81: KES/yr | C81: 120 | D81: 100 | E81: 80 | F81: ASSUMED | G81: Weekly vet visit fee is a separate line
A82: Sasso: grower batches per year per grower slot | B82: no. | C82: 1.8 | D82: 2 | E82: 2.4 | F82: ASSUMED | G82: About 5-month grow-out plus clean-out
A83: Sasso: mortality to sale (growers) | B83: % | C83: 0.16 | D83: 0.12 | E83: 0.09 | F83: ASSUMED
A84: Sasso: total feed per grower to sale (full ration) | B84: kg | C84: 12 | D84: 11 | E84: 10 | F84: ASSUMED | G84: Slow-growing improved kienyeji, FCR 3.5-4 to ~2.8 kg
A85: Sasso: share of grower ration supplied by forage/scavenging | B85: % | C85: 0.3 | D85: 0.4 | E85: 0.5 | F85: ASSUMED
A86: Sasso: farm-gate price per live bird | B86: KES/bird | C86: 650 | D86: 750 | E86: 850 | F86: BENCHMARK | G86: Mature kienyeji Sh900-1,500 retail (BeyondForest 2026), Sh600-1,200 dressed (Huduma 2026); farm-gate haircut applied (same as v1)
A87: Sasso: day-old chick cost | B87: KES | C87: 140 | D87: 120 | E87: 100 | F87: BENCHMARK | G87: Day-old improved kienyeji Sh90-140; Kenbro ~Sh115, Kenchic broiler ~Sh105 (BeyondForest 2025-26 guides). v1 used 170
A88: Sasso: drugs/vaccines per chick started | B88: KES | C88: 60 | D88: 40 | E88: 30 | F88: ASSUMED | G88: Vaccination programme; owner says birds already vaccinated
A89: Sasso: value per bird (capital) | B89: KES | C89: 500 | D89: 500 | E89: 500 | F89: ASSUMED
A90: Poultry: Kuroiler
A91: Kuroiler: standing birds | B91: birds | C91: 500 | D91: 500 | E91: 500 | F91: OWNER-REPORTED | G91: Intake update 2 (poultry total 2,270 after coordinator arithmetic correction; intake file says 2,770). Age/production stage not stated
A92: Kuroiler: share of standing flock kept as laying hens | B92: % | C92: 0.4 | D92: 0.4 | E92: 0.4 | F92: ASSUMED | G92: Structure choice, not a forecast. Age/stage unknown. See Mix sheet for 0-100%. No breed-specific source found for Sasso/Kuroiler/Rainbow/Kebro; the four breeds carry IDENTICAL parameters until breed-level data are measured. Age/stage not stated by owner
A93: Kuroiler: eggs per hen per year | B93: eggs | C93: 110 | D93: 150 | E93: 180 | F93: ASSUMED | G93: Improved kienyeji semi-intensive; breeder claims higher, not verified
A94: Kuroiler: breakage/rejects | B94: % | C94: 0.04 | D94: 0.03 | E94: 0.025 | F94: ASSUMED
A95: Kuroiler: farm-gate price per egg | B95: KES/egg | C95: 12 | D95: 15 | E95: 18 | F95: BENCHMARK | G95: Indigenous egg retail Sh540-750/tray (Business Daily, ~2024), exotic Sh400-600; farm gate ~400/tray exotic (Nation); Nation ~Jul 2026 retail spot Sh504-720/tray. Base 450/tray = 25% haircut on indigenous retail floor
A96: Kuroiler: feed per laying hen per day (full ration) | B96: g | C96: 120 | D96: 110 | E96: 105 | F96: BENCHMARK | G96: Standard layer intake 110-120 g
A97: Kuroiler: share of hen ration supplied by forage/scavenging | B97: % | C97: 0.25 | D97: 0.35 | E97: 0.45 | F97: ASSUMED | G97: Depends on range, stocking density and season
A98: Kuroiler: hens culled per year (share of hen slots) | B98: % | C98: 0.8 | D98: 0.8 | E98: 0.8 | F98: ASSUMED | G98: About 15-month laying cycle
A99: Kuroiler: spent hen price | B99: KES/bird | C99: 300 | D99: 400 | E99: 500 | F99: ASSUMED | G99: v1 used 350 for exotic layers
A100: Kuroiler: hen mortality per year | B100: % | C100: 0.09 | D100: 0.07 | E100: 0.06 | F100: ASSUMED
...

Sheet Cattle
A1: Cattle (annual, KES). All cells are live formulas from Inputs.
A2: Line | B2: Unit | C2: Low (adverse) | D2: Base | E2: High (favourable) | F2: Base in USD | G2: Note
A3: Production
A4: Milk sold | B4: L/yr | C4: =Inputs!C27*Inputs!C28*Inputs!C29 -> 8120 | D4: =Inputs!D27*Inputs!D28*Inputs!D29 -> 9600 | E4: =Inputs!E27*Inputs!E28*Inputs!E29 -> 13725
A5: Revenue
A6: Milk revenue | B6: KES | C6: =C4*Inputs!C30 -> 276080 | D6: =D4*Inputs!D30 -> 364800 | E6: =E4*Inputs!E30 -> 576450 | F6: =D6/Inputs!$D$4 -> 2808.5303
A7: Cattle sales | B7: KES | C7: =Inputs!C37*Inputs!C38 -> 32000 | D7: =Inputs!D37*Inputs!D38 -> 80000 | E7: =Inputs!E37*Inputs!E38 -> 100000 | F7: =D7/Inputs!$D$4 -> 615.90577
A8: Total revenue | B8: KES | C8: =C6+C7 -> 308080 | D8: =D6+D7 -> 444800 | E8: =E6+E7 -> 676450 | F8: =D8/Inputs!$D$4 -> 3424.4361
A9: Variable costs
A10: Dairy meal | B10: KES | C10: =Inputs!C27*Inputs!C32*Inputs!C29*Inputs!C33 -> 194880 | D10: =Inputs!D27*Inputs!D32*Inputs!D29*Inputs!D33 -> 187200 | E10: =Inputs!E27*Inputs!E32*Inputs!E29*Inputs!E33 -> 219600 | F10: =D10/Inputs!$D$4 -> 1441.2195
A11: Purchased forage | B11: KES | C11: =Inputs!C20*Inputs!C34 -> 40000 | D11: =Inputs!D20*Inputs!D34 -> 30000 | E11: =Inputs!E20*Inputs!E34 -> 20000 | F11: =D11/Inputs!$D$4 -> 230.96466
A12: Minerals | B12: KES | C12: =Inputs!C20*Inputs!C35 -> 18000 | D12: =Inputs!D20*Inputs!D35 -> 18000 | E12: =Inputs!E20*Inputs!E35 -> 18000 | F12: =D12/Inputs!$D$4 -> 138.5788
A13: Drugs, AI, acaricide | B13: KES | C13: =Inputs!C20*Inputs!C36 -> 70000 | D13: =Inputs!D20*Inputs!D36 -> 60000 | E13: =Inputs!E20*Inputs!E36 -> 50000 | F13: =D13/Inputs!$D$4 -> 461.92932
A14: Milk cooling, transport, levies | B14: KES | C14: =C4*Inputs!C31 -> 24360 | D14: =D4*Inputs!D31 -> 24000 | E14: =E4*Inputs!E31 -> 27450 | F14: =D14/Inputs!$D$4 -> 184.77173
A15: Mortality/loss allowance | B15: KES | C15: =Inputs!C20*Inputs!C40*Inputs!C39 -> 24000 | D15: =Inputs!D20*Inputs!D40*Inputs!D39 -> 18000 | E15: =Inputs!E20*Inputs!E40*Inputs!E39 -> 12000 | F15: =D15/Inputs!$D$4 -> 138.5788
A16: Total variable costs | B16: KES | C16: =SUM(C10:C15) -> 371240 | D16: =SUM(D10:D15) -> 337200 | E16: =SUM(E10:E15) -> 347050 | F16: =D16/Inputs!$D$4 -> 2596.0428
A17: Gross margin (before labour and fixed costs) | B17: KES | C17: =C8-C16 -> -63160 | D17: =D8-D16 -> 107600 | E17: =E8-E16 -> 329400 | F17: =D17/Inputs!$D$4 -> 828.39326
A18: Gross margin per head | B18: KES/head | C18: =C17/Inputs!C20 -> -6316 | D18: =D17/Inputs!D20 -> 10760 | E18: =E17/Inputs!E20 -> 32940
A19: Stock capital | B19: KES | C19: =Inputs!C20*Inputs!C40 -> 600000 | D19: =Inputs!D20*Inputs!D40 -> 600000 | E19: =Inputs!E20*Inputs!E40 -> 600000 | F19: =D19/Inputs!$D$4 -> 4619.2932
A20: Memo: purchased feed and forage | B20: KES | C20: =C10+C11 -> 234880 | D20: =D10+D11 -> 217200 | E20: =E10+E11 -> 239600 | F20: =D20/Inputs!$D$4 -> 1672.1842
A21: Memo: drugs and vet inputs | B21: KES | C21: =C13 -> 70000 | D21: =D13 -> 60000 | E21: =E13 -> 50000 | F21: =D21/Inputs!$D$4 -> 461.92932

Sheet Sheep
A1: Sheep (annual, KES). All cells are live formulas from Inputs.
A2: Line | B2: Unit | C2: Low (adverse) | D2: Base | E2: High (favourable) | F2: Base in USD | G2: Note
A3: Production
A4: Lambs/hoggets sold (weaned less replacements) | B4: head | C4: =MAX(0,Inputs!C42*(Inputs!C43-Inputs!C44)) -> 24.8 | D4: =MAX(0,Inputs!D42*(Inputs!D43-Inputs!D44)) -> 34 | E4: =MAX(0,Inputs!E42*(Inputs!E43-Inputs!E44)) -> 43.2
A5: Sale price per head | B5: KES | C5: =Inputs!C45*Inputs!C46 -> 5670 | D5: =Inputs!D45*Inputs!D46 -> 6720 | E5: =Inputs!E45*Inputs!E46 -> 8120 | F5: =D5/Inputs!$D$4 -> 51.736084
A6: Revenue
A7: Sales revenue | B7: KES | C7: =C4*C5 -> 140616 | D7: =D4*D5 -> 228480 | E7: =E4*E5 -> 350784 | F7: =D7/Inputs!$D$4 -> 1759.0269
A8: Variable costs
A9: Supplement/feed | B9: KES | C9: =Inputs!C21*Inputs!C47 -> 60000 | D9: =Inputs!D21*Inputs!D47 -> 50000 | E9: =Inputs!E21*Inputs!E47 -> 40000 | F9: =D9/Inputs!$D$4 -> 384.9411
A10: Drugs, deworm, dip, vaccines | B10: KES | C10: =Inputs!C21*Inputs!C48 -> 45000 | D10: =Inputs!D21*Inputs!D48 -> 40000 | E10: =Inputs!E21*Inputs!E48 -> 35000 | F10: =D10/Inputs!$D$4 -> 307.95288
A11: Minerals | B11: KES | C11: =Inputs!C21*Inputs!C49 -> 10000 | D11: =Inputs!D21*Inputs!D49 -> 10000 | E11: =Inputs!E21*Inputs!E49 -> 10000 | F11: =D11/Inputs!$D$4 -> 76.988221
A12: Selling cost | B12: KES | C12: =C7*Inputs!C50 -> 8436.96 | D12: =D7*Inputs!D50 -> 9139.2 | E12: =E7*Inputs!E50 -> 10523.52 | F12: =D12/Inputs!$D$4 -> 70.361075
A13: Total variable costs | B13: KES | C13: =SUM(C9:C12) -> 123436.96 | D13: =SUM(D9:D12) -> 109139.2 | E13: =SUM(E9:E12) -> 95523.52 | F13: =D13/Inputs!$D$4 -> 840.24328
A14: Gross margin | B14: KES | C14: =C7-C13 -> 17179.04 | D14: =D7-D13 -> 119340.8 | E14: =E7-E13 -> 255260.48 | F14: =D14/Inputs!$D$4 -> 918.78359
A15: Gross margin per head | B15: KES/head | C15: =C14/Inputs!C21 -> 343.5808 | D15: =D14/Inputs!D21 -> 2386.816 | E15: =E14/Inputs!E21 -> 5105.2096
A16: Stock capital | B16: KES | C16: =Inputs!C21*Inputs!C51 -> 300000 | D16: =Inputs!D21*Inputs!D51 -> 300000 | E16: =Inputs!E21*Inputs!E51 -> 300000 | F16: =D16/Inputs!$D$4 -> 2309.6466
A17: Memo: purchased feed | B17: KES | C17: =C9 -> 60000 | D17: =D9 -> 50000 | E17: =E9 -> 40000 | F17: =D17/Inputs!$D$4 -> 384.9411
A18: Memo: drugs and vet inputs | B18: KES | C18: =C10 -> 45000 | D18: =D10 -> 40000 | E18: =E10 -> 35000 | F18: =D18/Inputs!$D$4 -> 307.95288

Sheet Goats
A1: Goats (annual, KES). All cells are live formulas from Inputs.
A2: Line | B2: Unit | C2: Low (adverse) | D2: Base | E2: High (favourable) | F2: Base in USD | G2: Note
A3: Production
A4: Kids sold (weaned less replacements) | B4: head | C4: =MAX(0,Inputs!C53*(Inputs!C54-Inputs!C55)) -> 7.84 | D4: =MAX(0,Inputs!D53*(Inputs!D54-Inputs!D55)) -> 9.6 | E4: =MAX(0,Inputs!E53*(Inputs!E54-Inputs!E55)) -> 11.36
A5: Sale price per head | B5: KES | C5: =Inputs!C56*Inputs!C57 -> 5500 | D5: =Inputs!D56*Inputs!D57 -> 6500 | E5: =Inputs!E56*Inputs!E57 -> 7830 | F5: =D5/Inputs!$D$4 -> 50.042344
A6: Revenue
A7: Sales revenue | B7: KES | C7: =C4*C5 -> 43120 | D7: =D4*D5 -> 62400 | E7: =E4*E5 -> 88948.8 | F7: =D7/Inputs!$D$4 -> 480.4065
A8: Variable costs
A9: Supplement/feed | B9: KES | C9: =Inputs!C22*Inputs!C58 -> 12000 | D9: =Inputs!D22*Inputs!D58 -> 10000 | E9: =Inputs!E22*Inputs!E58 -> 8000 | F9: =D9/Inputs!$D$4 -> 76.988221
A10: Drugs, deworm, vaccines | B10: KES | C10: =Inputs!C22*Inputs!C48 -> 9000 | D10: =Inputs!D22*Inputs!D48 -> 8000 | E10: =Inputs!E22*Inputs!E48 -> 7000 | F10: =D10/Inputs!$D$4 -> 61.590577
A11: Minerals | B11: KES | C11: =Inputs!C22*Inputs!C49 -> 2000 | D11: =Inputs!D22*Inputs!D49 -> 2000 | E11: =Inputs!E22*Inputs!E49 -> 2000 | F11: =D11/Inputs!$D$4 -> 15.397644
A12: Selling cost | B12: KES | C12: =C7*Inputs!C50 -> 2587.2 | D12: =D7*Inputs!D50 -> 2496 | E12: =E7*Inputs!E50 -> 2668.464 | F12: =D12/Inputs!$D$4 -> 19.21626
A13: Total variable costs | B13: KES | C13: =SUM(C9:C12) -> 25587.2 | D13: =SUM(D9:D12) -> 22496 | E13: =SUM(E9:E12) -> 19668.464 | F13: =D13/Inputs!$D$4 -> 173.1927
A14: Gross margin | B14: KES | C14: =C7-C13 -> 17532.8 | D14: =D7-D13 -> 39904 | E14: =E7-E13 -> 69280.336 | F14: =D14/Inputs!$D$4 -> 307.2138
A15: Gross margin per head | B15: KES/head | C15: =C14/Inputs!C22 -> 1753.28 | D15: =D14/Inputs!D22 -> 3990.4 | E15: =E14/Inputs!E22 -> 6928.0336
A16: Stock capital | B16: KES | C16: =Inputs!C22*Inputs!C59 -> 65000 | D16: =Inputs!D22*Inputs!D59 -> 65000 | E16: =Inputs!E22*Inputs!E59 -> 65000 | F16: =D16/Inputs!$D$4 -> 500.42344
A17: Memo: purchased feed | B17: KES | C17: =C9 -> 12000 | D17: =D9 -> 10000 | E17: =E9 -> 8000 | F17: =D17/Inputs!$D$4 -> 76.988221
A18: Memo: drugs and vet inputs | B18: KES | C18: =C10 -> 9000 | D18: =D10 -> 8000 | E18: =E10 -> 7000 | F18: =D18/Inputs!$D$4 -> 61.590577

Sheet Poultry
A1: Poultry (annual, KES). All cells are live formulas from Inputs.
A2: Line | B2: Unit | C2: Low (adverse) | D2: Base | E2: High (favourable) | F2: Base in USD | G2: Note
A3: Sasso
A4: Standing birds | B4: birds | C4: =Inputs!C69 -> 500 | D4: =Inputs!D69 -> 500 | E4: =Inputs!E69 -> 500
A5: Laying hens (hen slots) | B5: birds | C5: =Inputs!C69*Inputs!C70 -> 200 | D5: =Inputs!D69*Inputs!D70 -> 200 | E5: =Inputs!E69*Inputs!E70 -> 200
A6: Grower slots | B6: birds | C6: =Inputs!C69-C5 -> 300 | D6: =Inputs!D69-D5 -> 300 | E6: =Inputs!E69-E5 -> 300
A7: Saleable eggs | B7: eggs/yr | C7: =C5*Inputs!C71*(1-Inputs!C72) -> 21120 | D7: =D5*Inputs!D71*(1-Inputs!D72) -> 29100 | E7: =E5*Inputs!E71*(1-Inputs!E72) -> 35100
A8: Egg revenue | B8: KES | C8: =C7*Inputs!C73 -> 253440 | D8: =D7*Inputs!D73 -> 436500 | E8: =E7*Inputs!E73 -> 631800 | F8: =D8/Inputs!$D$4 -> 3360.5358
A9: Spent hens sold | B9: birds | C9: =C5*Inputs!C76 -> 160 | D9: =D5*Inputs!D76 -> 160 | E9: =E5*Inputs!E76 -> 160
A10: Spent hen revenue | B10: KES | C10: =C9*Inputs!C77 -> 48000 | D10: =D9*Inputs!D77 -> 64000 | E10: =E9*Inputs!E77 -> 80000 | F10: =D10/Inputs!$D$4 -> 492.72461
A11: Grower birds started per year | B11: birds | C11: =C6*Inputs!C82 -> 540 | D11: =D6*Inputs!D82 -> 600 | E11: =E6*Inputs!E82 -> 720
A12: Grower birds sold | B12: birds | C12: =C11*(1-Inputs!C83) -> 453.6 | D12: =D11*(1-Inputs!D83) -> 528 | E12: =E11*(1-Inputs!E83) -> 655.2
A13: Live-bird revenue | B13: KES | C13: =C12*Inputs!C86 -> 294840 | D13: =D12*Inputs!D86 -> 396000 | E13: =E12*Inputs!E86 -> 556920 | F13: =D13/Inputs!$D$4 -> 3048.7335
A14: Total revenue | B14: KES | C14: =C8+C10+C13 -> 596280 | D14: =D8+D10+D13 -> 896500 | E14: =E8+E10+E13 -> 1268720 | F14: =D14/Inputs!$D$4 -> 6901.994
A15: Replacement pullets needed (culls + deaths) | B15: birds | C15: =C5*(Inputs!C76+Inputs!C78) -> 178 | D15: =D5*(Inputs!D76+Inputs!D78) -> 174 | E15: =E5*(Inputs!E76+Inputs!E78) -> 172
A16: Replacement chicks bought (allowing rearing mortality) | B16: birds | C16: =C15/(1-Inputs!C79) -> 197.77778 | D16: =D15/(1-Inputs!D79) -> 189.13043 | E16: =E15/(1-Inputs!E79) -> 182.97872
A17: Chicks bought (replacements + growers) | B17: KES | C17: =(C16+C11)*Inputs!C87 -> 103288.89 | D17: =(D16+D11)*Inputs!D87 -> 94695.652 | E17: =(E16+E11)*Inputs!E87 -> 90297.872 | F17: =D17/Inputs!$D$4 -> 729.04498
A18: Feed: laying hens | B18: KES | C18: =C5*Inputs!C74/1000*365*(1-Inputs!C75)*Inputs!C61/70 -> 403585.71 | D18: =D5*Inputs!D74/1000*365*(1-Inputs!D75)*Inputs!D61/70 -> 290800.71 | E18: =E5*Inputs!E74/1000*365*(1-Inputs!E75)*Inputs!E61/70 -> 216810 | F18: =D18/Inputs!$D$4 -> 2238.823
A19: Feed: replacement pullets | B19: KES | C19: =C16*Inputs!C80*(1-Inputs!C85)*Inputs!C62/70 -> 97900 | D19: =D16*Inputs!D80*(1-Inputs!D85)*Inputs!D62/70 -> 68086.957 | E19: =E16*Inputs!E80*(1-Inputs!E85)*Inputs!E62/70 -> 45875.38 | F19: =D19/Inputs!$D$4 -> 524.18936
A20: Feed: growers | B20: KES | C20: =C11*Inputs!C84*(1-Inputs!C85)*Inputs!C62/70 -> 291600 | D20: =D11*Inputs!D84*(1-Inputs!D85)*Inputs!D62/70 -> 237600 | E20: =E11*Inputs!E84*(1-Inputs!E85)*Inputs!E62/70 -> 200571.43 | F20: =D20/Inputs!$D$4 -> 1829.2401
A21: Drugs and vaccines | B21: KES | C21: =C5*Inputs!C81+(C16+C11)*Inputs!C88 -> 68266.667 | D21: =D5*Inputs!D81+(D16+D11)*Inputs!D88 -> 51565.217 | E21: =E5*Inputs!E81+(E16+E11)*Inputs!E88 -> 43089.362 | F21: =D21/Inputs!$D$4 -> 396.99143
A22: Brooding fuel and bedding | B22: KES | C22: =(C16+C11)*Inputs!C66 -> 14755.556 | D22: =(D16+D11)*Inputs!D66 -> 11836.957 | E22: =(E16+E11)*Inputs!E66 -> 10835.745 | F22: =D22/Inputs!$D$4 -> 91.130622
A23: Egg packaging | B23: KES | C23: =C7/30*Inputs!C64 -> 17600 | D23: =D7/30*Inputs!D64 -> 24250 | E23: =E7/30*Inputs!E64 -> 29250 | F23: =D23/Inputs!$D$4 -> 186.69644
A24: Selling costs | B24: KES | C24: =C8*Inputs!C63+(C10+C13)*Inputs!C65 -> 27279.6 | D24: =D8*Inputs!D63+(D10+D13)*Inputs!D65 -> 31495 | E24: =E8*Inputs!E63+(E10+E13)*Inputs!E65 -> 31743.6 | F24: =D24/Inputs!$D$4 -> 242.4744
A25: Total variable costs | B25: KES | C25: =C17+C18+C19+C20+C21+C22+C23+C24 -> 1024276.4 | D25: =D17+D18+D19+D20+D21+D22+D23+D24 -> 810330.5 | E25: =E17+E18+E19+E20+E21+E22+E23+E24 -> 668473.39 | F25: =D25/Inputs!$D$4 -> 6238.5903
A26: Gross margin | B26: KES | C26: =C14-C25 -> -427996.43 | D26: =D14-D25 -> 86169.503 | E26: =E14-E25 -> 600246.61 | F26: =D26/Inputs!$D$4 -> 663.40367
A27: Gross margin per standing bird | B27: KES/bird | C27: =C26/C4 -> -855.99285 | D27: =D26/D4 -> 172.33901 | E27: =E26/E4 -> 1200.4932
A28: Unit margin per hen slot (per year) | B28: KES/bird | C28: =Inputs!C71*(1-Inputs!C72)*(Inputs!C73*(1-Inputs!C63)-Inputs!C64/30)+Inputs!C76*Inputs!C77*(1-Inputs!C65)-(Inputs!C76+Inputs!C78)/(1-Inputs!C79)*(Inputs!C87+Inputs!C66+Inputs!C88+Inputs!C80*(1-Inputs!C85)*Inputs!C62/70)-Inputs!C74/1000*365*(1-Inputs!C75)*Inputs!C61/70-Inputs!C81 -> -1488.4721 | D28: =Inputs!D71*(1-Inputs!D72)*(Inputs!D73*(1-Inputs!D63)-Inputs!D64/30)+Inputs!D76*Inputs!D77*(1-Inputs!D65)-(Inputs!D76+Inputs!D78)/(1-Inputs!D79)*(Inputs!D87+Inputs!D66+Inputs!D88+Inputs!D80*(1-Inputs!D85)*Inputs!D62/70)-Inputs!D74/1000*365*(1-Inputs!D75)*Inputs!D61/70-Inputs!D81 -> 243.04752 | E28: =Inputs!E71*(1-Inputs!E72)*(Inputs!E73*(1-Inputs!E63)-Inputs!E64/30)+Inputs!E76*Inputs!E77*(1-Inputs!E65)-(Inputs!E76+Inputs!E78)/(1-Inputs!E79)*(Inputs!E87+Inputs!E66+Inputs!E88+Inputs!E80*(1-Inputs!E85)*Inputs!E62/70)-Inputs!E74/1000*365*(1-Inputs!E75)*Inputs!E61/70-Inputs!E81 -> 1814.2282
A29: Unit margin per grower slot (per year) | B29: KES/bird | C29: =Inputs!C82*((1-Inputs!C83)*Inputs!C86*(1-Inputs!C65)-Inputs!C87-Inputs!C66-Inputs!C88-Inputs!C84*(1-Inputs!C85)*Inputs!C62/70) -> -434.34 | D29: =Inputs!D82*((1-Inputs!D83)*Inputs!D86*(1-Inputs!D65)-Inputs!D87-Inputs!D66-Inputs!D88-Inputs!D84*(1-Inputs!D85)*Inputs!D62/70) -> 125.2 | E29: =Inputs!E82*((1-Inputs!E83)*Inputs!E86*(1-Inputs!E65)-Inputs!E87-Inputs!E66-Inputs!E88-Inputs!E84*(1-Inputs!E85)*Inputs!E62/70) -> 791.33657
A30: Check: slot margins reproduce gross margin (should be 0) | B30: KES | C30: =C26-(C5*C28+C6*C29) -> 0 | D30: =D26-(D5*D28+D6*D29) -> 0 | E30: =E26-(E5*E28+E6*E29) -> 0 | F30: =D30/Inputs!$D$4 -> 0
A31: Stock capital | B31: KES | C31: =Inputs!C69*Inputs!C89 -> 250000 | D31: =Inputs!D69*Inputs!D89 -> 250000 | E31: =Inputs!E69*Inputs!E89 -> 250000 | F31: =D31/Inputs!$D$4 -> 1924.7055
A32: Memo: purchased feed | B32: KES | C32: =C18+C19+C20 -> 793085.71 | D32: =D18+D19+D20 -> 596487.67 | E32: =E18+E19+E20 -> 463256.81 | F32: =D32/Inputs!$D$4 -> 4592.2525
A33: Kuroiler
A34: Standing birds | B34: birds | C34: =Inputs!C91 -> 500 | D34: =Inputs!D91 -> 500 | E34: =Inputs!E91 -> 500
A35: Laying hens (hen slots) | B35: birds | C35: =Inputs!C91*Inputs!C92 -> 200 | D35: =Inputs!D91*Inputs!D92 -> 200 | E35: =Inputs!E91*Inputs!E92 -> 200
A36: Grower slots | B36: birds | C36: =Inputs!C91-C35 -> 300 | D36: =Inputs!D91-D35 -> 300 | E36: =Inputs!E91-E35 -> 300
A37: Saleable eggs | B37: eggs/yr | C37: =C35*Inputs!C93*(1-Inputs!C94) -> 21120 | D37: =D35*Inputs!D93*(1-Inputs!D94) -> 29100 | E37: =E35*Inputs!E93*(1-Inputs!E94) -> 35100
A38: Egg revenue | B38: KES | C38: =C37*Inputs!C95 -> 253440 | D38: =D37*Inputs!D95 -> 436500 | E38: =E37*Inputs!E95 -> 631800 | F38: =D38/Inputs!$D$4 -> 3360.5358
A39: Spent hens sold | B39: birds | C39: =C35*Inputs!C98 -> 160 | D39: =D35*Inputs!D98 -> 160 | E39: =E35*Inputs!E98 -> 160
A40: Spent hen revenue | B40: KES | C40: =C39*Inputs!C99 -> 48000 | D40: =D39*Inputs!D99 -> 64000 | E40: =E39*Inputs!E99 -> 80000 | F40: =D40/Inputs!$D$4 -> 492.72461
A41: Grower birds started per year | B41: birds | C41: =C36*Inputs!C104 -> 540 | D41: =D36*Inputs!D104 -> 600 | E41: =E36*Inputs!E104 -> 720
A42: Grower birds sold | B42: birds | C42: =C41*(1-Inputs!C105) -> 453.6 | D42: =D41*(1-Inputs!D105) -> 528 | E42: =E41*(1-Inputs!E105) -> 655.2
A43: Live-bird revenue | B43: KES | C43: =C42*Inputs!C108 -> 294840 | D43: =D42*Inputs!D108 -> 396000 | E43: =E42*Inputs!E108 -> 556920 | F43: =D43/Inputs!$D$4 -> 3048.7335
A44: Total revenue | B44: KES | C44: =C38+C40+C43 -> 596280 | D44: =D38+D40+D43 -> 896500 | E44: =E38+E40+E43 -> 1268720 | F44: =D44/Inputs!$D$4 -> 6901.994
A45: Replacement pullets needed (culls + deaths) | B45: birds | C45: =C35*(Inputs!C98+Inputs!C100) -> 178 | D45: =D35*(Inputs!D98+Inputs!D100) -> 174 | E45: =E35*(Inputs!E98+Inputs!E100) -> 172
A46: Replacement chicks bought (allowing rearing mortality) | B46: birds | C46: =C45/(1-Inputs!C101) -> 197.77778 | D46: =D45/(1-Inputs!D101) -> 189.13043 | E46: =E45/(1-Inputs!E101) -> 182.97872
A47: Chicks bought (replacements + growers) | B47: KES | C47: =(C46+C41)*Inputs!C109 -> 103288.89 | D47: =(D46+D41)*Inputs!D109 -> 94695.652 | E47: =(E46+E41)*Inputs!E109 -> 90297.872 | F47: =D47/Inputs!$D$4 -> 729.04498
A48: Feed: laying hens | B48: KES | C48: =C35*Inputs!C96/1000*365*(1-Inputs!C97)*Inputs!C61/70 -> 403585.71 | D48: =D35*Inputs!D96/1000*365*(1-Inputs!D97)*Inputs!D61/70 -> 290800.71 | E48: =E35*Inputs!E96/1000*365*(1-Inputs!E97)*Inputs!E61/70 -> 216810 | F48: =D48/Inputs!$D$4 -> 2238.823
A49: Feed: replacement pullets | B49: KES | C49: =C46*Inputs!C102*(1-Inputs!C107)*Inputs!C62/70 -> 97900 | D49: =D46*Inputs!D102*(1-Inputs!D107)*Inputs!D62/70 -> 68086.957 | E49: =E46*Inputs!E102*(1-Inputs!E107)*Inputs!E62/70 -> 45875.38 | F49: =D49/Inputs!$D$4 -> 524.18936
A50: Feed: growers | B50: KES | C50: =C41*Inputs!C106*(1-Inputs!C107)*Inputs!C62/70 -> 291600 | D50: =D41*Inputs!D106*(1-Inputs!D107)*Inputs!D62/70 -> 237600 | E50: =E41*Inputs!E106*(1-Inputs!E107)*Inputs!E62/70 -> 200571.43 | F50: =D50/Inputs!$D$4 -> 1829.2401
A51: Drugs and vaccines | B51: KES | C51: =C35*Inputs!C103+(C46+C41)*Inputs!C110 -> 68266.667 | D51: =D35*Inputs!D103+(D46+D41)*Inputs!D110 -> 51565.217 | E51: =E35*Inputs!E103+(E46+E41)*Inputs!E110 -> 43089.362 | F51: =D51/Inputs!$D$4 -> 396.99143
A52: Brooding fuel and bedding | B52: KES | C52: =(C46+C41)*Inputs!C66 -> 14755.556 | D52: =(D46+D41)*Inputs!D66 -> 11836.957 | E52: =(E46+E41)*Inputs!E66 -> 10835.745 | F52: =D52/Inputs!$D$4 -> 91.130622
A53: Egg packaging | B53: KES | C53: =C37/30*Inputs!C64 -> 17600 | D53: =D37/30*Inputs!D64 -> 24250 | E53: =E37/30*Inputs!E64 -> 29250 | F53: =D53/Inputs!$D$4 -> 186.69644
A54: Selling costs | B54: KES | C54: =C38*Inputs!C63+(C40+C43)*Inputs!C65 -> 27279.6 | D54: =D38*Inputs!D63+(D40+D43)*Inputs!D65 -> 31495 | E54: =E38*Inputs!E63+(E40+E43)*Inputs!E65 -> 31743.6 | F54: =D54/Inputs!$D$4 -> 242.4744
A55: Total variable costs | B55: KES | C55: =C47+C48+C49+C50+C51+C52+C53+C54 -> 1024276.4 | D55: =D47+D48+D49+D50+D51+D52+D53+D54 -> 810330.5 | E55: =E47+E48+E49+E50+E51+E52+E53+E54 -> 668473.39 | F55: =D55/Inputs!$D$4 -> 6238.5903
A56: Gross margin | B56: KES | C56: =C44-C55 -> -427996.43 | D56: =D44-D55 -> 86169.503 | E56: =E44-E55 -> 600246.61 | F56: =D56/Inputs!$D$4 -> 663.40367
A57: Gross margin per standing bird | B57: KES/bird | C57: =C56/C34 -> -855.99285 | D57: =D56/D34 -> 172.33901 | E57: =E56/E34 -> 1200.4932
A58: Unit margin per hen slot (per year) | B58: KES/bird | C58: =Inputs!C93*(1-Inputs!C94)*(Inputs!C95*(1-Inputs!C63)-Inputs!C64/30)+Inputs!C98*Inputs!C99*(1-Inputs!C65)-(Inputs!C98+Inputs!C100)/(1-Inputs!C101)*(Inputs!C109+Inputs!C66+Inputs!C110+Inputs!C102*(1-Inputs!C107)*Inputs!C62/70)-Inputs!C96/1000*365*(1-Inputs!C97)*Inputs!C61/70-Inputs!C103 -> -1488.4721 | D58: =Inputs!D93*(1-Inputs!D94)*(Inputs!D95*(1-Inputs!D63)-Inputs!D64/30)+Inputs!D98*Inputs!D99*(1-Inputs!D65)-(Inputs!D98+Inputs!D100)/(1-Inputs!D101)*(Inputs!D109+Inputs!D66+Inputs!D110+Inputs!D102*(1-Inputs!D107)*Inputs!D62/70)-Inputs!D96/1000*365*(1-Inputs!D97)*Inputs!D61/70-Inputs!D103 -> 243.04752 | E58: =Inputs!E93*(1-Inputs!E94)*(Inputs!E95*(1-Inputs!E63)-Inputs!E64/30)+Inputs!E98*Inputs!E99*(1-Inputs!E65)-(Inputs!E98+Inputs!E100)/(1-Inputs!E101)*(Inputs!E109+Inputs!E66+Inputs!E110+Inputs!E102*(1-Inputs!E107)*Inputs!E62/70)-Inputs!E96/1000*365*(1-Inputs!E97)*Inputs!E61/70-Inputs!E103 -> 1814.2282
A59: Unit margin per grower slot (per year) | B59: KES/bird | C59: =Inputs!C104*((1-Inputs!C105)*Inputs!C108*(1-Inputs!C65)-Inputs!C109-Inputs!C66-Inputs!C110-Inputs!C106*(1-Inputs!C107)*Inputs!C62/70) -> -434.34 | D59: =Inputs!D104*((1-Inputs!D105)*Inputs!D108*(1-Inputs!D65)-Inputs!D109-Inputs!D66-Inputs!D110-Inputs!D106*(1-Inputs!D107)*Inputs!D62/70) -> 125.2 | E59: =Inputs!E104*((1-Inputs!E105)*Inputs!E108*(1-Inputs!E65)-Inputs!E109-Inputs!E66-Inputs!E110-Inputs!E106*(1-Inputs!E107)*Inputs!E62/70) -> 791.33657
A60: Check: slot margins reproduce gross margin (should be 0) | B60: KES | C60: =C56-(C35*C58+C36*C59) -> 0 | D60: =D56-(D35*D58+D36*D59) -> 0 | E60: =E56-(E35*E58+E36*E59) -> 0 | F60: =D60/Inputs!$D$4 -> 0
A61: Stock capital | B61: KES | C61: =Inputs!C91*Inputs!C111 -> 250000 | D61: =Inputs!D91*Inputs!D111 -> 250000 | E61: =Inputs!E91*Inputs!E111 -> 250000 | F61: =D61/Inputs!$D$4 -> 1924.7055
A62: Memo: purchased feed | B62: KES | C62: =C48+C49+C50 -> 793085.71 | D62: =D48+D49+D50 -> 596487.67 | E62: =E48+E49+E50 -> 463256.81 | F62: =D62/Inputs!$D$4 -> 4592.2525
A63: Rainbow
A64: Standing birds | B64: birds | C64: =Inputs!C113 -> 500 | D64: =Inputs!D113 -> 500 | E64: =Inputs!E113 -> 500
A65: Laying hens (hen slots) | B65: birds | C65: =Inputs!C113*Inputs!C114 -> 200 | D65: =Inputs!D113*Inputs!D114 -> 200 | E65: =Inputs!E113*Inputs!E114 -> 200
A66: Grower slots | B66: birds | C66: =Inputs!C113-C65 -> 300 | D66: =Inputs!D113-D65 -> 300 | E66: =Inputs!E113-E65 -> 300
A67: Saleable eggs | B67: eggs/yr | C67: =C65*Inputs!C115*(1-Inputs!C116) -> 21120 | D67: =D65*Inputs!D115*(1-Inputs!D116) -> 29100 | E67: =E65*Inputs!E115*(1-Inputs!E116) -> 35100
A68: Egg revenue | B68: KES | C68: =C67*Inputs!C117 -> 253440 | D68: =D67*Inputs!D117 -> 436500 | E68: =E67*Inputs!E117 -> 631800 | F68: =D68/Inputs!$D$4 -> 3360.5358
A69: Spent hens sold | B69: birds | C69: =C65*Inputs!C120 -> 160 | D69: =D65*Inputs!D120 -> 160 | E69: =E65*Inputs!E120 -> 160
A70: Spent hen revenue | B70: KES | C70: =C69*Inputs!C121 -> 48000 | D70: =D69*Inputs!D121 -> 64000 | E70: =E69*Inputs!E121 -> 80000 | F70: =D70/Inputs!$D$4 -> 492.72461
A71: Grower birds started per year | B71: birds | C71: =C66*Inputs!C126 -> 540 | D71: =D66*Inputs!D126 -> 600 | E71: =E66*Inputs!E126 -> 720
A72: Grower birds sold | B72: birds | C72: =C71*(1-Inputs!C127) -> 453.6 | D72: =D71*(1-Inputs!D127) -> 528 | E72: =E71*(1-Inputs!E127) -> 655.2
A73: Live-bird revenue | B73: KES | C73: =C72*Inputs!C130 -> 294840 | D73: =D72*Inputs!D130 -> 396000 | E73: =E72*Inputs!E130 -> 556920 | F73: =D73/Inputs!$D$4 -> 3048.7335
A74: Total revenue | B74: KES | C74: =C68+C70+C73 -> 596280 | D74: =D68+D70+D73 -> 896500 | E74: =E68+E70+E73 -> 1268720 | F74: =D74/Inputs!$D$4 -> 6901.994
A75: Replacement pullets needed (culls + deaths) | B75: birds | C75: =C65*(Inputs!C120+Inputs!C122) -> 178 | D75: =D65*(Inputs!D120+Inputs!D122) -> 174 | E75: =E65*(Inputs!E120+Inputs!E122) -> 172
A76: Replacement chicks bought (allowing rearing mortality) | B76: birds | C76: =C75/(1-Inputs!C123) -> 197.77778 | D76: =D75/(1-Inputs!D123) -> 189.13043 | E76: =E75/(1-Inputs!E123) -> 182.97872
A77: Chicks bought (replacements + growers) | B77: KES | C77: =(C76+C71)*Inputs!C131 -> 103288.89 | D77: =(D76+D71)*Inputs!D131 -> 94695.652 | E77: =(E76+E71)*Inputs!E131 -> 90297.872 | F77: =D77/Inputs!$D$4 -> 729.04498
A78: Feed: laying hens | B78: KES | C78: =C65*Inputs!C118/1000*365*(1-Inputs!C119)*Inputs!C61/70 -> 403585.71 | D78: =D65*Inputs!D118/1000*365*(1-Inputs!D119)*Inputs!D61/70 -> 290800.71 | E78: =E65*Inputs!E118/1000*365*(1-Inputs!E119)*Inputs!E61/70 -> 216810 | F78: =D78/Inputs!$D$4 -> 2238.823
A79: Feed: replacement pullets | B79: KES | C79: =C76*Inputs!C124*(1-Inputs!C129)*Inputs!C62/70 -> 97900 | D79: =D76*Inputs!D124*(1-Inputs!D129)*Inputs!D62/70 -> 68086.957 | E79: =E76*Inputs!E124*(1-Inputs!E129)*Inputs!E62/70 -> 45875.38 | F79: =D79/Inputs!$D$4 -> 524.18936
A80: Feed: growers | B80: KES | C80: =C71*Inputs!C128*(1-Inputs!C129)*Inputs!C62/70 -> 291600 | D80: =D71*Inputs!D128*(1-Inputs!D129)*Inputs!D62/70 -> 237600 | E80: =E71*Inputs!E128*(1-Inputs!E129)*Inputs!E62/70 -> 200571.43 | F80: =D80/Inputs!$D$4 -> 1829.2401
A81: Drugs and vaccines | B81: KES | C81: =C65*Inputs!C125+(C76+C71)*Inputs!C132 -> 68266.667 | D81: =D65*Inputs!D125+(D76+D71)*Inputs!D132 -> 51565.217 | E81: =E65*Inputs!E125+(E76+E71)*Inputs!E132 -> 43089.362 | F81: =D81/Inputs!$D$4 -> 396.99143
A82: Brooding fuel and bedding | B82: KES | C82: =(C76+C71)*Inputs!C66 -> 14755.556 | D82: =(D76+D71)*Inputs!D66 -> 11836.957 | E82: =(E76+E71)*Inputs!E66 -> 10835.745 | F82: =D82/Inputs!$D$4 -> 91.130622
A83: Egg packaging | B83: KES | C83: =C67/30*Inputs!C64 -> 17600 | D83: =D67/30*Inputs!D64 -> 24250 | E83: =E67/30*Inputs!E64 -> 29250 | F83: =D83/Inputs!$D$4 -> 186.69644
A84: Selling costs | B84: KES | C84: =C68*Inputs!C63+(C70+C73)*Inputs!C65 -> 27279.6 | D84: =D68*Inputs!D63+(D70+D73)*Inputs!D65 -> 31495 | E84: =E68*Inputs!E63+(E70+E73)*Inputs!E65 -> 31743.6 | F84: =D84/Inputs!$D$4 -> 242.4744
A85: Total variable costs | B85: KES | C85: =C77+C78+C79+C80+C81+C82+C83+C84 -> 1024276.4 | D85: =D77+D78+D79+D80+D81+D82+D83+D84 -> 810330.5 | E85: =E77+E78+E79+E80+E81+E82+E83+E84 -> 668473.39 | F85: =D85/Inputs!$D$4 -> 6238.5903
A86: Gross margin | B86: KES | C86: =C74-C85 -> -427996.43 | D86: =D74-D85 -> 86169.503 | E86: =E74-E85 -> 600246.61 | F86: =D86/Inputs!$D$4 -> 663.40367
A87: Gross margin per standing bird | B87: KES/bird | C87: =C86/C64 -> -855.99285 | D87: =D86/D64 -> 172.33901 | E87: =E86/E64 -> 1200.4932
A88: Unit margin per hen slot (per year) | B88: KES/bird | C88: =Inputs!C115*(1-Inputs!C116)*(Inputs!C117*(1-Inputs!C63)-Inputs!C64/30)+Inputs!C120*Inputs!C121*(1-Inputs!C65)-(Inputs!C120+Inputs!C122)/(1-Inputs!C123)*(Inputs!C131+Inputs!C66+Inputs!C132+Inputs!C124*(1-Inputs!C129)*Inputs!C62/70)-Inputs!C118/1000*365*(1-Inputs!C119)*Inputs!C61/70-Inputs!C125 -> -1488.4721 | D88: =Inputs!D115*(1-Inputs!D116)*(Inputs!D117*(1-Inputs!D63)-Inputs!D64/30)+Inputs!D120*Inputs!D121*(1-Inputs!D65)-(Inputs!D120+Inputs!D122)/(1-Inputs!D123)*(Inputs!D131+Inputs!D66+Inputs!D132+Inputs!D124*(1-Inputs!D129)*Inputs!D62/70)-Inputs!D118/1000*365*(1-Inputs!D119)*Inputs!D61/70-Inputs!D125 -> 243.04752 | E88: =Inputs!E115*(1-Inputs!E116)*(Inputs!E117*(1-Inputs!E63)-Inputs!E64/30)+Inputs!E120*Inputs!E121*(1-Inputs!E65)-(Inputs!E120+Inputs!E122)/(1-Inputs!E123)*(Inputs!E131+Inputs!E66+Inputs!E132+Inputs!E124*(1-Inputs!E129)*Inputs!E62/70)-Inputs!E118/1000*365*(1-Inputs!E119)*Inputs!E61/70-Inputs!E125 -> 1814.2282
A89: Unit margin per grower slot (per year) | B89: KES/bird | C89: =Inputs!C126*((1-Inputs!C127)*Inputs!C130*(1-Inputs!C65)-Inputs!C131-Inputs!C66-Inputs!C132-Inputs!C128*(1-Inputs!C129)*Inputs!C62/70) -> -434.34 | D89: =Inputs!D126*((1-Inputs!D127)*Inputs!D130*(1-Inputs!D65)-Inputs!D131-Inputs!D66-Inputs!D132-Inputs!D128*(1-Inputs!D129)*Inputs!D62/70) -> 125.2 | E89: =Inputs!E126*((1-Inputs!E127)*Inputs!E130*(1-Inputs!E65)-Inputs!E131-Inputs!E66-Inputs!E132-Inputs!E128*(1-Inputs!E129)*Inputs!E62/70) -> 791.33657
A90: Check: slot margins reproduce gross margin (should be 0) | B90: KES | C90: =C86-(C65*C88+C66*C89) -> 0 | D90: =D86-(D65*D88+D66*D89) -> 0 | E90: =E86-(E65*E88+E66*E89) -> 0 | F90: =D90/Inputs!$D$4 -> 0
A91: Stock capital | B91: KES | C91: =Inputs!C113*Inputs!C133 -> 250000 | D91: =Inputs!D113*Inputs!D133 -> 250000 | E91: =Inputs!E113*Inputs!E133 -> 250000 | F91: =D91/Inputs!$D$4 -> 1924.7055
A92: Memo: purchased feed | B92: KES | C92: =C78+C79+C80 -> 793085.71 | D92: =D78+D79+D80 -> 596487.67 | E92: =E78+E79+E80 -> 463256.81 | F92: =D92/Inputs!$D$4 -> 4592.2525
A93: Kebro
A94: Standing birds | B94: birds | C94: =Inputs!C135 -> 500 | D94: =Inputs!D135 -> 500 | E94: =Inputs!E135 -> 500
A95: Laying hens (hen slots) | B95: birds | C95: =Inputs!C135*Inputs!C136 -> 200 | D95: =Inputs!D135*Inputs!D136 -> 200 | E95: =Inputs!E135*Inputs!E136 -> 200
A96: Grower slots | B96: birds | C96: =Inputs!C135-C95 -> 300 | D96: =Inputs!D135-D95 -> 300 | E96: =Inputs!E135-E95 -> 300
A97: Saleable eggs | B97: eggs/yr | C97: =C95*Inputs!C137*(1-Inputs!C138) -> 21120 | D97: =D95*Inputs!D137*(1-Inputs!D138) -> 29100 | E97: =E95*Inputs!E137*(1-Inputs!E138) -> 35100
A98: Egg revenue | B98: KES | C98: =C97*Inputs!C139 -> 253440 | D98: =D97*Inputs!D139 -> 436500 | E98: =E97*Inputs!E139 -> 631800 | F98: =D98/Inputs!$D$4 -> 3360.5358
A99: Spent hens sold | B99: birds | C99: =C95*Inputs!C142 -> 160 | D99: =D95*Inputs!D142 -> 160 | E99: =E95*Inputs!E142 -> 160
A100: Spent hen revenue | B100: KES | C100: =C99*Inputs!C143 -> 48000 | D100: =D99*Inputs!D143 -> 64000 | E100: =E99*Inputs!E143 -> 80000 | F100: =D100/Inputs!$D$4 -> 492.72461
...

Sheet Mix
A1: Mix (annual, KES). All cells are live formulas from Inputs.
A2: Line | B2: Unit | C2: Low (adverse) | D2: Base | E2: High (favourable) | F2: Base in USD | G2: Note
A3: Hen share applied to all four chicken breeds (others unchanged). Other columns hold B12 option 2 value at that mix
A4: Hen share 0% of chicken flock
A5: Chicken gross margin at 0% hens | B5: KES | C5: =Inputs!C69*(0*Poultry!C28+1*Poultry!C29)+Inputs!C91*(0*Poultry!C58+1*Poultry!C59)+Inputs!C113*(0*Poultry!C88+1*Poultry!C89)+Inputs!C135*(0*Poultry!C118+1*Poultry!C119) -> -868680 | D5: =Inputs!D69*(0*Poultry!D28+1*Poultry!D29)+Inputs!D91*(0*Poultry!D58+1*Poultry!D59)+Inputs!D113*(0*Poultry!D88+1*Poultry!D89)+Inputs!D135*(0*Poultry!D118+1*Poultry!D119) -> 250400 | E5: =Inputs!E69*(0*Poultry!E28+1*Poultry!E29)+Inputs!E91*(0*Poultry!E58+1*Poultry!E59)+Inputs!E113*(0*Poultry!E88+1*Poultry!E89)+Inputs!E135*(0*Poultry!E118+1*Poultry!E119) -> 1582673.1 | F5: =D5/Inputs!$D$4 -> 1927.785
A6: Egg trays to sell per day (chickens only) | B6: trays/day | C6: =(Inputs!C69*0*Inputs!C71*(1-Inputs!C72)+Inputs!C91*0*Inputs!C93*(1-Inputs!C94)+Inputs!C113*0*Inputs!C115*(1-Inputs!C116)+Inputs!C135*0*Inputs!C137*(1-Inputs!C138))/30/365 -> 0 | D6: =(Inputs!D69*0*Inputs!D71*(1-Inputs!D72)+Inputs!D91*0*Inputs!D93*(1-Inputs!D94)+Inputs!D113*0*Inputs!D115*(1-Inputs!D116)+Inputs!D135*0*Inputs!D137*(1-Inputs!D138))/30/365 -> 0 | E6: =(Inputs!E69*0*Inputs!E71*(1-Inputs!E72)+Inputs!E91*0*Inputs!E93*(1-Inputs!E94)+Inputs!E113*0*Inputs!E115*(1-Inputs!E116)+Inputs!E135*0*Inputs!E137*(1-Inputs!E138))/30/365 -> 0
A7: Grower birds to sell per week (chickens only) | B7: birds/wk | C7: =(Inputs!C69*1*Inputs!C82*(1-Inputs!C83)+Inputs!C91*1*Inputs!C104*(1-Inputs!C105)+Inputs!C113*1*Inputs!C126*(1-Inputs!C127)+Inputs!C135*1*Inputs!C148*(1-Inputs!C149))/52 -> 58.153846 | D7: =(Inputs!D69*1*Inputs!D82*(1-Inputs!D83)+Inputs!D91*1*Inputs!D104*(1-Inputs!D105)+Inputs!D113*1*Inputs!D126*(1-Inputs!D127)+Inputs!D135*1*Inputs!D148*(1-Inputs!D149))/52 -> 67.692308 | E7: =(Inputs!E69*1*Inputs!E82*(1-Inputs!E83)+Inputs!E91*1*Inputs!E104*(1-Inputs!E105)+Inputs!E113*1*Inputs!E126*(1-Inputs!E127)+Inputs!E135*1*Inputs!E148*(1-Inputs!E149))/52 -> 84
A8: Farm OMBM at this mix | B8: KES | C8: =Farm_PnL!C46-Poultry!C256+C5 -> -3838062.9 | D8: =Farm_PnL!D46-Poultry!D256+D5 -> -1627086.5 | E8: =Farm_PnL!E46-Poultry!E256+E5 -> 771798.8 | F8: =D8/Inputs!$D$4 -> -12526.65
A9: B12 owner-operator value at this mix | B9: KES | C9: =B12!C21-Poultry!C256+C5 -> -5309046.4 | D9: =B12!D21-Poultry!D256+D5 -> -2472467 | E9: =B12!E21-Poultry!E256+E5 -> 378040.52 | F9: =D9/Inputs!$D$4 -> -19035.083
A10: Hen share 20% of chicken flock
A11: Chicken gross margin at 20% hens | B11: KES | C11: =Inputs!C69*(0.2*Poultry!C28+0.8*Poultry!C29)+Inputs!C91*(0.2*Poultry!C58+0.8*Poultry!C59)+Inputs!C113*(0.2*Poultry!C88+0.8*Poultry!C89)+Inputs!C135*(0.2*Poultry!C118+0.8*Poultry!C119) -> -1290332.9 | D11: =Inputs!D69*(0.2*Poultry!D28+0.8*Poultry!D29)+Inputs!D91*(0.2*Poultry!D58+0.8*Poultry!D59)+Inputs!D113*(0.2*Poultry!D88+0.8*Poultry!D89)+Inputs!D135*(0.2*Poultry!D118+0.8*Poultry!D119) -> 297539.01 | E11: =Inputs!E69*(0.2*Poultry!E28+0.8*Poultry!E29)+Inputs!E91*(0.2*Poultry!E58+0.8*Poultry!E59)+Inputs!E113*(0.2*Poultry!E88+0.8*Poultry!E89)+Inputs!E135*(0.2*Poultry!E118+0.8*Poultry!E119) -> 1991829.8 | F11: =D11/Inputs!$D$4 -> 2290.6999
A12: Egg trays to sell per day (chickens only) | B12: trays/day | C12: =(Inputs!C69*0.2*Inputs!C71*(1-Inputs!C72)+Inputs!C91*0.2*Inputs!C93*(1-Inputs!C94)+Inputs!C113*0.2*Inputs!C115*(1-Inputs!C116)+Inputs!C135*0.2*Inputs!C137*(1-Inputs!C138))/30/365 -> 3.8575342 | D12: =(Inputs!D69*0.2*Inputs!D71*(1-Inputs!D72)+Inputs!D91*0.2*Inputs!D93*(1-Inputs!D94)+Inputs!D113*0.2*Inputs!D115*(1-Inputs!D116)+Inputs!D135*0.2*Inputs!D137*(1-Inputs!D138))/30/365 -> 5.3150685 | E12: =(Inputs!E69*0.2*Inputs!E71*(1-Inputs!E72)+Inputs!E91*0.2*Inputs!E93*(1-Inputs!E94)+Inputs!E113*0.2*Inputs!E115*(1-Inputs!E116)+Inputs!E135*0.2*Inputs!E137*(1-Inputs!E138))/30/365 -> 6.4109589
A13: Grower birds to sell per week (chickens only) | B13: birds/wk | C13: =(Inputs!C69*0.8*Inputs!C82*(1-Inputs!C83)+Inputs!C91*0.8*Inputs!C104*(1-Inputs!C105)+Inputs!C113*0.8*Inputs!C126*(1-Inputs!C127)+Inputs!C135*0.8*Inputs!C148*(1-Inputs!C149))/52 -> 46.523077 | D13: =(Inputs!D69*0.8*Inputs!D82*(1-Inputs!D83)+Inputs!D91*0.8*Inputs!D104*(1-Inputs!D105)+Inputs!D113*0.8*Inputs!D126*(1-Inputs!D127)+Inputs!D135*0.8*Inputs!D148*(1-Inputs!D149))/52 -> 54.153846 | E13: =(Inputs!E69*0.8*Inputs!E82*(1-Inputs!E83)+Inputs!E91*0.8*Inputs!E104*(1-Inputs!E105)+Inputs!E113*0.8*Inputs!E126*(1-Inputs!E127)+Inputs!E135*0.8*Inputs!E148*(1-Inputs!E149))/52 -> 67.2
A14: Farm OMBM at this mix | B14: KES | C14: =Farm_PnL!C46-Poultry!C256+C11 -> -4259715.7 | D14: =Farm_PnL!D46-Poultry!D256+D11 -> -1579947.5 | E14: =Farm_PnL!E46-Poultry!E256+E11 -> 1180955.5 | F14: =D14/Inputs!$D$4 -> -12163.735
A15: B12 owner-operator value at this mix | B15: KES | C15: =B12!C21-Poultry!C256+C11 -> -5730699.2 | D15: =B12!D21-Poultry!D256+D11 -> -2425328 | E15: =B12!E21-Poultry!E256+E11 -> 787197.18 | F15: =D15/Inputs!$D$4 -> -18672.169
A16: Hen share 40% of chicken flock
A17: Chicken gross margin at 40% hens | B17: KES | C17: =Inputs!C69*(0.4*Poultry!C28+0.6*Poultry!C29)+Inputs!C91*(0.4*Poultry!C58+0.6*Poultry!C59)+Inputs!C113*(0.4*Poultry!C88+0.6*Poultry!C89)+Inputs!C135*(0.4*Poultry!C118+0.6*Poultry!C119) -> -1711985.7 | D17: =Inputs!D69*(0.4*Poultry!D28+0.6*Poultry!D29)+Inputs!D91*(0.4*Poultry!D58+0.6*Poultry!D59)+Inputs!D113*(0.4*Poultry!D88+0.6*Poultry!D89)+Inputs!D135*(0.4*Poultry!D118+0.6*Poultry!D119) -> 344678.01 | E17: =Inputs!E69*(0.4*Poultry!E28+0.6*Poultry!E29)+Inputs!E91*(0.4*Poultry!E58+0.6*Poultry!E59)+Inputs!E113*(0.4*Poultry!E88+0.6*Poultry!E89)+Inputs!E135*(0.4*Poultry!E118+0.6*Poultry!E119) -> 2400986.5 | F17: =D17/Inputs!$D$4 -> 2653.6147
A18: Egg trays to sell per day (chickens only) | B18: trays/day | C18: =(Inputs!C69*0.4*Inputs!C71*(1-Inputs!C72)+Inputs!C91*0.4*Inputs!C93*(1-Inputs!C94)+Inputs!C113*0.4*Inputs!C115*(1-Inputs!C116)+Inputs!C135*0.4*Inputs!C137*(1-Inputs!C138))/30/365 -> 7.7150685 | D18: =(Inputs!D69*0.4*Inputs!D71*(1-Inputs!D72)+Inputs!D91*0.4*Inputs!D93*(1-Inputs!D94)+Inputs!D113*0.4*Inputs!D115*(1-Inputs!D116)+Inputs!D135*0.4*Inputs!D137*(1-Inputs!D138))/30/365 -> 10.630137 | E18: =(Inputs!E69*0.4*Inputs!E71*(1-Inputs!E72)+Inputs!E91*0.4*Inputs!E93*(1-Inputs!E94)+Inputs!E113*0.4*Inputs!E115*(1-Inputs!E116)+Inputs!E135*0.4*Inputs!E137*(1-Inputs!E138))/30/365 -> 12.821918
A19: Grower birds to sell per week (chickens only) | B19: birds/wk | C19: =(Inputs!C69*0.6*Inputs!C82*(1-Inputs!C83)+Inputs!C91*0.6*Inputs!C104*(1-Inputs!C105)+Inputs!C113*0.6*Inputs!C126*(1-Inputs!C127)+Inputs!C135*0.6*Inputs!C148*(1-Inputs!C149))/52 -> 34.892308 | D19: =(Inputs!D69*0.6*Inputs!D82*(1-Inputs!D83)+Inputs!D91*0.6*Inputs!D104*(1-Inputs!D105)+Inputs!D113*0.6*Inputs!D126*(1-Inputs!D127)+Inputs!D135*0.6*Inputs!D148*(1-Inputs!D149))/52 -> 40.615385 | E19: =(Inputs!E69*0.6*Inputs!E82*(1-Inputs!E83)+Inputs!E91*0.6*Inputs!E104*(1-Inputs!E105)+Inputs!E113*0.6*Inputs!E126*(1-Inputs!E127)+Inputs!E135*0.6*Inputs!E148*(1-Inputs!E149))/52 -> 50.4
A20: Farm OMBM at this mix | B20: KES | C20: =Farm_PnL!C46-Poultry!C256+C17 -> -4681368.6 | D20: =Farm_PnL!D46-Poultry!D256+D17 -> -1532808.5 | E20: =Farm_PnL!E46-Poultry!E256+E17 -> 1590112.1 | F20: =D20/Inputs!$D$4 -> -11800.82
A21: B12 owner-operator value at this mix | B21: KES | C21: =B12!C21-Poultry!C256+C17 -> -6152352.1 | D21: =B12!D21-Poultry!D256+D17 -> -2378189 | E21: =B12!E21-Poultry!E256+E17 -> 1196353.8 | F21: =D21/Inputs!$D$4 -> -18309.254
A22: Hen share 60% of chicken flock
A23: Chicken gross margin at 60% hens | B23: KES | C23: =Inputs!C69*(0.6*Poultry!C28+0.4*Poultry!C29)+Inputs!C91*(0.6*Poultry!C58+0.4*Poultry!C59)+Inputs!C113*(0.6*Poultry!C88+0.4*Poultry!C89)+Inputs!C135*(0.6*Poultry!C118+0.4*Poultry!C119) -> -2133638.6 | D23: =Inputs!D69*(0.6*Poultry!D28+0.4*Poultry!D29)+Inputs!D91*(0.6*Poultry!D58+0.4*Poultry!D59)+Inputs!D113*(0.6*Poultry!D88+0.4*Poultry!D89)+Inputs!D135*(0.6*Poultry!D118+0.4*Poultry!D119) -> 391817.02 | E23: =Inputs!E69*(0.6*Poultry!E28+0.4*Poultry!E29)+Inputs!E91*(0.6*Poultry!E58+0.4*Poultry!E59)+Inputs!E113*(0.6*Poultry!E88+0.4*Poultry!E89)+Inputs!E135*(0.6*Poultry!E118+0.4*Poultry!E119) -> 2810143.1 | F23: =D23/Inputs!$D$4 -> 3016.5295
A24: Egg trays to sell per day (chickens only) | B24: trays/day | C24: =(Inputs!C69*0.6*Inputs!C71*(1-Inputs!C72)+Inputs!C91*0.6*Inputs!C93*(1-Inputs!C94)+Inputs!C113*0.6*Inputs!C115*(1-Inputs!C116)+Inputs!C135*0.6*Inputs!C137*(1-Inputs!C138))/30/365 -> 11.572603 | D24: =(Inputs!D69*0.6*Inputs!D71*(1-Inputs!D72)+Inputs!D91*0.6*Inputs!D93*(1-Inputs!D94)+Inputs!D113*0.6*Inputs!D115*(1-Inputs!D116)+Inputs!D135*0.6*Inputs!D137*(1-Inputs!D138))/30/365 -> 15.945205 | E24: =(Inputs!E69*0.6*Inputs!E71*(1-Inputs!E72)+Inputs!E91*0.6*Inputs!E93*(1-Inputs!E94)+Inputs!E113*0.6*Inputs!E115*(1-Inputs!E116)+Inputs!E135*0.6*Inputs!E137*(1-Inputs!E138))/30/365 -> 19.232877
A25: Grower birds to sell per week (chickens only) | B25: birds/wk | C25: =(Inputs!C69*0.4*Inputs!C82*(1-Inputs!C83)+Inputs!C91*0.4*Inputs!C104*(1-Inputs!C105)+Inputs!C113*0.4*Inputs!C126*(1-Inputs!C127)+Inputs!C135*0.4*Inputs!C148*(1-Inputs!C149))/52 -> 23.261538 | D25: =(Inputs!D69*0.4*Inputs!D82*(1-Inputs!D83)+Inputs!D91*0.4*Inputs!D104*(1-Inputs!D105)+Inputs!D113*0.4*Inputs!D126*(1-Inputs!D127)+Inputs!D135*0.4*Inputs!D148*(1-Inputs!D149))/52 -> 27.076923 | E25: =(Inputs!E69*0.4*Inputs!E82*(1-Inputs!E83)+Inputs!E91*0.4*Inputs!E104*(1-Inputs!E105)+Inputs!E113*0.4*Inputs!E126*(1-Inputs!E127)+Inputs!E135*0.4*Inputs!E148*(1-Inputs!E149))/52 -> 33.6
A26: Farm OMBM at this mix | B26: KES | C26: =Farm_PnL!C46-Poultry!C256+C23 -> -5103021.4 | D26: =Farm_PnL!D46-Poultry!D256+D23 -> -1485669.5 | E26: =Farm_PnL!E46-Poultry!E256+E23 -> 1999268.8 | F26: =D26/Inputs!$D$4 -> -11437.905
A27: B12 owner-operator value at this mix | B27: KES | C27: =B12!C21-Poultry!C256+C23 -> -6574004.9 | D27: =B12!D21-Poultry!D256+D23 -> -2331050 | E27: =B12!E21-Poultry!E256+E23 -> 1605510.5 | F27: =D27/Inputs!$D$4 -> -17946.339
A28: Hen share 80% of chicken flock
A29: Chicken gross margin at 80% hens | B29: KES | C29: =Inputs!C69*(0.8*Poultry!C28+0.2*Poultry!C29)+Inputs!C91*(0.8*Poultry!C58+0.2*Poultry!C59)+Inputs!C113*(0.8*Poultry!C88+0.2*Poultry!C89)+Inputs!C135*(0.8*Poultry!C118+0.2*Poultry!C119) -> -2555291.4 | D29: =Inputs!D69*(0.8*Poultry!D28+0.2*Poultry!D29)+Inputs!D91*(0.8*Poultry!D58+0.2*Poultry!D59)+Inputs!D113*(0.8*Poultry!D88+0.2*Poultry!D89)+Inputs!D135*(0.8*Poultry!D118+0.2*Poultry!D119) -> 438956.02 | E29: =Inputs!E69*(0.8*Poultry!E28+0.2*Poultry!E29)+Inputs!E91*(0.8*Poultry!E58+0.2*Poultry!E59)+Inputs!E113*(0.8*Poultry!E88+0.2*Poultry!E89)+Inputs!E135*(0.8*Poultry!E118+0.2*Poultry!E119) -> 3219299.8 | F29: =D29/Inputs!$D$4 -> 3379.4443
A30: Egg trays to sell per day (chickens only) | B30: trays/day | C30: =(Inputs!C69*0.8*Inputs!C71*(1-Inputs!C72)+Inputs!C91*0.8*Inputs!C93*(1-Inputs!C94)+Inputs!C113*0.8*Inputs!C115*(1-Inputs!C116)+Inputs!C135*0.8*Inputs!C137*(1-Inputs!C138))/30/365 -> 15.430137 | D30: =(Inputs!D69*0.8*Inputs!D71*(1-Inputs!D72)+Inputs!D91*0.8*Inputs!D93*(1-Inputs!D94)+Inputs!D113*0.8*Inputs!D115*(1-Inputs!D116)+Inputs!D135*0.8*Inputs!D137*(1-Inputs!D138))/30/365 -> 21.260274 | E30: =(Inputs!E69*0.8*Inputs!E71*(1-Inputs!E72)+Inputs!E91*0.8*Inputs!E93*(1-Inputs!E94)+Inputs!E113*0.8*Inputs!E115*(1-Inputs!E116)+Inputs!E135*0.8*Inputs!E137*(1-Inputs!E138))/30/365 -> 25.643836
A31: Grower birds to sell per week (chickens only) | B31: birds/wk | C31: =(Inputs!C69*0.2*Inputs!C82*(1-Inputs!C83)+Inputs!C91*0.2*Inputs!C104*(1-Inputs!C105)+Inputs!C113*0.2*Inputs!C126*(1-Inputs!C127)+Inputs!C135*0.2*Inputs!C148*(1-Inputs!C149))/52 -> 11.630769 | D31: =(Inputs!D69*0.2*Inputs!D82*(1-Inputs!D83)+Inputs!D91*0.2*Inputs!D104*(1-Inputs!D105)+Inputs!D113*0.2*Inputs!D126*(1-Inputs!D127)+Inputs!D135*0.2*Inputs!D148*(1-Inputs!D149))/52 -> 13.538462 | E31: =(Inputs!E69*0.2*Inputs!E82*(1-Inputs!E83)+Inputs!E91*0.2*Inputs!E104*(1-Inputs!E105)+Inputs!E113*0.2*Inputs!E126*(1-Inputs!E127)+Inputs!E135*0.2*Inputs!E148*(1-Inputs!E149))/52 -> 16.8
A32: Farm OMBM at this mix | B32: KES | C32: =Farm_PnL!C46-Poultry!C256+C29 -> -5524674.3 | D32: =Farm_PnL!D46-Poultry!D256+D29 -> -1438530.5 | E32: =Farm_PnL!E46-Poultry!E256+E29 -> 2408425.4 | F32: =D32/Inputs!$D$4 -> -11074.99
A33: B12 owner-operator value at this mix | B33: KES | C33: =B12!C21-Poultry!C256+C29 -> -6995657.8 | D33: =B12!D21-Poultry!D256+D29 -> -2283911 | E33: =B12!E21-Poultry!E256+E29 -> 2014667.1 | F33: =D33/Inputs!$D$4 -> -17583.424
A34: Hen share 100% of chicken flock
A35: Chicken gross margin at 100% hens | B35: KES | C35: =Inputs!C69*(1*Poultry!C28+0*Poultry!C29)+Inputs!C91*(1*Poultry!C58+0*Poultry!C59)+Inputs!C113*(1*Poultry!C88+0*Poultry!C89)+Inputs!C135*(1*Poultry!C118+0*Poultry!C119) -> -2976944.3 | D35: =Inputs!D69*(1*Poultry!D28+0*Poultry!D29)+Inputs!D91*(1*Poultry!D58+0*Poultry!D59)+Inputs!D113*(1*Poultry!D88+0*Poultry!D89)+Inputs!D135*(1*Poultry!D118+0*Poultry!D119) -> 486095.03 | E35: =Inputs!E69*(1*Poultry!E28+0*Poultry!E29)+Inputs!E91*(1*Poultry!E58+0*Poultry!E59)+Inputs!E113*(1*Poultry!E88+0*Poultry!E89)+Inputs!E135*(1*Poultry!E118+0*Poultry!E119) -> 3628456.4 | F35: =D35/Inputs!$D$4 -> 3742.3592
A36: Egg trays to sell per day (chickens only) | B36: trays/day | C36: =(Inputs!C69*1*Inputs!C71*(1-Inputs!C72)+Inputs!C91*1*Inputs!C93*(1-Inputs!C94)+Inputs!C113*1*Inputs!C115*(1-Inputs!C116)+Inputs!C135*1*Inputs!C137*(1-Inputs!C138))/30/365 -> 19.287671 | D36: =(Inputs!D69*1*Inputs!D71*(1-Inputs!D72)+Inputs!D91*1*Inputs!D93*(1-Inputs!D94)+Inputs!D113*1*Inputs!D115*(1-Inputs!D116)+Inputs!D135*1*Inputs!D137*(1-Inputs!D138))/30/365 -> 26.575342 | E36: =(Inputs!E69*1*Inputs!E71*(1-Inputs!E72)+Inputs!E91*1*Inputs!E93*(1-Inputs!E94)+Inputs!E113*1*Inputs!E115*(1-Inputs!E116)+Inputs!E135*1*Inputs!E137*(1-Inputs!E138))/30/365 -> 32.054795
A37: Grower birds to sell per week (chickens only) | B37: birds/wk | C37: =(Inputs!C69*0*Inputs!C82*(1-Inputs!C83)+Inputs!C91*0*Inputs!C104*(1-Inputs!C105)+Inputs!C113*0*Inputs!C126*(1-Inputs!C127)+Inputs!C135*0*Inputs!C148*(1-Inputs!C149))/52 -> 0 | D37: =(Inputs!D69*0*Inputs!D82*(1-Inputs!D83)+Inputs!D91*0*Inputs!D104*(1-Inputs!D105)+Inputs!D113*0*Inputs!D126*(1-Inputs!D127)+Inputs!D135*0*Inputs!D148*(1-Inputs!D149))/52 -> 0 | E37: =(Inputs!E69*0*Inputs!E82*(1-Inputs!E83)+Inputs!E91*0*Inputs!E104*(1-Inputs!E105)+Inputs!E113*0*Inputs!E126*(1-Inputs!E127)+Inputs!E135*0*Inputs!E148*(1-Inputs!E149))/52 -> 0
A38: Farm OMBM at this mix | B38: KES | C38: =Farm_PnL!C46-Poultry!C256+C35 -> -5946327.1 | D38: =Farm_PnL!D46-Poultry!D256+D35 -> -1391391.5 | E38: =Farm_PnL!E46-Poultry!E256+E35 -> 2817582.1 | F38: =D38/Inputs!$D$4 -> -10712.076
A39: B12 owner-operator value at this mix | B39: KES | C39: =B12!C21-Poultry!C256+C35 -> -7417310.6 | D39: =B12!D21-Poultry!D256+D35 -> -2236772 | E39: =B12!E21-Poultry!E256+E35 -> 2423823.8 | F39: =D39/Inputs!$D$4 -> -17220.509

Sheet Labour
A1: Labour (annual, KES). All cells are live formulas from Inputs.
A2: Line | B2: Unit | C2: Low (adverse) | D2: Base | E2: High (favourable) | F2: Base in USD | G2: Note
A3: Pay (owner-reported KES 22,000 each; one is a relative)
A4: Staff 1 | B4: KES/month | C4: =Inputs!C248 -> 22000 | D4: =Inputs!D248 -> 22000 | E4: =Inputs!E248 -> 22000
A5: Staff 2 (relative; placeholder) | B5: KES/month | C5: =Inputs!C249 -> 22000 | D5: =Inputs!D249 -> 22000 | E5: =Inputs!E249 -> 22000
A6: Staff 3 | B6: KES/month | C6: =Inputs!C250 -> 22000 | D6: =Inputs!D250 -> 22000 | E6: =Inputs!E250 -> 22000
A7: Pay as multiple of legal stockman minimum (each) | B7: x | C7: =Inputs!C248/Inputs!C246 -> 2.3820403 | D7: =Inputs!D248/Inputs!D246 -> 2.3820403 | E7: =Inputs!E248/Inputs!E246 -> 2.3820403 | G7: Foreman/clerk minimum is higher: see next row
A8: Pay as multiple of legal foreman/clerk minimum | B8: x | C8: =Inputs!C248/Inputs!C247 -> 1.5249048 | D8: =Inputs!D248/Inputs!D247 -> 1.5249048 | E8: =Inputs!E248/Inputs!E247 -> 1.5249048
A9: Annual cost
A10: Basic pay (x12) | B10: KES | C10: =(C4+C5+C6)*12 -> 792000 | D10: =(D4+D5+D6)*12 -> 792000 | E10: =(E4+E5+E6)*12 -> 792000 | F10: =D10/Inputs!$D$4 -> 6097.4671
A11: Employer NSSF + housing levy + NITA | B11: KES | C11: =(C4+C5+C6)*12*(Inputs!C251+Inputs!C252)+3*12*Inputs!C253 -> 61200 | D11: =(D4+D5+D6)*12*(Inputs!D251+Inputs!D252)+3*12*Inputs!D253 -> 61200 | E11: =(E4+E5+E6)*12*(Inputs!E251+Inputs!E252)+3*12*Inputs!E253 -> 61200 | F11: =D11/Inputs!$D$4 -> 471.16791
A12: Casual relief labour (leave, peaks) | B12: KES | C12: =Inputs!C254*Inputs!C255 -> 17500 | D12: =Inputs!D254*Inputs!D255 -> 15000 | E12: =Inputs!E254*Inputs!E255 -> 12500 | F12: =D12/Inputs!$D$4 -> 115.48233
A13: Task hours required per year | B13: h | C13: =(Inputs!C258+Inputs!C259+Inputs!C260+Inputs!C262+Poultry!C244/100*Inputs!C261)*365 -> 7135.75 | D13: =(Inputs!D258+Inputs!D259+Inputs!D260+Inputs!D262+Poultry!D244/100*Inputs!D261)*365 -> 5869.2 | E13: =(Inputs!E258+Inputs!E259+Inputs!E260+Inputs!E262+Poultry!E244/100*Inputs!E261)*365 -> 5015.465
A14: Productive hours per person per year | B14: h | C14: =Inputs!C256*Inputs!C257 -> 2160 | D14: =Inputs!D256*Inputs!D257 -> 2160 | E14: =Inputs!E256*Inputs!E257 -> 2160
A15: FTE required | B15: FTE | C15: =C13/C14 -> 3.303588 | D15: =D13/D14 -> 2.7172222 | E15: =E13/E14 -> 2.3219745
A16: Utilisation of 3 staff | B16: % | C16: =C15/3 -> 1.101196 | D16: =D15/3 -> 0.90574074 | E16: =E15/3 -> 0.77399151
A17: Hours beyond the 3 staff (to be covered by extra casuals) | B17: h | C17: =MAX(0,C13-3*C14) -> 655.75 | D17: =MAX(0,D13-3*D14) -> 0 | E17: =MAX(0,E13-3*E14) -> 0
A18: Extra casual labour for hours beyond 3 staff | B18: KES | C18: =C17/8*Inputs!C255 -> 40984.375 | D18: =D17/8*Inputs!D255 -> 0 | E18: =E17/8*Inputs!E255 -> 0 | F18: =D18/Inputs!$D$4 -> 0
A19: Total hired labour cost | B19: KES | C19: =C10+C11+C12+C18 -> 911684.38 | D19: =D10+D11+D12+D18 -> 868200 | E19: =E10+E11+E12+E18 -> 865700 | F19: =D19/Inputs!$D$4 -> 6684.1173
A20: Monthly basic pay bill | B20: KES/month | C20: =C4+C5+C6 -> 66000 | D20: =D4+D5+D6 -> 66000 | E20: =E4+E5+E6 -> 66000
A21: All-in cost per staff member per month (incl. statutory) | B21: KES/month | C21: =(C10+C11)/36 -> 23700 | D21: =(D10+D11)/36 -> 23700 | E21: =(E10+E11)/36 -> 23700
A22: Minimum people for 7-day cover (1 on site, 5.5-day weeks) | B22: FTE | C22: =365/(5.5*52*(1-3/52)) -> 1.3543599 | D22: =365/(5.5*52*(1-3/52)) -> 1.3543599 | E22: =365/(5.5*52*(1-3/52)) -> 1.3543599
A23: Poultry per staff member | B23: birds | C23: =Poultry!C244/3 -> 756.66667 | D23: =Poultry!D244/3 -> 756.66667 | E23: =Poultry!E244/3 -> 756.66667
A24: Hired labour as % of revenue | B24: % | C24: =C19/Farm_PnL!C15 -> 0.28057559 | D24: =D19/Farm_PnL!D15 -> 0.178858 | E24: =E19/Farm_PnL!E15 -> 0.12373749
A25: Hired labour as % of gross margin | B25: % | C25: =IF(Farm_PnL!C30<=0,"GM<=0",C19/Farm_PnL!C30) -> GM<=0 | D25: =IF(Farm_PnL!D30<=0,"GM<=0",D19/Farm_PnL!D30) -> 1.0603001 | E25: =IF(Farm_PnL!E30<=0,"GM<=0",E19/Farm_PnL!E30) -> 0.24104572
A26: Gross margin covers labour + vet fees + fixed costs? (GM / total) | B26: x | C26: =Farm_PnL!C30/Farm_PnL!C44 -> -0.6036701 | D26: =Farm_PnL!D30/Farm_PnL!D44 -> 0.34819408 | E26: =Farm_PnL!E30/Farm_PnL!E44 -> 1.7945306

Sheet Lorry
A1: Lorry (annual, KES). All cells are live formulas from Inputs.
A2: Line | B2: Unit | C2: Low (adverse) | D2: Base | E2: High (favourable) | F2: Base in USD | G2: Note
A3: Standing costs (incurred whether or not the lorry moves)
A4: Lorry value | B4: KES | C4: =Inputs!C273 -> 4500000 | D4: =Inputs!D273 -> 4500000 | E4: =Inputs!E273 -> 4500000 | F4: =D4/Inputs!$D$4 -> 34644.699
A5: Depreciation ((value - residual) / life) | B5: KES | C5: =Inputs!C273*(1-Inputs!C274)/Inputs!C275 -> 421875 | D5: =Inputs!D273*(1-Inputs!D274)/Inputs!D275 -> 337500 | E5: =Inputs!E273*(1-Inputs!E274)/Inputs!E275 -> 281250 | F5: =D5/Inputs!$D$4 -> 2598.3525 | G5: Non-cash, but the real cost of ownership
A6: Comprehensive insurance | B6: KES | C6: =Inputs!C273*Inputs!C276 -> 225000 | D6: =Inputs!D273*Inputs!D276 -> 180000 | E6: =Inputs!E273*Inputs!E276 -> 135000 | F6: =D6/Inputs!$D$4 -> 1385.788
A7: NTSA annual inspection | B7: KES | C7: =Inputs!C277 -> 4600 | D7: =Inputs!D277 -> 4600 | E7: =Inputs!E277 -> 4600 | F7: =D7/Inputs!$D$4 -> 35.414582
A8: Licence, governor, GPS tracker, driver licence upkeep | B8: KES | C8: =Inputs!C278 -> 40000 | D8: =Inputs!D278 -> 30000 | E8: =Inputs!E278 -> 25000 | F8: =D8/Inputs!$D$4 -> 230.96466
A9: Fixed maintenance | B9: KES | C9: =Inputs!C273*Inputs!C279 -> 135000 | D9: =Inputs!D273*Inputs!D279 -> 90000 | E9: =Inputs!E273*Inputs!E279 -> 67500 | F9: =D9/Inputs!$D$4 -> 692.89399
A10: Standing cash costs | B10: KES | C10: =C6+C7+C8+C9 -> 404600 | D10: =D6+D7+D8+D9 -> 304600 | E10: =E6+E7+E8+E9 -> 232100 | F10: =D10/Inputs!$D$4 -> 2345.0612
A11: Standing cost incl. depreciation | B11: KES | C11: =C10+C5 -> 826475 | D11: =D10+D5 -> 642100 | E11: =E10+E5 -> 513350 | F11: =D11/Inputs!$D$4 -> 4943.4137
A12: Own-farm use (feed, sales runs)
A13: Fuel | B13: KES | C13: =Inputs!C283/Inputs!C281*Inputs!C282 -> 337500 | D13: =Inputs!D283/Inputs!D281*Inputs!D282 -> 197333.33 | E13: =Inputs!E283/Inputs!E281*Inputs!E282 -> 117272.73 | F13: =D13/Inputs!$D$4 -> 1519.2342
A14: Variable maintenance (tyres, oil, repairs) | B14: KES | C14: =Inputs!C283*Inputs!C280 -> 108000 | D14: =Inputs!D283*Inputs!D280 -> 56000 | E14: =Inputs!E283*Inputs!E280 -> 33000 | F14: =D14/Inputs!$D$4 -> 431.13404
A15: Driver (ad hoc days) | B15: KES | C15: =Inputs!C284*Inputs!C285 -> 140000 | D15: =Inputs!D284*Inputs!D285 -> 78000 | E15: =Inputs!E284*Inputs!E285 -> 48000 | F15: =D15/Inputs!$D$4 -> 600.50812
A16: Own-use running cost | B16: KES | C16: =C13+C14+C15 -> 585500 | D16: =D13+D14+D15 -> 331333.33 | E16: =E13+E14+E15 -> 198272.73 | F16: =D16/Inputs!$D$4 -> 2550.8764
A17: Credit: transport the lorry replaces | B17: KES | C17: =Inputs!C286*Inputs!C267 -> 27500 | D17: =Inputs!D286*Inputs!D267 -> 24000 | E17: =Inputs!E286*Inputs!E267 -> 20000 | F17: =D17/Inputs!$D$4 -> 184.77173
A18: External hire (zero in headline: no source for demand or rates)
A19: Hire days | B19: days | C19: =Inputs!C287 -> 0 | D19: =Inputs!D287 -> 0 | E19: =Inputs!E287 -> 0
A20: Hire revenue | B20: KES | C20: =C19*Inputs!C288 -> 0 | D20: =D19*Inputs!D288 -> 0 | E20: =E19*Inputs!E288 -> 0 | F20: =D20/Inputs!$D$4 -> 0
A21: Hire running cost (fuel, maintenance, driver) | B21: KES | C21: =C19*(Inputs!C289/Inputs!C281*Inputs!C282+Inputs!C289*Inputs!C280+Inputs!C290) -> 0 | D21: =D19*(Inputs!D289/Inputs!D281*Inputs!D282+Inputs!D289*Inputs!D280+Inputs!D290) -> 0 | E21: =E19*(Inputs!E289/Inputs!E281*Inputs!E282+Inputs!E289*Inputs!E280+Inputs!E290) -> 0 | F21: =D21/Inputs!$D$4 -> 0
A22: Net hire contribution | B22: KES | C22: =C20-C21 -> 0 | D22: =D20-D21 -> 0 | E22: =E20-E21 -> 0 | F22: =D22/Inputs!$D$4 -> 0
A23: Net effect on the farm
A24: Net lorry cost to OMBM (standing + running - credit - hire) | B24: KES | C24: =C11+C16-C17-C22 -> 1384475 | D24: =D11+D16-D17-D22 -> 949433.33 | E24: =E11+E16-E17-E22 -> 691622.73 | F24: =D24/Inputs!$D$4 -> 7309.5183
A25: Net lorry cash cost (excl. depreciation) | B25: KES | C25: =C24-C5 -> 962600 | D25: =D24-D5 -> 611933.33 | E25: =E24-E5 -> 410372.73 | F25: =D25/Inputs!$D$4 -> 4711.1659
A26: Net lorry cost as % of poultry+livestock gross margin | B26: % | C26: =IF(Farm_PnL!C30<=0,"GM<=0",C24/Farm_PnL!C30) -> GM<=0 | D26: =IF(Farm_PnL!D30<=0,"GM<=0",D24/Farm_PnL!D30) -> 1.1595073 | E26: =IF(Farm_PnL!E30<=0,"GM<=0",E24/Farm_PnL!E30) -> 0.1925756
A27: Break-even hire (illustrative revenue per day from Inputs)
A28: Net contribution per hire day (revenue - fuel - maintenance - driver) | B28: KES/day | C28: =Inputs!C288-(Inputs!C289/Inputs!C281*Inputs!C282+Inputs!C289*Inputs!C280+Inputs!C290) -> 4362.5 | D28: =Inputs!D288-(Inputs!D289/Inputs!D281*Inputs!D282+Inputs!D289*Inputs!D280+Inputs!D290) -> 13000 | E28: =Inputs!E288-(Inputs!E289/Inputs!E281*Inputs!E282+Inputs!E289*Inputs!E280+Inputs!E290) -> 21986.364
A29: Hire days per year to cover the lorry economically (incl. depreciation) | B29: days | C29: =IF(C28<=0,"never",(C11+C16-C17)/C28) -> 317.35817 | D29: =IF(D28<=0,"never",(D11+D16-D17)/D28) -> 73.033333 | E29: =IF(E28<=0,"never",(E11+E16-E17)/E28) -> 31.456895
A30: Hire days per year to cover cash costs only | B30: days | C30: =IF(C28<=0,"never",(C10+C16-C17)/C28) -> 220.6533 | D30: =IF(D28<=0,"never",(D10+D16-D17)/D28) -> 47.071795 | E30: =IF(E28<=0,"never",(E10+E16-E17)/E28) -> 18.664875
A31: Break-even hire days as % of a 250-day working year | B31: % | C31: =IF(ISNUMBER(C29),C29/250,"n/a") -> 1.2694327 | D31: =IF(ISNUMBER(D29),D29/250,"n/a") -> 0.29213333 | E31: =IF(ISNUMBER(E29),E29/250,"n/a") -> 0.12582758
A32: Net lorry cost to OMBM if hired 0 days a year at illustrative rate | B32: KES | C32: =C11+C16-C17-0*C28 -> 1384475 | D32: =D11+D16-D17-0*D28 -> 949433.33 | E32: =E11+E16-E17-0*E28 -> 691622.73 | F32: =D32/Inputs!$D$4 -> 7309.5183
A33: Net lorry cost to OMBM if hired 25 days a year at illustrative rate | B33: KES | C33: =C11+C16-C17-25*C28 -> 1275412.5 | D33: =D11+D16-D17-25*D28 -> 624433.33 | E33: =E11+E16-E17-25*E28 -> 141963.64 | F33: =D33/Inputs!$D$4 -> 4807.4011
A34: Net lorry cost to OMBM if hired 50 days a year at illustrative rate | B34: KES | C34: =C11+C16-C17-50*C28 -> 1166350 | D34: =D11+D16-D17-50*D28 -> 299433.33 | E34: =E11+E16-E17-50*E28 -> -407695.45 | F34: =D34/Inputs!$D$4 -> 2305.284
A35: Net lorry cost to OMBM if hired 100 days a year at illustrative rate | B35: KES | C35: =C11+C16-C17-100*C28 -> 948225 | D35: =D11+D16-D17-100*D28 -> -350566.67 | E35: =E11+E16-E17-100*E28 -> -1507013.6 | F35: =D35/Inputs!$D$4 -> -2698.9504
A36: Net lorry cost to OMBM if hired 150 days a year at illustrative rate | B36: KES | C36: =C11+C16-C17-150*C28 -> 730100 | D36: =D11+D16-D17-150*D28 -> -1000566.7 | E36: =E11+E16-E17-150*E28 -> -2606331.8 | F36: =D36/Inputs!$D$4 -> -7703.1847
A37: Net lorry cost to OMBM if hired 200 days a year at illustrative rate | B37: KES | C37: =C11+C16-C17-200*C28 -> 511975 | D37: =D11+D16-D17-200*D28 -> -1650566.7 | E37: =E11+E16-E17-200*E28 -> -3705650 | F37: =D37/Inputs!$D$4 -> -12707.419
A38: Sell the lorry instead
A39: Net sale proceeds (after selling cost) | B39: KES | C39: =Inputs!C273*(1-Inputs!C9) -> 4275000 | D39: =Inputs!D273*(1-Inputs!D9) -> 4275000 | E39: =Inputs!E273*(1-Inputs!E9) -> 4275000 | F39: =D39/Inputs!$D$4 -> 32912.464
A40: Return on proceeds at declared real return | B40: KES | C40: =C39*Inputs!C5 -> 85500 | D40: =D39*Inputs!D5 -> 85500 | E40: =E39*Inputs!E5 -> 85500 | F40: =D40/Inputs!$D$4 -> 658.24929
A41: Annual gain from selling (cost saved + return on proceeds) | B41: KES | C41: =C24+C40 -> 1469975 | D41: =D24+D40 -> 1034933.3 | E41: =E24+E40 -> 777122.73 | F41: =D41/Inputs!$D$4 -> 7967.7676

Sheet Capital
A1: Capital (annual, KES). All cells are live formulas from Inputs.
A2: Line | B2: Unit | C2: Low (adverse) | D2: Base | E2: High (favourable) | F2: Base in USD | G2: Note
A3: Capital base from owner data (market / replacement values, mostly ASSUMED)
A4: Land: acres x price per acre | B4: KES | C4: =Inputs!C11*Inputs!C12 -> 8050000 | D4: =Inputs!D11*Inputs!D12 -> 11500000 | E4: =Inputs!E11*Inputs!E12 -> 16100000 | F4: =D4/Inputs!$D$4 -> 88536.454 | G4: Owned outright; opportunity cost only
A5: Water pans (sunk; inside land value) | B5: KES | C5: =Inputs!C17 -> 0 | D5: =Inputs!D17 -> 0 | E5: =Inputs!E17 -> 0 | F5: =D5/Inputs!$D$4 -> 0
A6: Farm structures | B6: KES | C6: =Inputs!C13 -> 2000000 | D6: =Inputs!D13 -> 2000000 | E6: =Inputs!E13 -> 2000000 | F6: =D6/Inputs!$D$4 -> 15397.644
A7: Cattle | B7: KES | C7: =Cattle!C19 -> 600000 | D7: =Cattle!D19 -> 600000 | E7: =Cattle!E19 -> 600000 | F7: =D7/Inputs!$D$4 -> 4619.2932
A8: Sheep | B8: KES | C8: =Sheep!C16 -> 300000 | D8: =Sheep!D16 -> 300000 | E8: =Sheep!E16 -> 300000 | F8: =D8/Inputs!$D$4 -> 2309.6466
A9: Goats | B9: KES | C9: =Goats!C16 -> 65000 | D9: =Goats!D16 -> 65000 | E9: =Goats!E16 -> 65000 | F9: =D9/Inputs!$D$4 -> 500.42344
A10: Poultry | B10: KES | C10: =Poultry!C261 -> 1230000 | D10: =Poultry!D261 -> 1230000 | E10: =Poultry!E261 -> 1230000 | F10: =D10/Inputs!$D$4 -> 9469.5512
A11: All animals | B11: KES | C11: =SUM(C7:C10) -> 2195000 | D11: =SUM(D7:D10) -> 2195000 | E11: =SUM(E7:E10) -> 2195000 | F11: =D11/Inputs!$D$4 -> 16898.914
A12: Lorry | B12: KES | C12: =Inputs!C273 -> 4500000 | D12: =Inputs!D273 -> 4500000 | E12: =Inputs!E273 -> 4500000 | F12: =D12/Inputs!$D$4 -> 34644.699
A13: Feed and drug stores on hand | B13: KES | C13: =Inputs!C67/12*(Farm_PnL!C59+Farm_PnL!C61) -> 2055122.4 | D13: =Inputs!D67/12*(Farm_PnL!D59+Farm_PnL!D61) -> 1577155.8 | E13: =Inputs!E67/12*(Farm_PnL!E59+Farm_PnL!E61) -> 1266930.6 | F13: =D13/Inputs!$D$4 -> 12142.242
A14: TOTAL capital (land + pans + structures + animals + lorry + stores) | B14: KES | C14: =C4+C5+C6+C11+C12+C13 -> 18800122 | D14: =D4+D5+D6+D11+D12+D13 -> 21772156 | E14: =E4+E5+E6+E11+E12+E13 -> 26061931 | F14: =D14/Inputs!$D$4 -> 167619.95
A15: Capital excluding land (the operating base) | B15: KES | C15: =C14-C4 -> 10750122 | D15: =D14-D4 -> 10272156 | E15: =E14-E4 -> 9961930.6 | F15: =D15/Inputs!$D$4 -> 79083.5
A16: Capital excluding land and lorry | B16: KES | C16: =C15-C12 -> 6250122.4 | D16: =D15-D12 -> 5772155.8 | E16: =E15-E12 -> 5461930.6 | F16: =D16/Inputs!$D$4 -> 44438.8
A17: Ambiguity test: is KES 2m structures only or total capital?
A18: Land + animals + lorry (everything except structures) | B18: KES | C18: =C4+C11+C12 -> 14745000 | D18: =D4+D11+D12 -> 18195000 | E18: =E4+E11+E12 -> 22795000 | F18: =D18/Inputs!$D$4 -> 140080.07
A19: Could KES 2m be TOTAL capital? | B19: text | C19: =IF(C18>Inputs!C13,"No: land, animals and lorry alone exceed KES 2m","Possible") -> No: land, animals and lorry alone exceed KES 2m | D19: =IF(D18>Inputs!D13,"No: land, animals and lorry alone exceed KES 2m","Possible") -> No: land, animals and lorry alone exceed KES 2m | E19: =IF(E18>Inputs!E13,"No: land, animals and lorry alone exceed KES 2m","Possible") -> No: land, animals and lorry alone exceed KES 2m
A20: Animals alone vs KES 2m | B20: text | C20: =IF(C11>Inputs!C13,"Animals alone exceed KES 2m","Animals below KES 2m") -> Animals alone exceed KES 2m | D20: =IF(D11>Inputs!D13,"Animals alone exceed KES 2m","Animals below KES 2m") -> Animals alone exceed KES 2m | E20: =IF(E11>Inputs!E13,"Animals alone exceed KES 2m","Animals below KES 2m") -> Animals alone exceed KES 2m
A21: Returns
A22: OMBM / capital excluding land | B22: % | C22: =Farm_PnL!C46/C15 -> -0.43547119 | D22: =Farm_PnL!D46/D15 -> -0.14921975 | E22: =Farm_PnL!E46/E15 -> 0.15961887
A23: OMBM / total capital | B23: % | C23: =Farm_PnL!C46/C14 -> -0.24900735 | D23: =Farm_PnL!D46/D14 -> -0.070402239 | E23: =Farm_PnL!E46/E14 -> 0.061012829
A24: Land as share of total capital | B24: % | C24: =C4/C14 -> 0.4281887 | D24: =D4/D14 -> 0.52819758 | E24: =E4/E14 -> 0.6177593

Sheet Overhead
A1: Control and management overhead: PLAN generic structure vs right-sized for this farm (KES/yr). ASSUMED quotes, unchanged from v1. Blue = editable.
A2: Item | B2: Class | C2: PLAN generic KES/yr | D2: Right-sized KES/yr | E2: Treatment | F2: Generic USD | G2: Right-sized USD | H2: Note
A3: External bookkeeper (remote, monthly) | B3: Control | C3: 72000 | D3: 48000 | E3: KEEP (non-waivable) | F3: =C3/Inputs!$D$4 -> 554.31519 | G3: =D3/Inputs!$D$4 -> 369.54346 | H3: KES 6k vs 4k per month; owner-only vendor creation, M-Pesa/bank feeds go to owner
A4: Randomised spot-counts | B4: Control | C4: 60000 | D4: 18000 | E4: KEEP, cheaper | F4: =C4/Inputs!$D$4 -> 461.92932 | G4: =D4/Inputs!$D$4 -> 138.5788 | H4: 4 audited counts vs 6 neighbour/para-vet/representative counts, randomised, photo + tally
A5: Quarterly non-preparer reconciliation + annual accountant review | B5: Control | C5: 80000 | D5: 36000 | E5: KEEP, scaled | F5: =C5/Inputs!$D$4 -> 615.90577 | G5: =D5/Inputs!$D$4 -> 277.15759 | H5: Accountant reviews bookkeeper's M-Pesa/bank reconciliation once a quarter, short annual review
A6: Consultant agronomist and stockman backstop | B6: Control | C6: 120000 | D6: 24000 | E6: BUY BY THE HOUR | F6: =C6/Inputs!$D$4 -> 923.85865 | G6: =D6/Inputs!$D$4 -> 184.77173 | H6: ~6 visits/yr at ~KES 4k, on call, instead of a retainer
A7: Farm Model upkeep | B7: Control | C7: 60000 | D7: 0 | E7: DROP | F7: =C7/Inputs!$D$4 -> 461.92932 | G7: =D7/Inputs!$D$4 -> 0 | H7: Owner or bookkeeper maintains this workbook
A8: Representative / steward | B8: Control | C8: 120000 | D8: 36000 | E8: KEEP, cheaper | F8: =C8/Inputs!$D$4 -> 923.85865 | G8: =D8/Inputs!$D$4 -> 277.15759 | H8: Trusted unrelated local person with second mandate, KES 3k/month stipend
A9: Hotline | B9: Control | C9: 12000 | D9: 0 | E9: DROP | F9: =C9/Inputs!$D$4 -> 92.385865 | G9: =D9/Inputs!$D$4 -> 0 | H9: WhatsApp/SMS to owner and representative
A10: Fidelity premium | B10: Control | C10: 20000 | D10: 0 | E10: DROP | F10: =C10/Inputs!$D$4 -> 153.97644 | G10: =D10/Inputs!$D$4 -> 0 | H10: Staff do not handle cash; sales proceeds paid to owner till/M-Pesa
A11: Entity and legal (amortised 3 yrs) | B11: Control | C11: 50000 | D11: 15000 | E11: KEEP, scaled | F11: =C11/Inputs!$D$4 -> 384.9411 | G11: =D11/Inputs!$D$4 -> 115.48233 | H11: Lawyer hours: staff contracts, fraud-response one-pager, title/lease advice (separate)
A12: GSM alarms and sensors (amortised) | B12: Control | C12: 20000 | D12: 0 | E12: DROP | F12: =C12/Inputs!$D$4 -> 153.97644 | G12: =D12/Inputs!$D$4 -> 0 | H12: Revisit if layers move to a closed brooder/house
A13: Data store, geotag/camera tooling (amortised) | B13: Control | C13: 20000 | D13: 11000 | E13: KEEP, cheap | F13: =C13/Inputs!$D$4 -> 153.97644 | G13: =D13/Inputs!$D$4 -> 84.687043 | H13: Smartphone camera + shared sheet + bundles
A14: Coordinator | B14: Control | C14: 180000 | D14: 0 | E14: DROP | F14: =C14/Inputs!$D$4 -> 1385.788 | G14: =D14/Inputs!$D$4 -> 0 | H14: Owner is coordinator at this scale
... A16: Ad hoc consultants | B16: Control | C16: 80000 | D16: 0 | E16: DROP | F16: =C16/Inputs!$D$4 -> 615.90577 | G16: =D16/Inputs!$D$4 -> 0 | H16: Covered by hourly consultant line above
A17: Total control-and-oversight cost | C17: =SUM(C3:C16) -> 994000 | D17: =SUM(D3:D16) -> 188000 | F17: =C17/Inputs!$D$4 -> 7652.6291 | G17: =D17/Inputs!$D$4 -> 1447.3786
A18: Memo: only the core items (bookkeeper, spot-counts, reconciliation/review, representative, legal) | C18: =C3+C4+C5+C8+C11 -> 382000 | D18: =D3+D4+D5+D8+D11 -> 153000 | F18: =C18/Inputs!$D$4 -> 2940.95 | G18: =D18/Inputs!$D$4 -> 1177.9198
A20: Management cost (reported separately, B10)
A21: Manager (KES 35k/month) | B21: Management | C21: 420000 | D21: 0 | E21: DROP | F21: =C21/Inputs!$D$4 -> 3233.5053 | G21: =D21/Inputs!$D$4 -> 0 | H21: Local livestock manager pay assumed; no source. Existing 3 staff + owner replace this
A22: Deputy (KES 20k/month) | B22: Management | C22: 240000 | D22: 0 | E22: DROP | F22: =C22/Inputs!$D$4 -> 1847.7173 | G22: =D22/Inputs!$D$4 -> 0 | H22: Assumed
A23: Supervisor stipend uplift (working supervisor accountable for daily tallies) | B23: Management | C23: 0 | D23: 72000 | E23: ADD | F23: =C23/Inputs!$D$4 -> 0 | G23: =D23/Inputs!$D$4 -> 554.31519 | H23: KES 6k/month on top of staff 1 pay on Labour sheet, tied to tally completeness
A24: Total management cost | C24: =SUM(C21:C23) -> 660000 | D24: =SUM(D21:D23) -> 72000 | F24: =C24/Inputs!$D$4 -> 5081.2226 | G24: =D24/Inputs!$D$4 -> 554.31519
A25: TOTAL overhead (controls + management) | C25: =C17+C24 -> 1654000 | D25: =D17+D24 -> 260000 | F25: =C25/Inputs!$D$4 -> 12733.852 | G25: =D25/Inputs!$D$4 -> 2001.6937

Sheet Farm_PnL
A1: Farm_PnL (annual, KES). All cells are live formulas from Inputs.
A2: Line | B2: Unit | C2: Low (adverse) | D2: Base | E2: High (favourable) | F2: Base in USD | G2: Note
A3: Revenue
A4: Cattle and dairy | B4: KES | C4: =Cattle!C8 -> 308080 | D4: =Cattle!D8 -> 444800 | E4: =Cattle!E8 -> 676450 | F4: =D4/Inputs!$D$4 -> 3424.4361
A5: Sheep | B5: KES | C5: =Sheep!C7 -> 140616 | D5: =Sheep!D7 -> 228480 | E5: =Sheep!E7 -> 350784 | F5: =D5/Inputs!$D$4 -> 1759.0269
A6: Goats | B6: KES | C6: =Goats!C7 -> 43120 | D6: =Goats!D7 -> 62400 | E6: =Goats!E7 -> 88948.8 | F6: =D6/Inputs!$D$4 -> 480.4065
A7: Sasso | B7: KES | C7: =Poultry!C14 -> 596280 | D7: =Poultry!D14 -> 896500 | E7: =Poultry!E14 -> 1268720 | F7: =D7/Inputs!$D$4 -> 6901.994
A8: Kuroiler | B8: KES | C8: =Poultry!C44 -> 596280 | D8: =Poultry!D44 -> 896500 | E8: =Poultry!E44 -> 1268720 | F8: =D8/Inputs!$D$4 -> 6901.994
A9: Rainbow | B9: KES | C9: =Poultry!C74 -> 596280 | D9: =Poultry!D74 -> 896500 | E9: =Poultry!E74 -> 1268720 | F9: =D9/Inputs!$D$4 -> 6901.994
A10: Kebro | B10: KES | C10: =Poultry!C104 -> 596280 | D10: =Poultry!D104 -> 896500 | E10: =Poultry!E104 -> 1268720 | F10: =D10/Inputs!$D$4 -> 6901.994
A11: Ducks | B11: KES | C11: =Poultry!C134 -> 134400 | D11: =Poultry!D134 -> 176000 | E11: =Poultry!E134 -> 254800 | F11: =D11/Inputs!$D$4 -> 1354.9927
A12: Geese | B12: KES | C12: =Poultry!C164 -> 82000 | D12: =Poultry!D164 -> 123200 | E12: =Poultry!E164 -> 182000 | F12: =D12/Inputs!$D$4 -> 948.49488
A13: Turkeys | B13: KES | C13: =Poultry!C194 -> 67200 | D13: =Poultry!D194 -> 89250 | E13: =Poultry!E194 -> 113400 | F13: =D13/Inputs!$D$4 -> 687.11987
A14: Guinea fowl | B14: KES | C14: =Poultry!C224 -> 88800 | D14: =Poultry!D224 -> 144000 | E14: =Poultry!E224 -> 255000 | F14: =D14/Inputs!$D$4 -> 1108.6304
A15: Total revenue | B15: KES | C15: =C4+C5+C6+C7+C8+C9+C10+C11+C12+C13+C14 -> 3249336 | D15: =D4+D5+D6+D7+D8+D9+D10+D11+D12+D13+D14 -> 4854130 | E15: =E4+E5+E6+E7+E8+E9+E10+E11+E12+E13+E14 -> 6996262.8 | F15: =D15/Inputs!$D$4 -> 37371.083
A16: Memo: egg revenue | B16: KES | C16: =Poultry!C251 -> 1013760 | D16: =Poultry!D251 -> 1746000 | E16: =Poultry!E251 -> 2527200 | F16: =D16/Inputs!$D$4 -> 13442.143
A17: Memo: all poultry revenue | B17: KES | C17: =Poultry!C253 -> 2757520 | D17: =Poultry!D253 -> 4118450 | E17: =Poultry!E253 -> 5880080 | F17: =D17/Inputs!$D$4 -> 31707.214
A18: Gross margin by enterprise
A19: Cattle and dairy | B19: KES | C19: =Cattle!C17 -> -63160 | D19: =Cattle!D17 -> 107600 | E19: =Cattle!E17 -> 329400 | F19: =D19/Inputs!$D$4 -> 828.39326
A20: Sheep | B20: KES | C20: =Sheep!C14 -> 17179.04 | D20: =Sheep!D14 -> 119340.8 | E20: =Sheep!E14 -> 255260.48 | F20: =D20/Inputs!$D$4 -> 918.78359
A21: Goats | B21: KES | C21: =Goats!C14 -> 17532.8 | D21: =Goats!D14 -> 39904 | E21: =Goats!E14 -> 69280.336 | F21: =D21/Inputs!$D$4 -> 307.2138
A22: Sasso | B22: KES | C22: =Poultry!C26 -> -427996.43 | D22: =Poultry!D26 -> 86169.503 | E22: =Poultry!E26 -> 600246.61 | F22: =D22/Inputs!$D$4 -> 663.40367
A23: Kuroiler | B23: KES | C23: =Poultry!C56 -> -427996.43 | D23: =Poultry!D56 -> 86169.503 | E23: =Poultry!E56 -> 600246.61 | F23: =D23/Inputs!$D$4 -> 663.40367
A24: Rainbow | B24: KES | C24: =Poultry!C86 -> -427996.43 | D24: =Poultry!D86 -> 86169.503 | E24: =Poultry!E86 -> 600246.61 | F24: =D24/Inputs!$D$4 -> 663.40367
A25: Kebro | B25: KES | C25: =Poultry!C116 -> -427996.43 | D25: =Poultry!D116 -> 86169.503 | E25: =Poultry!E116 -> 600246.61 | F25: =D25/Inputs!$D$4 -> 663.40367
A26: Ducks | B26: KES | C26: =Poultry!C146 -> -26320 | D26: =Poultry!D146 -> 45560 | E26: =Poultry!E146 -> 147613.14 | F26: =D26/Inputs!$D$4 -> 350.75833
A27: Geese | B27: KES | C27: =Poultry!C176 -> 11471.429 | D27: =Poultry!D176 -> 65622 | E27: =Poultry!E176 -> 133068.57 | F27: =D27/Inputs!$D$4 -> 505.2121
A28: Turkeys | B28: KES | C28: =Poultry!C206 -> 3454.2857 | D28: =Poultry!D206 -> 36030 | E28: =Poultry!E206 -> 72258 | F28: =D28/Inputs!$D$4 -> 277.38856
A29: Guinea fowl | B29: KES | C29: =Poultry!C236 -> -10381.071 | D29: =Poultry!D236 -> 60090 | E29: =Poultry!E236 -> 183567.86 | F29: =D29/Inputs!$D$4 -> 462.62222
A30: Total gross margin | B30: KES | C30: =C19+C20+C21+C22+C23+C24+C25+C26+C27+C28+C29 -> -1762209.2 | D30: =D19+D20+D21+D22+D23+D24+D25+D26+D27+D28+D29 -> 818824.81 | E30: =E19+E20+E21+E22+E23+E24+E25+E26+E27+E28+E29 -> 3591434.8 | F30: =D30/Inputs!$D$4 -> 6303.9865
A31: Total variable costs | B31: KES | C31: =Cattle!C16+Sheep!C13+Goats!C13+Poultry!C254 -> 5011545.2 | D31: =Cattle!D16+Sheep!D13+Goats!D13+Poultry!D254 -> 4035305.2 | E31: =Cattle!E16+Sheep!E13+Goats!E13+Poultry!E254 -> 3404828 | F31: =D31/Inputs!$D$4 -> 31067.097
A32: Labour and fixed costs
A33: Hired labour (3 staff at 22,000 + statutory + casuals) | B33: KES | C33: =Labour!C19 -> 911684.38 | D33: =Labour!D19 -> 868200 | E33: =Labour!E19 -> 865700 | F33: =D33/Inputs!$D$4 -> 6684.1173
A34: Appointed vet: weekly visit fees | B34: KES | C34: =Inputs!C263*Inputs!C264 -> 208000 | D34: =Inputs!D263*Inputs!D264 -> 156000 | E34: =Inputs!E263*Inputs!E264 -> 104000 | F34: =D34/Inputs!$D$4 -> 1201.0162
A35: Water and power | B35: KES | C35: =Inputs!C266 -> 70000 | D35: =Inputs!D266 -> 60000 | E35: =Inputs!E266 -> 50000 | F35: =D35/Inputs!$D$4 -> 461.92932
A36: Transport and communications | B36: KES | C36: =Inputs!C267 -> 55000 | D36: =Inputs!D267 -> 48000 | E36: =Inputs!E267 -> 40000 | F36: =D36/Inputs!$D$4 -> 369.54346
A37: Licences, permits, cess | B37: KES | C37: =Inputs!C268 -> 10000 | D37: =Inputs!D268 -> 10000 | E37: =Inputs!E268 -> 10000 | F37: =D37/Inputs!$D$4 -> 76.988221
A38: Land rent and rates (owner: nil) | B38: KES | C38: =Inputs!C16 -> 0 | D38: =Inputs!D16 -> 0 | E38: =Inputs!E16 -> 0 | F38: =D38/Inputs!$D$4 -> 0
A39: Repairs and maintenance of structures | B39: KES | C39: =Inputs!C13*Inputs!C15 -> 80000 | D39: =Inputs!D13*Inputs!D15 -> 60000 | E39: =Inputs!E13*Inputs!E15 -> 40000 | F39: =D39/Inputs!$D$4 -> 461.92932
A40: Depreciation of structures | B40: KES | C40: =Inputs!C13/Inputs!C14 -> 200000 | D40: =Inputs!D13/Inputs!D14 -> 200000 | E40: =Inputs!E13/Inputs!E14 -> 200000 | F40: =D40/Inputs!$D$4 -> 1539.7644
A41: Stock capital (all species) | B41: KES | C41: =Cattle!C19+Sheep!C16+Goats!C16+Poultry!C261 -> 2195000 | D41: =Cattle!D19+Sheep!D16+Goats!D16+Poultry!D261 -> 2195000 | E41: =Cattle!E19+Sheep!E16+Goats!E16+Poultry!E261 -> 2195000 | F41: =D41/Inputs!$D$4 -> 16898.914
A42: Insurance on stock | B42: KES | C42: =C41*Inputs!C269 -> 0 | D42: =D41*Inputs!D269 -> 0 | E42: =E41*Inputs!E269 -> 0 | F42: =D42/Inputs!$D$4 -> 0
A43: Lorry: net cost (standing + running - credit, depreciation incl.) | B43: KES | C43: =Lorry!C24 -> 1384475 | D43: =Lorry!D24 -> 949433.33 | E43: =Lorry!E24 -> 691622.73 | F43: =D43/Inputs!$D$4 -> 7309.5183
A44: Total labour + fixed costs | B44: KES | C44: =C33+C34+C35+C36+C37+C38+C39+C40+C42+C43 -> 2919159.4 | D44: =D33+D34+D35+D36+D37+D38+D39+D40+D42+D43 -> 2351633.3 | E44: =E33+E34+E35+E36+E37+E38+E39+E40+E42+E43 -> 2001322.7 | F44: =D44/Inputs!$D$4 -> 18104.807
A45: Result
A46: OMBM: operating margin before management and controls | B46: KES | C46: =C30-C44 -> -4681368.6 | D46: =D30-D44 -> -1532808.5 | E46: =E30-E44 -> 1590112.1 | F46: =D46/Inputs!$D$4 -> -11800.82 | G46: B10 definition; owner time excluded (priced in B12); no land rent or rates charged
A47: OMBM as % of revenue | B47: % | C47: =IF(C15=0,0,C46/C15) -> -1.4407155 | D47: =IF(D15=0,0,D46/D15) -> -0.3157741 | E47: =IF(E15=0,0,E46/E15) -> 0.22728021
A48: OMBM if the lorry did not exist (lorry net cost removed) | B48: KES | C48: =C46+C43 -> -3296893.6 | D48: =D46+D43 -> -583375.19 | E48: =E46+E43 -> 2281734.8 | F48: =D48/Inputs!$D$4 -> -4491.3018
A49: Cash margin (OMBM + non-cash depreciation of structures and lorry) | B49: KES | C49: =C46+C40+Lorry!C5 -> -4059493.6 | D49: =D46+D40+Lorry!D5 -> -995308.52 | E49: =E46+E40+Lorry!E5 -> 2071362.1 | F49: =D49/Inputs!$D$4 -> -7662.7032
A50: Contribution ratio (1 - variable cost / revenue) | B50: ratio | C50: =1-C31/C15 -> -0.54232902 | D50: =1-D31/D15 -> 0.16868621 | E50: =1-E31/E15 -> 0.51333618
A51: Gross margin per task hour (before fixed costs)
A52: Cattle and dairy | B52: KES/h | C52: =C19/(Inputs!C258*365) -> -43.260274 | D52: =D19/(Inputs!D258*365) -> 84.227006 | E52: =E19/(Inputs!E258*365) -> 282.02055
A53: Sheep | B53: KES/h | C53: =C20/(Inputs!C259*365) -> 26.147702 | D53: =D20/(Inputs!D259*365) -> 217.97406 | E53: =E20/(Inputs!E259*365) -> 537.95675
A54: Goats | B54: KES/h | C54: =C21/(Inputs!C260*365) -> 80.058447 | D54: =D21/(Inputs!D260*365) -> 218.65205 | E54: =E21/(Inputs!E260*365) -> 421.79809
A55: Four chicken breeds | B55: KES/h | C55: =Poultry!C256/(Poultry!C245/100*Inputs!C261*365) -> -469.03718 | D55: =Poultry!D256/(Poultry!D245/100*Inputs!D261*365) -> 118.04042 | E55: =Poultry!E256/(Poultry!E245/100*Inputs!E261*365) -> 996.6735
A56: Ducks, geese, turkeys, guinea fowl | B56: KES/h | C56: =Poultry!C257/((Poultry!C244-Poultry!C245)/100*Inputs!C261*365) -> -44.191491 | D56: =Poultry!D257/((Poultry!D244-Poultry!D245)/100*Inputs!D261*365) -> 525.88026 | E56: =Poultry!E257/((Poultry!E244-Poultry!E245)/100*Inputs!E261*365) -> 1649.7012
A57: Scale and capital
A58: Livestock units | B58: TLU | C58: =Inputs!C20*Inputs!C23+(Inputs!C21+Inputs!C22)*Inputs!C24+Poultry!C244*Inputs!C25 -> 35.7 | D58: =Inputs!D20*Inputs!D23+(Inputs!D21+Inputs!D22)*Inputs!D24+Poultry!D244*Inputs!D25 -> 35.7 | E58: =Inputs!E20*Inputs!E23+(Inputs!E21+Inputs!E22)*Inputs!E24+Poultry!E244*Inputs!E25 -> 35.7
A59: Purchased feed and forage | B59: KES | C59: =Cattle!C20+Sheep!C17+Goats!C17+Poultry!C258 -> 3685178.2 | D59: =Cattle!D20+Sheep!D17+Goats!D17+Poultry!D258 -> 2820650.7 | E59: =Cattle!E20+Sheep!E17+Goats!E17+Poultry!E258 -> 2255203.7 | F59: =D59/Inputs!$D$4 -> 21715.688
A60: Purchased feed as % of revenue | B60: % | C60: =C59/C15 -> 1.1341327 | D60: =D59/D15 -> 0.58108264 | E60: =E59/E15 -> 0.32234405
A61: Drugs and vet inputs (stored 6 months) | B61: KES | C61: =Cattle!C21+Sheep!C18+Goats!C18+Poultry!C260 -> 425066.67 | D61: =Cattle!D21+Sheep!D18+Goats!D18+Poultry!D260 -> 333660.87 | E61: =Cattle!E21+Sheep!E18+Goats!E18+Poultry!E260 -> 278657.45 | F61: =D61/Inputs!$D$4 -> 2568.7957
A62: Working capital: stores on hand + cash float | B62: KES | C62: =Capital!C13+Inputs!C270/12*(C33+C34+C35+C36+C37+Lorry!C25) -> 2424669.8 | D62: =Capital!D13+Inputs!D270/12*(D33+D34+D35+D36+D37+Lorry!D25) -> 1869511.3 | E62: =Capital!E13+Inputs!E270/12*(E33+E34+E35+E36+E37+Lorry!E25) -> 1513609.3 | F62: =D62/Inputs!$D$4 -> 14393.035
A63: K: operating capital at risk (stock + structures + lorry + working capital) | B63: KES | C63: =C41+Inputs!C13+Inputs!C273+C62 -> 11119670 | D63: =D41+Inputs!D13+Inputs!D273+D62 -> 10564511 | E63: =E41+Inputs!E13+Inputs!E273+E62 -> 10208609 | F63: =D63/Inputs!$D$4 -> 81334.293
A64: K without the lorry | B64: KES | C64: =C63-Inputs!C273 -> 6619669.8 | D64: =D63-Inputs!D273 -> 6064511.3 | E64: =E63-Inputs!E273 -> 5708609.3 | F64: =D64/Inputs!$D$4 -> 46689.594
A65: Land value L (opportunity cost only) | B65: KES | C65: =Capital!C4 -> 8050000 | D65: =Capital!D4 -> 11500000 | E65: =Capital!E4 -> 16100000 | F65: =D65/Inputs!$D$4 -> 88536.454
A66: Asset base (land + structures + stock + lorry) | B66: KES | C66: =C65+Inputs!C13+C41+Inputs!C273 -> 16745000 | D66: =D65+Inputs!D13+D41+Inputs!D273 -> 20195000 | E66: =E65+Inputs!E13+E41+Inputs!E273 -> 24795000 | F66: =D66/Inputs!$D$4 -> 155477.71
A67: Revenue in USD | B67: USD | C67: =C15/Inputs!C4 -> 25016.06 | D67: =D15/Inputs!D4 -> 37371.083 | E67: =E15/Inputs!E4 -> 53862.983
A68: Revenue per acre | B68: KES/acre | C68: =C15/Inputs!C11 -> 141275.48 | D68: =D15/Inputs!D11 -> 211049.13 | E68: =E15/Inputs!E11 -> 304185.34

Sheet Cash_18m
A1: 18-month cash flow, owner-operator (lorry kept). Months 1-6 run on the owner-reported 6-month feed and drug stores (no purchases); purchases start in month 7. Opening cash from Inputs. Not income: the stores are the owner's existing inventory.
A2: Line | B2: Unit | C2: M1 | D2: M2 | E2: M3 | F2: M4 | G2: M5 | H2: M6 | I2: M7 | J2: M8 | K2: M9 | L2: M10 | M2: M11 | N2: M12 | O2: M13 | P2: M14 | Q2: M15 | R2: M16 | S2: M17 | T2: M18 | U2: Total
A3: Scenario: Low (adverse)
A4: Revenue (flat monthly; no seasonality) | B4: KES | C4: =Farm_PnL!C15/12 -> 270778 | D4: =Farm_PnL!C15/12 -> 270778 | E4: =Farm_PnL!C15/12 -> 270778 | F4: =Farm_PnL!C15/12 -> 270778 | G4: =Farm_PnL!C15/12 -> 270778 | H4: =Farm_PnL!C15/12 -> 270778 | I4: =Farm_PnL!C15/12 -> 270778 | J4: =Farm_PnL!C15/12 -> 270778 | K4: =Farm_PnL!C15/12 -> 270778 | L4: =Farm_PnL!C15/12 -> 270778 | M4: =Farm_PnL!C15/12 -> 270778 | N4: =Farm_PnL!C15/12 -> 270778 | O4: =Farm_PnL!C15/12 -> 270778 | P4: =Farm_PnL!C15/12 -> 270778 | Q4: =Farm_PnL!C15/12 -> 270778 | R4: =Farm_PnL!C15/12 -> 270778 | S4: =Farm_PnL!C15/12 -> 270778 | T4: =Farm_PnL!C15/12 -> 270778 | U4: =SUM(C4:T4) -> 4874004
A5: Staff pay + statutory + casuals | B5: KES | C5: =-Farm_PnL!C33/12 -> -75973.698 | D5: =-Farm_PnL!C33/12 -> -75973.698 | E5: =-Farm_PnL!C33/12 -> -75973.698 | F5: =-Farm_PnL!C33/12 -> -75973.698 | G5: =-Farm_PnL!C33/12 -> -75973.698 | H5: =-Farm_PnL!C33/12 -> -75973.698 | I5: =-Farm_PnL!C33/12 -> -75973.698 | J5: =-Farm_PnL!C33/12 -> -75973.698 | K5: =-Farm_PnL!C33/12 -> -75973.698 | L5: =-Farm_PnL!C33/12 -> -75973.698 | M5: =-Farm_PnL!C33/12 -> -75973.698 | N5: =-Farm_PnL!C33/12 -> -75973.698 | O5: =-Farm_PnL!C33/12 -> -75973.698 | P5: =-Farm_PnL!C33/12 -> -75973.698 | Q5: =-Farm_PnL!C33/12 -> -75973.698 | R5: =-Farm_PnL!C33/12 -> -75973.698 | S5: =-Farm_PnL!C33/12 -> -75973.698 | T5: =-Farm_PnL!C33/12 -> -75973.698 | U5: =SUM(C5:T5) -> -1367526.6
A6: Weekly vet fees | B6: KES | C6: =-Farm_PnL!C34/12 -> -17333.333 | D6: =-Farm_PnL!C34/12 -> -17333.333 | E6: =-Farm_PnL!C34/12 -> -17333.333 | F6: =-Farm_PnL!C34/12 -> -17333.333 | G6: =-Farm_PnL!C34/12 -> -17333.333 | H6: =-Farm_PnL!C34/12 -> -17333.333 | I6: =-Farm_PnL!C34/12 -> -17333.333 | J6: =-Farm_PnL!C34/12 -> -17333.333 | K6: =-Farm_PnL!C34/12 -> -17333.333 | L6: =-Farm_PnL!C34/12 -> -17333.333 | M6: =-Farm_PnL!C34/12 -> -17333.333 | N6: =-Farm_PnL!C34/12 -> -17333.333 | O6: =-Farm_PnL!C34/12 -> -17333.333 | P6: =-Farm_PnL!C34/12 -> -17333.333 | Q6: =-Farm_PnL!C34/12 -> -17333.333 | R6: =-Farm_PnL!C34/12 -> -17333.333 | S6: =-Farm_PnL!C34/12 -> -17333.333 | T6: =-Farm_PnL!C34/12 -> -17333.333 | U6: =SUM(C6:T6) -> -312000
A7: Water, transport, licences, repairs, insurance | B7: KES | C7: =-(Farm_PnL!C35+Farm_PnL!C36+Farm_PnL!C37+Farm_PnL!C38+Farm_PnL!C39+Farm_PnL!C42)/12 -> -17916.667 | D7: =-(Farm_PnL!C35+Farm_PnL!C36+Farm_PnL!C37+Farm_PnL!C38+Farm_PnL!C39+Farm_PnL!C42)/12 -> -17916.667 | E7: =-(Farm_PnL!C35+Farm_PnL!C36+Farm_PnL!C37+Farm_PnL!C38+Farm_PnL!C39+Farm_PnL!C42)/12 -> -17916.667 | F7: =-(Farm_PnL!C35+Farm_PnL!C36+Farm_PnL!C37+Farm_PnL!C38+Farm_PnL!C39+Farm_PnL!C42)/12 -> -17916.667 | G7: =-(Farm_PnL!C35+Farm_PnL!C36+Farm_PnL!C37+Farm_PnL!C38+Farm_PnL!C39+Farm_PnL!C42)/12 -> -17916.667 | H7: =-(Farm_PnL!C35+Farm_PnL!C36+Farm_PnL!C37+Farm_PnL!C38+Farm_PnL!C39+Farm_PnL!C42)/12 -> -17916.667 | I7: =-(Farm_PnL!C35+Farm_PnL!C36+Farm_PnL!C37+Farm_PnL!C38+Farm_PnL!C39+Farm_PnL!C42)/12 -> -17916.667 | J7: =-(Farm_PnL!C35+Farm_PnL!C36+Farm_PnL!C37+Farm_PnL!C38+Farm_PnL!C39+Farm_PnL!C42)/12 -> -17916.667 | K7: =-(Farm_PnL!C35+Farm_PnL!C36+Farm_PnL!C37+Farm_PnL!C38+Farm_PnL!C39+Farm_PnL!C42)/12 -> -17916.667 | L7: =-(Farm_PnL!C35+Farm_PnL!C36+Farm_PnL!C37+Farm_PnL!C38+Farm_PnL!C39+Farm_PnL!C42)/12 -> -17916.667 | M7: =-(Farm_PnL!C35+Farm_PnL!C36+Farm_PnL!C37+Farm_PnL!C38+Farm_PnL!C39+Farm_PnL!C42)/12 -> -17916.667 | N7: =-(Farm_PnL!C35+Farm_PnL!C36+Farm_PnL!C37+Farm_PnL!C38+Farm_PnL!C39+Farm_PnL!C42)/12 -> -17916.667 | O7: =-(Farm_PnL!C35+Farm_PnL!C36+Farm_PnL!C37+Farm_PnL!C38+Farm_PnL!C39+Farm_PnL!C42)/12 -> -17916.667 | P7: =-(Farm_PnL!C35+Farm_PnL!C36+Farm_PnL!C37+Farm_PnL!C38+Farm_PnL!C39+Farm_PnL!C42)/12 -> -17916.667 | Q7: =-(Farm_PnL!C35+Farm_PnL!C36+Farm_PnL!C37+Farm_PnL!C38+Farm_PnL!C39+Farm_PnL!C42)/12 -> -17916.667 | R7: =-(Farm_PnL!C35+Farm_PnL!C36+Farm_PnL!C37+Farm_PnL!C38+Farm_PnL!C39+Farm_PnL!C42)/12 -> -17916.667 | S7: =-(Farm_PnL!C35+Farm_PnL!C36+Farm_PnL!C37+Farm_PnL!C38+Farm_PnL!C39+Farm_PnL!C42)/12 -> -17916.667 | T7: =-(Farm_PnL!C35+Farm_PnL!C36+Farm_PnL!C37+Farm_PnL!C38+Farm_PnL!C39+Farm_PnL!C42)/12 -> -17916.667 | U7: =SUM(C7:T7) -> -322500
A8: Lorry cash costs (net of credit; hire if any) | B8: KES | C8: =-Lorry!C25/12 -> -80216.667 | D8: =-Lorry!C25/12 -> -80216.667 | E8: =-Lorry!C25/12 -> -80216.667 | F8: =-Lorry!C25/12 -> -80216.667 | G8: =-Lorry!C25/12 -> -80216.667 | H8: =-Lorry!C25/12 -> -80216.667 | I8: =-Lorry!C25/12 -> -80216.667 | J8: =-Lorry!C25/12 -> -80216.667 | K8: =-Lorry!C25/12 -> -80216.667 | L8: =-Lorry!C25/12 -> -80216.667 | M8: =-Lorry!C25/12 -> -80216.667 | N8: =-Lorry!C25/12 -> -80216.667 | O8: =-Lorry!C25/12 -> -80216.667 | P8: =-Lorry!C25/12 -> -80216.667 | Q8: =-Lorry!C25/12 -> -80216.667 | R8: =-Lorry!C25/12 -> -80216.667 | S8: =-Lorry!C25/12 -> -80216.667 | T8: =-Lorry!C25/12 -> -80216.667 | U8: =SUM(C8:T8) -> -1443900
A9: Controls + supervisor stipend + owner travel | B9: KES | C9: =-(B12!C17+B12!C18+B12!C19)/12 -> -41666.667 | D9: =-(B12!C17+B12!C18+B12!C19)/12 -> -41666.667 | E9: =-(B12!C17+B12!C18+B12!C19)/12 -> -41666.667 | F9: =-(B12!C17+B12!C18+B12!C19)/12 -> -41666.667 | G9: =-(B12!C17+B12!C18+B12!C19)/12 -> -41666.667 | H9: =-(B12!C17+B12!C18+B12!C19)/12 -> -41666.667 | I9: =-(B12!C17+B12!C18+B12!C19)/12 -> -41666.667 | J9: =-(B12!C17+B12!C18+B12!C19)/12 -> -41666.667 | K9: =-(B12!C17+B12!C18+B12!C19)/12 -> -41666.667 | L9: =-(B12!C17+B12!C18+B12!C19)/12 -> -41666.667 | M9: =-(B12!C17+B12!C18+B12!C19)/12 -> -41666.667 | N9: =-(B12!C17+B12!C18+B12!C19)/12 -> -41666.667 | O9: =-(B12!C17+B12!C18+B12!C19)/12 -> -41666.667 | P9: =-(B12!C17+B12!C18+B12!C19)/12 -> -41666.667 | Q9: =-(B12!C17+B12!C18+B12!C19)/12 -> -41666.667 | R9: =-(B12!C17+B12!C18+B12!C19)/12 -> -41666.667 | S9: =-(B12!C17+B12!C18+B12!C19)/12 -> -41666.667 | T9: =-(B12!C17+B12!C18+B12!C19)/12 -> -41666.667 | U9: =SUM(C9:T9) -> -750000
A10: Other variable costs (chicks, brooding, packing, selling, minerals, mortality allowance) | B10: KES | C10: =-(Farm_PnL!C31-Farm_PnL!C59-Farm_PnL!C61)/12 -> -75108.361 | D10: =-(Farm_PnL!C31-Farm_PnL!C59-Farm_PnL!C61)/12 -> -75108.361 | E10: =-(Farm_PnL!C31-Farm_PnL!C59-Farm_PnL!C61)/12 -> -75108.361 | F10: =-(Farm_PnL!C31-Farm_PnL!C59-Farm_PnL!C61)/12 -> -75108.361 | G10: =-(Farm_PnL!C31-Farm_PnL!C59-Farm_PnL!C61)/12 -> -75108.361 | H10: =-(Farm_PnL!C31-Farm_PnL!C59-Farm_PnL!C61)/12 -> -75108.361 | I10: =-(Farm_PnL!C31-Farm_PnL!C59-Farm_PnL!C61)/12 -> -75108.361 | J10: =-(Farm_PnL!C31-Farm_PnL!C59-Farm_PnL!C61)/12 -> -75108.361 | K10: =-(Farm_PnL!C31-Farm_PnL!C59-Farm_PnL!C61)/12 -> -75108.361 | L10: =-(Farm_PnL!C31-Farm_PnL!C59-Farm_PnL!C61)/12 -> -75108.361 | M10: =-(Farm_PnL!C31-Farm_PnL!C59-Farm_PnL!C61)/12 -> -75108.361 | N10: =-(Farm_PnL!C31-Farm_PnL!C59-Farm_PnL!C61)/12 -> -75108.361 | O10: =-(Farm_PnL!C31-Farm_PnL!C59-Farm_PnL!C61)/12 -> -75108.361 | P10: =-(Farm_PnL!C31-Farm_PnL!C59-Farm_PnL!C61)/12 -> -75108.361 | Q10: =-(Farm_PnL!C31-Farm_PnL!C59-Farm_PnL!C61)/12 -> -75108.361 | R10: =-(Farm_PnL!C31-Farm_PnL!C59-Farm_PnL!C61)/12 -> -75108.361 | S10: =-(Farm_PnL!C31-Farm_PnL!C59-Farm_PnL!C61)/12 -> -75108.361 | T10: =-(Farm_PnL!C31-Farm_PnL!C59-Farm_PnL!C61)/12 -> -75108.361 | U10: =SUM(C10:T10) -> -1351950.5
A11: Feed and drugs purchased (nil while 6-month stores last) | B11: KES | C11: =IF(1<=Inputs!$D$67,0,-(Farm_PnL!C59+Farm_PnL!C61)/12) -> 0 | D11: =IF(2<=Inputs!$D$67,0,-(Farm_PnL!C59+Farm_PnL!C61)/12) -> 0 | E11: =IF(3<=Inputs!$D$67,0,-(Farm_PnL!C59+Farm_PnL!C61)/12) -> 0 | F11: =IF(4<=Inputs!$D$67,0,-(Farm_PnL!C59+Farm_PnL!C61)/12) -> 0 | G11: =IF(5<=Inputs!$D$67,0,-(Farm_PnL!C59+Farm_PnL!C61)/12) -> 0 | H11: =IF(6<=Inputs!$D$67,0,-(Farm_PnL!C59+Farm_PnL!C61)/12) -> 0 | I11: =IF(7<=Inputs!$D$67,0,-(Farm_PnL!C59+Farm_PnL!C61)/12) -> -342520.41 | J11: =IF(8<=Inputs!$D$67,0,-(Farm_PnL!C59+Farm_PnL!C61)/12) -> -342520.41 | K11: =IF(9<=Inputs!$D$67,0,-(Farm_PnL!C59+Farm_PnL!C61)/12) -> -342520.41 | L11: =IF(10<=Inputs!$D$67,0,-(Farm_PnL!C59+Farm_PnL!C61)/12) -> -342520.41 | M11: =IF(11<=Inputs!$D$67,0,-(Farm_PnL!C59+Farm_PnL!C61)/12) -> -342520.41 | N11: =IF(12<=Inputs!$D$67,0,-(Farm_PnL!C59+Farm_PnL!C61)/12) -> -342520.41 | O11: =IF(13<=Inputs!$D$67,0,-(Farm_PnL!C59+Farm_PnL!C61)/12) -> -342520.41 | P11: =IF(14<=Inputs!$D$67,0,-(Farm_PnL!C59+Farm_PnL!C61)/12) -> -342520.41 | Q11: =IF(15<=Inputs!$D$67,0,-(Farm_PnL!C59+Farm_PnL!C61)/12) -> -342520.41 | R11: =IF(16<=Inputs!$D$67,0,-(Farm_PnL!C59+Farm_PnL!C61)/12) -> -342520.41 | S11: =IF(17<=Inputs!$D$67,0,-(Farm_PnL!C59+Farm_PnL!C61)/12) -> -342520.41 | T11: =IF(18<=Inputs!$D$67,0,-(Farm_PnL!C59+Farm_PnL!C61)/12) -> -342520.41 | U11: =SUM(C11:T11) -> -4110244.9
A12: Net cash flow | B12: KES | C12: =SUM(C4:C11) -> -37437.393 | D12: =SUM(D4:D11) -> -37437.393 | E12: =SUM(E4:E11) -> -37437.393 | F12: =SUM(F4:F11) -> -37437.393 | G12: =SUM(G4:G11) -> -37437.393 | H12: =SUM(H4:H11) -> -37437.393 | I12: =SUM(I4:I11) -> -379957.8 | J12: =SUM(J4:J11) -> -379957.8 | ... T12: =SUM(T4:T11) -> -379957.8 | U12: =SUM(C12:T12) -> -4784118
A13: Cumulative cash (incl. opening cash) | B13: KES | C13: =Inputs!C271+C12 -> -37437.393 | D13: =C13+D12 -> -74874.785 | E13: =D13+E12 -> -112312.18 | F13: =E13+F12 -> -149749.57 | G13: =F13+G12 -> -187186.96 | H13: =G13+H12 -> -224624.36 | I13: =H13+I12 -> -604582.16 | J13: =I13+J12 -> -984539.96 | K13: =J13+K12 -> -1364497.8 | ... T13: =S13+T12 -> -4784118
A14: Lowest cumulative cash / month of low point | C14: =MIN(C13:T13) -> -4784118 | D14: =MATCH(C14,C13:T13,0) -> 18
A16: Scenario: Base
A17: Revenue (flat monthly; no seasonality) | B17: KES | C17: =Farm_PnL!D15/12 -> 404510.83 | D17: =Farm_PnL!D15/12 -> 404510.83 | E17: =Farm_PnL!D15/12 -> 404510.83 | F17: =Farm_PnL!D15/12 -> 404510.83 | G17: =Farm_PnL!D15/12 -> 404510.83 | H17: =Farm_PnL!D15/12 -> 404510.83 | I17: =Farm_PnL!D15/12 -> 404510.83 | J17: =Farm_PnL!D15/12 -> 404510.83 | K17: =Farm_PnL!D15/12 -> 404510.83 | L17: =Farm_PnL!D15/12 -> 404510.83 | M17: =Farm_PnL!D15/12 -> 404510.83 | N17: =Farm_PnL!D15/12 -> 404510.83 | O17: =Farm_PnL!D15/12 -> 404510.83 | P17: =Farm_PnL!D15/12 -> 404510.83 | Q17: =Farm_PnL!D15/12 -> 404510.83 | R17: =Farm_PnL!D15/12 -> 404510.83 | S17: =Farm_PnL!D15/12 -> 404510.83 | T17: =Farm_PnL!D15/12 -> 404510.83 | U17: =SUM(C17:T17) -> 7281195
A18: Staff pay + statutory + casuals | B18: KES | C18: =-Farm_PnL!D33/12 -> -72350 | D18: =-Farm_PnL!D33/12 -> -72350 | E18: =-Farm_PnL!D33/12 -> -72350 | F18: =-Farm_PnL!D33/12 -> -72350 | G18: =-Farm_PnL!D33/12 -> -72350 | H18: =-Farm_PnL!D33/12 -> -72350 | I18: =-Farm_PnL!D33/12 -> -72350 | J18: =-Farm_PnL!D33/12 -> -72350 | K18: =-Farm_PnL!D33/12 -> -72350 | L18: =-Farm_PnL!D33/12 -> -72350 | M18: =-Farm_PnL!D33/12 -> -72350 | N18: =-Farm_PnL!D33/12 -> -72350 | O18: =-Farm_PnL!D33/12 -> -72350 | P18: =-Farm_PnL!D33/12 -> -72350 | Q18: =-Farm_PnL!D33/12 -> -72350 | R18: =-Farm_PnL!D33/12 -> -72350 | S18: =-Farm_PnL!D33/12 -> -72350 | T18: =-Farm_PnL!D33/12 -> -72350 | U18: =SUM(C18:T18) -> -1302300
A19: Weekly vet fees | B19: KES | C19: =-Farm_PnL!D34/12 -> -13000 | D19: =-Farm_PnL!D34/12 -> -13000 | E19: =-Farm_PnL!D34/12 -> -13000 | F19: =-Farm_PnL!D34/12 -> -13000 | G19: =-Farm_PnL!D34/12 -> -13000 | H19: =-Farm_PnL!D34/12 -> -13000 | I19: =-Farm_PnL!D34/12 -> -13000 | J19: =-Farm_PnL!D34/12 -> -13000 | K19: =-Farm_PnL!D34/12 -> -13000 | L19: =-Farm_PnL!D34/12 -> -13000 | M19: =-Farm_PnL!D34/12 -> -13000 | N19: =-Farm_PnL!D34/12 -> -13000 | O19: =-Farm_PnL!D34/12 -> -13000 | P19: =-Farm_PnL!D34/12 -> -13000 | Q19: =-Farm_PnL!D34/12 -> -13000 | R19: =-Farm_PnL!D34/12 -> -13000 | S19: =-Farm_PnL!D34/12 -> -13000 | T19: =-Farm_PnL!D34/12 -> -13000 | U19: =SUM(C19:T19) -> -234000
A20: Water, transport, licences, repairs, insurance | B20: KES | C20: =-(Farm_PnL!D35+Farm_PnL!D36+Farm_PnL!D37+Farm_PnL!D38+Farm_PnL!D39+Farm_PnL!D42)/12 -> -14833.333 | D20: =-(Farm_PnL!D35+Farm_PnL!D36+Farm_PnL!D37+Farm_PnL!D38+Farm_PnL!D39+Farm_PnL!D42)/12 -> -14833.333 | E20: =-(Farm_PnL!D35+Farm_PnL!D36+Farm_PnL!D37+Farm_PnL!D38+Farm_PnL!D39+Farm_PnL!D42)/12 -> -14833.333 | F20: =-(Farm_PnL!D35+Farm_PnL!D36+Farm_PnL!D37+Farm_PnL!D38+Farm_PnL!D39+Farm_PnL!D42)/12 -> -14833.333 | G20: =-(Farm_PnL!D35+Farm_PnL!D36+Farm_PnL!D37+Farm_PnL!D38+Farm_PnL!D39+Farm_PnL!D42)/12 -> -14833.333 | H20: =-(Farm_PnL!D35+Farm_PnL!D36+Farm_PnL!D37+Farm_PnL!D38+Farm_PnL!D39+Farm_PnL!D42)/12 -> -14833.333 | I20: =-(Farm_PnL!D35+Farm_PnL!D36+Farm_PnL!D37+Farm_PnL!D38+Farm_PnL!D39+Farm_PnL!D42)/12 -> -14833.333 | J20: =-(Farm_PnL!D35+Farm_PnL!D36+Farm_PnL!D37+Farm_PnL!D38+Farm_PnL!D39+Farm_PnL!D42)/12 -> -14833.333 | K20: =-(Farm_PnL!D35+Farm_PnL!D36+Farm_PnL!D37+Farm_PnL!D38+Farm_PnL!D39+Farm_PnL!D42)/12 -> -14833.333 | L20: =-(Farm_PnL!D35+Farm_PnL!D36+Farm_PnL!D37+Farm_PnL!D38+Farm_PnL!D39+Farm_PnL!D42)/12 -> -14833.333 | M20: =-(Farm_PnL!D35+Farm_PnL!D36+Farm_PnL!D37+Farm_PnL!D38+Farm_PnL!D39+Farm_PnL!D42)/12 -> -14833.333 | N20: =-(Farm_PnL!D35+Farm_PnL!D36+Farm_PnL!D37+Farm_PnL!D38+Farm_PnL!D39+Farm_PnL!D42)/12 -> -14833.333 | O20: =-(Farm_PnL!D35+Farm_PnL!D36+Farm_PnL!D37+Farm_PnL!D38+Farm_PnL!D39+Farm_PnL!D42)/12 -> -14833.333 | P20: =-(Farm_PnL!D35+Farm_PnL!D36+Farm_PnL!D37+Farm_PnL!D38+Farm_PnL!D39+Farm_PnL!D42)/12 -> -14833.333 | Q20: =-(Farm_PnL!D35+Farm_PnL!D36+Farm_PnL!D37+Farm_PnL!D38+Farm_PnL!D39+Farm_PnL!D42)/12 -> -14833.333 | R20: =-(Farm_PnL!D35+Farm_PnL!D36+Farm_PnL!D37+Farm_PnL!D38+Farm_PnL!D39+Farm_PnL!D42)/12 -> -14833.333 | S20: =-(Farm_PnL!D35+Farm_PnL!D36+Farm_PnL!D37+Farm_PnL!D38+Farm_PnL!D39+Farm_PnL!D42)/12 -> -14833.333 | T20: =-(Farm_PnL!D35+Farm_PnL!D36+Farm_PnL!D37+Farm_PnL!D38+Farm_PnL!D39+Farm_PnL!D42)/12 -> -14833.333 | U20: =SUM(C20:T20) -> -267000
A21: Lorry cash costs (net of credit; hire if any) | B21: KES | C21: =-Lorry!D25/12 -> -50994.444 | D21: =-Lorry!D25/12 -> -50994.444 | E21: =-Lorry!D25/12 -> -50994.444 | F21: =-Lorry!D25/12 -> -50994.444 | G21: =-Lorry!D25/12 -> -50994.444 | H21: =-Lorry!D25/12 -> -50994.444 | I21: =-Lorry!D25/12 -> -50994.444 | J21: =-Lorry!D25/12 -> -50994.444 | K21: =-Lorry!D25/12 -> -50994.444 | L21: =-Lorry!D25/12 -> -50994.444 | M21: =-Lorry!D25/12 -> -50994.444 | N21: =-Lorry!D25/12 -> -50994.444 | O21: =-Lorry!D25/12 -> -50994.444 | P21: =-Lorry!D25/12 -> -50994.444 | Q21: =-Lorry!D25/12 -> -50994.444 | R21: =-Lorry!D25/12 -> -50994.444 | S21: =-Lorry!D25/12 -> -50994.444 | T21: =-Lorry!D25/12 -> -50994.444 | U21: =SUM(C21:T21) -> -917900
A22: Controls + supervisor stipend + owner travel | B22: KES | C22: =-(B12!D17+B12!D18+B12!D19)/12 -> -29666.667 | D22: =-(B12!D17+B12!D18+B12!D19)/12 -> -29666.667 | E22: =-(B12!D17+B12!D18+B12!D19)/12 -> -29666.667 | F22: =-(B12!D17+B12!D18+B12!D19)/12 -> -29666.667 | G22: =-(B12!D17+B12!D18+B12!D19)/12 -> -29666.667 | H22: =-(B12!D17+B12!D18+B12!D19)/12 -> -29666.667 | I22: =-(B12!D17+B12!D18+B12!D19)/12 -> -29666.667 | J22: =-(B12!D17+B12!D18+B12!D19)/12 -> -29666.667 | K22: =-(B12!D17+B12!D18+B12!D19)/12 -> -29666.667 | L22: =-(B12!D17+B12!D18+B12!D19)/12 -> -29666.667 | M22: =-(B12!D17+B12!D18+B12!D19)/12 -> -29666.667 | N22: =-(B12!D17+B12!D18+B12!D19)/12 -> -29666.667 | O22: =-(B12!D17+B12!D18+B12!D19)/12 -> -29666.667 | P22: =-(B12!D17+B12!D18+B12!D19)/12 -> -29666.667 | Q22: =-(B12!D17+B12!D18+B12!D19)/12 -> -29666.667 | R22: =-(B12!D17+B12!D18+B12!D19)/12 -> -29666.667 | S22: =-(B12!D17+B12!D18+B12!D19)/12 -> -29666.667 | T22: =-(B12!D17+B12!D18+B12!D19)/12 -> -29666.667 | U22: =SUM(C22:T22) -> -534000
A23: Other variable costs (chicks, brooding, packing, selling, minerals, mortality allowance) | B23: KES | C23: =-(Farm_PnL!D31-Farm_PnL!D59-Farm_PnL!D61)/12 -> -73416.136 | D23: =-(Farm_PnL!D31-Farm_PnL!D59-Farm_PnL!D61)/12 -> -73416.136 | E23: =-(Farm_PnL!D31-Farm_PnL!D59-Farm_PnL!D61)/12 -> -73416.136 | F23: =-(Farm_PnL!D31-Farm_PnL!D59-Farm_PnL!D61)/12 -> -73416.136 | G23: =-(Farm_PnL!D31-Farm_PnL!D59-Farm_PnL!D61)/12 -> -73416.136 | H23: =-(Farm_PnL!D31-Farm_PnL!D59-Farm_PnL!D61)/12 -> -73416.136 | I23: =-(Farm_PnL!D31-Farm_PnL!D59-Farm_PnL!D61)/12 -> -73416.136 | J23: =-(Farm_PnL!D31-Farm_PnL!D59-Farm_PnL!D61)/12 -> -73416.136 | K23: =-(Farm_PnL!D31-Farm_PnL!D59-Farm_PnL!D61)/12 -> -73416.136 | L23: =-(Farm_PnL!D31-Farm_PnL!D59-Farm_PnL!D61)/12 -> -73416.136 | M23: =-(Farm_PnL!D31-Farm_PnL!D59-Farm_PnL!D61)/12 -> -73416.136 | N23: =-(Farm_PnL!D31-Farm_PnL!D59-Farm_PnL!D61)/12 -> -73416.136 | O23: =-(Farm_PnL!D31-Farm_PnL!D59-Farm_PnL!D61)/12 -> -73416.136 | P23: =-(Farm_PnL!D31-Farm_PnL!D59-Farm_PnL!D61)/12 -> -73416.136 | Q23: =-(Farm_PnL!D31-Farm_PnL!D59-Farm_PnL!D61)/12 -> -73416.136 | R23: =-(Farm_PnL!D31-Farm_PnL!D59-Farm_PnL!D61)/12 -> -73416.136 | S23: =-(Farm_PnL!D31-Farm_PnL!D59-Farm_PnL!D61)/12 -> -73416.136 | T23: =-(Farm_PnL!D31-Farm_PnL!D59-Farm_PnL!D61)/12 -> -73416.136 | U23: =SUM(C23:T23) -> -1321490.5
A24: Feed and drugs purchased (nil while 6-month stores last) | B24: KES | C24: =IF(1<=Inputs!$D$67,0,-(Farm_PnL!D59+Farm_PnL!D61)/12) -> 0 | D24: =IF(2<=Inputs!$D$67,0,-(Farm_PnL!D59+Farm_PnL!D61)/12) -> 0 | E24: =IF(3<=Inputs!$D$67,0,-(Farm_PnL!D59+Farm_PnL!D61)/12) -> 0 | F24: =IF(4<=Inputs!$D$67,0,-(Farm_PnL!D59+Farm_PnL!D61)/12) -> 0 | G24: =IF(5<=Inputs!$D$67,0,-(Farm_PnL!D59+Farm_PnL!D61)/12) -> 0 | H24: =IF(6<=Inputs!$D$67,0,-(Farm_PnL!D59+Farm_PnL!D61)/12) -> 0 | I24: =IF(7<=Inputs!$D$67,0,-(Farm_PnL!D59+Farm_PnL!D61)/12) -> -262859.3 | J24: =IF(8<=Inputs!$D$67,0,-(Farm_PnL!D59+Farm_PnL!D61)/12) -> -262859.3 | K24: =IF(9<=Inputs!$D$67,0,-(Farm_PnL!D59+Farm_PnL!D61)/12) -> -262859.3 | L24: =IF(10<=Inputs!$D$67,0,-(Farm_PnL!D59+Farm_PnL!D61)/12) -> -262859.3 | M24: =IF(11<=Inputs!$D$67,0,-(Farm_PnL!D59+Farm_PnL!D61)/12) -> -262859.3 | N24: =IF(12<=Inputs!$D$67,0,-(Farm_PnL!D59+Farm_PnL!D61)/12) -> -262859.3 | O24: =IF(13<=Inputs!$D$67,0,-(Farm_PnL!D59+Farm_PnL!D61)/12) -> -262859.3 | P24: =IF(14<=Inputs!$D$67,0,-(Farm_PnL!D59+Farm_PnL!D61)/12) -> -262859.3 | Q24: =IF(15<=Inputs!$D$67,0,-(Farm_PnL!D59+Farm_PnL!D61)/12) -> -262859.3 | R24: =IF(16<=Inputs!$D$67,0,-(Farm_PnL!D59+Farm_PnL!D61)/12) -> -262859.3 | S24: =IF(17<=Inputs!$D$67,0,-(Farm_PnL!D59+Farm_PnL!D61)/12) -> -262859.3 | T24: =IF(18<=Inputs!$D$67,0,-(Farm_PnL!D59+Farm_PnL!D61)/12) -> -262859.3 | U24: =SUM(C24:T24) -> -3154311.6
A25: Net cash flow | B25: KES | C25: =SUM(C17:C24) -> 150250.25 | D25: =SUM(D17:D24) -> 150250.25 | E25: =SUM(E17:E24) -> 150250.25 | F25: =SUM(F17:F24) -> 150250.25 | G25: =SUM(G17:G24) -> 150250.25 | H25: =SUM(H17:H24) -> 150250.25 | I25: =SUM(I17:I24) -> -112609.04 | J25: =SUM(J17:J24) -> -112609.04 | ... T25: =SUM(T17:T24) -> -112609.04 | U25: =SUM(C25:T25) -> -449807
A26: Cumulative cash (incl. opening cash) | B26: KES | C26: =Inputs!D271+C25 -> 150250.25 | D26: =C26+D25 -> 300500.51 | E26: =D26+E25 -> 450750.76 | F26: =E26+F25 -> 601001.01 | G26: =F26+G25 -> 751251.26 | H26: =G26+H25 -> 901501.52 | I26: =H26+I25 -> 788892.47 | J26: =I26+J25 -> 676283.43 | K26: =J26+K25 -> 563674.39 | ... T26: =S26+T25 -> -449807
A27: Lowest cumulative cash / month of low point | C27: =MIN(C26:T26) -> -449807 | D27: =MATCH(C27,C26:T26,0) -> 18
A29: Scenario: High (favourable)
A30: Revenue (flat monthly; no seasonality) | B30: KES | C30: =Farm_PnL!E15/12 -> 583021.9 | D30: =Farm_PnL!E15/12 -> 583021.9 | E30: =Farm_PnL!E15/12 -> 583021.9 | F30: =Farm_PnL!E15/12 -> 583021.9 | G30: =Farm_PnL!E15/12 -> 583021.9 | H30: =Farm_PnL!E15/12 -> 583021.9 | I30: =Farm_PnL!E15/12 -> 583021.9 | J30: =Farm_PnL!E15/12 -> 583021.9 | K30: =Farm_PnL!E15/12 -> 583021.9 | L30: =Farm_PnL!E15/12 -> 583021.9 | M30: =Farm_PnL!E15/12 -> 583021.9 | N30: =Farm_PnL!E15/12 -> 583021.9 | O30: =Farm_PnL!E15/12 -> 583021.9 | P30: =Farm_PnL!E15/12 -> 583021.9 | Q30: =Farm_PnL!E15/12 -> 583021.9 | R30: =Farm_PnL!E15/12 -> 583021.9 | S30: =Farm_PnL!E15/12 -> 583021.9 | T30: =Farm_PnL!E15/12 -> 583021.9 | U30: =SUM(C30:T30) -> 10494394
A31: Staff pay + statutory + casuals | B31: KES | C31: =-Farm_PnL!E33/12 -> -72141.667 | D31: =-Farm_PnL!E33/12 -> -72141.667 | E31: =-Farm_PnL!E33/12 -> -72141.667 | F31: =-Farm_PnL!E33/12 -> -72141.667 | G31: =-Farm_PnL!E33/12 -> -72141.667 | H31: =-Farm_PnL!E33/12 -> -72141.667 | I31: =-Farm_PnL!E33/12 -> -72141.667 | J31: =-Farm_PnL!E33/12 -> -72141.667 | K31: =-Farm_PnL!E33/12 -> -72141.667 | L31: =-Farm_PnL!E33/12 -> -72141.667 | M31: =-Farm_PnL!E33/12 -> -72141.667 | N31: =-Farm_PnL!E33/12 -> -72141.667 | O31: =-Farm_PnL!E33/12 -> -72141.667 | P31: =-Farm_PnL!E33/12 -> -72141.667 | Q31: =-Farm_PnL!E33/12 -> -72141.667 | R31: =-Farm_PnL!E33/12 -> -72141.667 | S31: =-Farm_PnL!E33/12 -> -72141.667 | T31: =-Farm_PnL!E33/12 -> -72141.667 | U31: =SUM(C31:T31) -> -1298550
A32: Weekly vet fees | B32: KES | C32: =-Farm_PnL!E34/12 -> -8666.6667 | D32: =-Farm_PnL!E34/12 -> -8666.6667 | E32: =-Farm_PnL!E34/12 -> -8666.6667 | F32: =-Farm_PnL!E34/12 -> -8666.6667 | G32: =-Farm_PnL!E34/12 -> -8666.6667 | H32: =-Farm_PnL!E34/12 -> -8666.6667 | I32: =-Farm_PnL!E34/12 -> -8666.6667 | J32: =-Farm_PnL!E34/12 -> -8666.6667 | K32: =-Farm_PnL!E34/12 -> -8666.6667 | L32: =-Farm_PnL!E34/12 -> -8666.6667 | M32: =-Farm_PnL!E34/12 -> -8666.6667 | N32: =-Farm_PnL!E34/12 -> -8666.6667 | O32: =-Farm_PnL!E34/12 -> -8666.6667 | P32: =-Farm_PnL!E34/12 -> -8666.6667 | Q32: =-Farm_PnL!E34/12 -> -8666.6667 | R32: =-Farm_PnL!E34/12 -> -8666.6667 | S32: =-Farm_PnL!E34/12 -> -8666.6667 | T32: =-Farm_PnL!E34/12 -> -8666.6667 | U32: =SUM(C32:T32) -> -156000
A33: Water, transport, licences, repairs, insurance | B33: KES | C33: =-(Farm_PnL!E35+Farm_PnL!E36+Farm_PnL!E37+Farm_PnL!E38+Farm_PnL!E39+Farm_PnL!E42)/12 -> -11666.667 | D33: =-(Farm_PnL!E35+Farm_PnL!E36+Farm_PnL!E37+Farm_PnL!E38+Farm_PnL!E39+Farm_PnL!E42)/12 -> -11666.667 | E33: =-(Farm_PnL!E35+Farm_PnL!E36+Farm_PnL!E37+Farm_PnL!E38+Farm_PnL!E39+Farm_PnL!E42)/12 -> -11666.667 | F33: =-(Farm_PnL!E35+Farm_PnL!E36+Farm_PnL!E37+Farm_PnL!E38+Farm_PnL!E39+Farm_PnL!E42)/12 -> -11666.667 | G33: =-(Farm_PnL!E35+Farm_PnL!E36+Farm_PnL!E37+Farm_PnL!E38+Farm_PnL!E39+Farm_PnL!E42)/12 -> -11666.667 | H33: =-(Farm_PnL!E35+Farm_PnL!E36+Farm_PnL!E37+Farm_PnL!E38+Farm_PnL!E39+Farm_PnL!E42)/12 -> -11666.667 | I33: =-(Farm_PnL!E35+Farm_PnL!E36+Farm_PnL!E37+Farm_PnL!E38+Farm_PnL!E39+Farm_PnL!E42)/12 -> -11666.667 | J33: =-(Farm_PnL!E35+Farm_PnL!E36+Farm_PnL!E37+Farm_PnL!E38+Farm_PnL!E39+Farm_PnL!E42)/12 -> -11666.667 | K33: =-(Farm_PnL!E35+Farm_PnL!E36+Farm_PnL!E37+Farm_PnL!E38+Farm_PnL!E39+Farm_PnL!E42)/12 -> -11666.667 | L33: =-(Farm_PnL!E35+Farm_PnL!E36+Farm_PnL!E37+Farm_PnL!E38+Farm_PnL!E39+Farm_PnL!E42)/12 -> -11666.667 | M33: =-(Farm_PnL!E35+Farm_PnL!E36+Farm_PnL!E37+Farm_PnL!E38+Farm_PnL!E39+Farm_PnL!E42)/12 -> -11666.667 | N33: =-(Farm_PnL!E35+Farm_PnL!E36+Farm_PnL!E37+Farm_PnL!E38+Farm_PnL!E39+Farm_PnL!E42)/12 -> -11666.667 | O33: =-(Farm_PnL!E35+Farm_PnL!E36+Farm_PnL!E37+Farm_PnL!E38+Farm_PnL!E39+Farm_PnL!E42)/12 -> -11666.667 | P33: =-(Farm_PnL!E35+Farm_PnL!E36+Farm_PnL!E37+Farm_PnL!E38+Farm_PnL!E39+Farm_PnL!E42)/12 -> -11666.667 | Q33: =-(Farm_PnL!E35+Farm_PnL!E36+Farm_PnL!E37+Farm_PnL!E38+Farm_PnL!E39+Farm_PnL!E42)/12 -> -11666.667 | R33: =-(Farm_PnL!E35+Farm_PnL!E36+Farm_PnL!E37+Farm_PnL!E38+Farm_PnL!E39+Farm_PnL!E42)/12 -> -11666.667 | S33: =-(Farm_PnL!E35+Farm_PnL!E36+Farm_PnL!E37+Farm_PnL!E38+Farm_PnL!E39+Farm_PnL!E42)/12 -> -11666.667 | T33: =-(Farm_PnL!E35+Farm_PnL!E36+Farm_PnL!E37+Farm_PnL!E38+Farm_PnL!E39+Farm_PnL!E42)/12 -> -11666.667 | U33: =SUM(C33:T33) -> -210000
A34: Lorry cash costs (net of credit; hire if any) | B34: KES | C34: =-Lorry!E25/12 -> -34197.727 | D34: =-Lorry!E25/12 -> -34197.727 | E34: =-Lorry!E25/12 -> -34197.727 | F34: =-Lorry!E25/12 -> -34197.727 | G34: =-Lorry!E25/12 -> -34197.727 | H34: =-Lorry!E25/12 -> -34197.727 | I34: =-Lorry!E25/12 -> -34197.727 | J34: =-Lorry!E25/12 -> -34197.727 | K34: =-Lorry!E25/12 -> -34197.727 | L34: =-Lorry!E25/12 -> -34197.727 | M34: =-Lorry!E25/12 -> -34197.727 | N34: =-Lorry!E25/12 -> -34197.727 | O34: =-Lorry!E25/12 -> -34197.727 | P34: =-Lorry!E25/12 -> -34197.727 | Q34: =-Lorry!E25/12 -> -34197.727 | R34: =-Lorry!E25/12 -> -34197.727 | S34: =-Lorry!E25/12 -> -34197.727 | T34: =-Lorry!E25/12 -> -34197.727 | U34: =SUM(C34:T34) -> -615559.09
A35: Controls + supervisor stipend + owner travel | B35: KES | C35: =-(B12!E17+B12!E18+B12!E19)/12 -> -25666.667 | D35: =-(B12!E17+B12!E18+B12!E19)/12 -> -25666.667 | E35: =-(B12!E17+B12!E18+B12!E19)/12 -> -25666.667 | F35: =-(B12!E17+B12!E18+B12!E19)/12 -> -25666.667 | G35: =-(B12!E17+B12!E18+B12!E19)/12 -> -25666.667 | H35: =-(B12!E17+B12!E18+B12!E19)/12 -> -25666.667 | I35: =-(B12!E17+B12!E18+B12!E19)/12 -> -25666.667 | J35: =-(B12!E17+B12!E18+B12!E19)/12 -> -25666.667 | K35: =-(B12!E17+B12!E18+B12!E19)/12 -> -25666.667 | L35: =-(B12!E17+B12!E18+B12!E19)/12 -> -25666.667 | M35: =-(B12!E17+B12!E18+B12!E19)/12 -> -25666.667 | N35: =-(B12!E17+B12!E18+B12!E19)/12 -> -25666.667 | O35: =-(B12!E17+B12!E18+B12!E19)/12 -> -25666.667 | P35: =-(B12!E17+B12!E18+B12!E19)/12 -> -25666.667 | Q35: =-(B12!E17+B12!E18+B12!E19)/12 -> -25666.667 | R35: =-(B12!E17+B12!E18+B12!E19)/12 -> -25666.667 | S35: =-(B12!E17+B12!E18+B12!E19)/12 -> -25666.667 | T35: =-(B12!E17+B12!E18+B12!E19)/12 -> -25666.667 | U35: =SUM(C35:T35) -> -462000
A36: Other variable costs (chicks, brooding, packing, selling, minerals, mortality allowance) | B36: KES | C36: =-(Farm_PnL!E31-Farm_PnL!E59-Farm_PnL!E61)/12 -> -72580.571 | D36: =-(Farm_PnL!E31-Farm_PnL!E59-Farm_PnL!E61)/12 -> -72580.571 | E36: =-(Farm_PnL!E31-Farm_PnL!E59-Farm_PnL!E61)/12 -> -72580.571 | F36: =-(Farm_PnL!E31-Farm_PnL!E59-Farm_PnL!E61)/12 -> -72580.571 | G36: =-(Farm_PnL!E31-Farm_PnL!E59-Farm_PnL!E61)/12 -> -72580.571 | H36: =-(Farm_PnL!E31-Farm_PnL!E59-Farm_PnL!E61)/12 -> -72580.571 | I36: =-(Farm_PnL!E31-Farm_PnL!E59-Farm_PnL!E61)/12 -> -72580.571 | J36: =-(Farm_PnL!E31-Farm_PnL!E59-Farm_PnL!E61)/12 -> -72580.571 | K36: =-(Farm_PnL!E31-Farm_PnL!E59-Farm_PnL!E61)/12 -> -72580.571 | L36: =-(Farm_PnL!E31-Farm_PnL!E59-Farm_PnL!E61)/12 -> -72580.571 | M36: =-(Farm_PnL!E31-Farm_PnL!E59-Farm_PnL!E61)/12 -> -72580.571 | N36: =-(Farm_PnL!E31-Farm_PnL!E59-Farm_PnL!E61)/12 -> -72580.571 | O36: =-(Farm_PnL!E31-Farm_PnL!E59-Farm_PnL!E61)/12 -> -72580.571 | P36: =-(Farm_PnL!E31-Farm_PnL!E59-Farm_PnL!E61)/12 -> -72580.571 | Q36: =-(Farm_PnL!E31-Farm_PnL!E59-Farm_PnL!E61)/12 -> -72580.571 | R36: =-(Farm_PnL!E31-Farm_PnL!E59-Farm_PnL!E61)/12 -> -72580.571 | S36: =-(Farm_PnL!E31-Farm_PnL!E59-Farm_PnL!E61)/12 -> -72580.571 | T36: =-(Farm_PnL!E31-Farm_PnL!E59-Farm_PnL!E61)/12 -> -72580.571 | U36: =SUM(C36:T36) -> -1306450.3
A37: Feed and drugs purchased (nil while 6-month stores last) | B37: KES | C37: =IF(1<=Inputs!$D$67,0,-(Farm_PnL!E59+Farm_PnL!E61)/12) -> 0 | D37: =IF(2<=Inputs!$D$67,0,-(Farm_PnL!E59+Farm_PnL!E61)/12) -> 0 | E37: =IF(3<=Inputs!$D$67,0,-(Farm_PnL!E59+Farm_PnL!E61)/12) -> 0 | F37: =IF(4<=Inputs!$D$67,0,-(Farm_PnL!E59+Farm_PnL!E61)/12) -> 0 | G37: =IF(5<=Inputs!$D$67,0,-(Farm_PnL!E59+Farm_PnL!E61)/12) -> 0 | H37: =IF(6<=Inputs!$D$67,0,-(Farm_PnL!E59+Farm_PnL!E61)/12) -> 0 | I37: =IF(7<=Inputs!$D$67,0,-(Farm_PnL!E59+Farm_PnL!E61)/12) -> -211155.09 | J37: =IF(8<=Inputs!$D$67,0,-(Farm_PnL!E59+Farm_PnL!E61)/12) -> -211155.09 | K37: =IF(9<=Inputs!$D$67,0,-(Farm_PnL!E59+Farm_PnL!E61)/12) -> -211155.09 | L37: =IF(10<=Inputs!$D$67,0,-(Farm_PnL!E59+Farm_PnL!E61)/12) -> -211155.09 | M37: =IF(11<=Inputs!$D$67,0,-(Farm_PnL!E59+Farm_PnL!E61)/12) -> -211155.09 | N37: =IF(12<=Inputs!$D$67,0,-(Farm_PnL!E59+Farm_PnL!E61)/12) -> -211155.09 | O37: =IF(13<=Inputs!$D$67,0,-(Farm_PnL!E59+Farm_PnL!E61)/12) -> -211155.09 | P37: =IF(14<=Inputs!$D$67,0,-(Farm_PnL!E59+Farm_PnL!E61)/12) -> -211155.09 | Q37: =IF(15<=Inputs!$D$67,0,-(Farm_PnL!E59+Farm_PnL!E61)/12) -> -211155.09 | R37: =IF(16<=Inputs!$D$67,0,-(Farm_PnL!E59+Farm_PnL!E61)/12) -> -211155.09 | S37: =IF(17<=Inputs!$D$67,0,-(Farm_PnL!E59+Farm_PnL!E61)/12) -> -211155.09 | T37: =IF(18<=Inputs!$D$67,0,-(Farm_PnL!E59+Farm_PnL!E61)/12) -> -211155.09 | U37: =SUM(C37:T37) -> -2533861.1
A38: Net cash flow | B38: KES | C38: =SUM(C30:C37) -> 358101.94 | D38: =SUM(D30:D37) -> 358101.94 | E38: =SUM(E30:E37) -> 358101.94 | F38: =SUM(F30:F37) -> 358101.94 | G38: =SUM(G30:G37) -> 358101.94 | H38: =SUM(H30:H37) -> 358101.94 | I38: =SUM(I30:I37) -> 146946.84 | J38: =SUM(J30:J37) -> 146946.84 | ... T38: =SUM(T30:T37) -> 146946.84 | U38: =SUM(C38:T38) -> 3911973.7
A39: Cumulative cash (incl. opening cash) | B39: KES | C39: =Inputs!E271+C38 -> 358101.94 | D39: =C39+D38 -> 716203.87 | E39: =D39+E38 -> 1074305.8 | F39: =E39+F38 -> 1432407.7 | G39: =F39+G38 -> 1790509.7 | H39: =G39+H38 -> 2148611.6 | I39: =H39+I38 -> 2295558.5 | J39: =I39+J38 -> 2442505.3 | K39: =J39+K38 -> 2589452.1 | ... T39: =S39+T38 -> 3911973.7
A40: Lowest cumulative cash / month of low point | C40: =MIN(C39:T39) -> 358101.94 | D40: =MATCH(C40,C39:T39,0) -> 1
A42: Summary (columns C/D/E = Low/Base/High)
A43: Peak funding need over 18 months (opening cash + lowest cumulative; 0 if never negative) | C43: =MAX(0,-C14) -> 4784118 | D43: =MAX(0,-C27) -> 449807 | E43: =MAX(0,-C40) -> 0
A44: Cumulative cash after 18 months | C44: =T13 -> -4784118 | D44: =T26 -> -449807 | E44: =T39 -> 3911973.7
A45: Month of lowest cumulative cash | C45: =D14 -> 18 | D45: =D27 -> 18 | E45: =D40 -> 1
A46: Average monthly net cash flow in months 7-18 (after stores run out) | C46: =AVERAGE(I12:T12) -> -379957.8 | D46: =AVERAGE(I25:T25) -> -112609.04 | E46: =AVERAGE(I38:T38) -> 146946.84
A47: Average monthly net cash flow in months 1-6 (on stores) | C47: =AVERAGE(C12:H12) -> -37437.393 | D47: =AVERAGE(C25:H25) -> 150250.25 | E47: =AVERAGE(C38:H38) -> 358101.94

Sheet B12
A1: B12 (annual, KES). All cells are live formulas from Inputs.
A2: Line | B2: Unit | C2: Low (adverse) | D2: Base | E2: High (favourable) | F2: Base in USD | G2: Note
A3: Common terms
A4: OMBM (lorry as owned) | B4: KES | C4: =Farm_PnL!C46 -> -4681368.6 | D4: =Farm_PnL!D46 -> -1532808.5 | E4: =Farm_PnL!E46 -> 1590112.1 | F4: =D4/Inputs!$D$4 -> -11800.82
A5: Revenue | B5: KES | C5: =Farm_PnL!C15 -> 3249336 | D5: =Farm_PnL!D15 -> 4854130 | E5: =Farm_PnL!E15 -> 6996262.8 | F5: =D5/Inputs!$D$4 -> 37371.083
A6: K | B6: KES | C6: =Farm_PnL!C63 -> 11119670 | D6: =Farm_PnL!D63 -> 10564511 | E6: =Farm_PnL!E63 -> 10208609 | F6: =D6/Inputs!$D$4 -> 81334.293
A7: g x L (land value change) | B7: KES | C7: =Inputs!C6*Farm_PnL!C65 -> 0 | D7: =Inputs!D6*Farm_PnL!D65 -> 115000 | E7: =Inputs!E6*Farm_PnL!E65 -> 322000 | F7: =D7/Inputs!$D$4 -> 885.36454
A8: Risk charge r x K | B8: KES | C8: =Inputs!C7*Farm_PnL!C63 -> 555983.49 | D8: =Inputs!D7*Farm_PnL!D63 -> 422580.45 | E8: =Inputs!E7*Farm_PnL!E63 -> 306258.28 | F8: =D8/Inputs!$D$4 -> 3253.3717
A9: Option 1: Self-run, PLAN generic structure (manager + deputy + full controls)
A10: Owner hours | B10: h/yr | C10: =Inputs!C292 -> 450 | D10: =Inputs!D292 -> 390 | E10: =Inputs!E292 -> 330
A11: Controls (generic) | B11: KES | C11: =Overhead!$C$17 -> 994000 | D11: =Overhead!$C$17 -> 994000 | E11: =Overhead!$C$17 -> 994000 | F11: =D11/Inputs!$D$4 -> 7652.6291
A12: Manager + deputy | B12: KES | C12: =Overhead!$C$24 -> 660000 | D12: =Overhead!$C$24 -> 660000 | E12: =Overhead!$C$24 -> 660000 | F12: =D12/Inputs!$D$4 -> 5081.2226
A13: Set-up / years | B13: KES | C13: =Inputs!C299/Inputs!C301 -> 112500 | D13: =Inputs!D299/Inputs!D301 -> 112500 | E13: =Inputs!E299/Inputs!E301 -> 112500 | F13: =D13/Inputs!$D$4 -> 866.11748
A14: VALUE: self-run generic | B14: KES | C14: =C4-C11-C12-C10*Inputs!C8-C13-C8+C7 -> -7183852.1 | D14: =D4-D11-D12-D10*Inputs!D8-D13-D8+D7 -> -3723889 | E14: =E4-E11-E12-E10*Inputs!E8-E13-E8+E7 -> -243146.17 | F14: =D14/Inputs!$D$4 -> -28669.559
A15: Option 2: Owner-operator, simplified controls, lorry kept (owner >300 km away)
A16: Owner hours (remote + visits incl. long travel + admin) | B16: h/yr | C16: =Inputs!C293*52+Inputs!C294*Inputs!C295+Inputs!C297*52 -> 1000 | D16: =Inputs!D293*52+Inputs!D294*Inputs!D295+Inputs!D297*52 -> 556 | E16: =Inputs!E293*52+Inputs!E294*Inputs!E295+Inputs!E297*52 -> 346
A17: Controls (right-sized) | B17: KES | C17: =Overhead!$D$17 -> 188000 | D17: =Overhead!$D$17 -> 188000 | E17: =Overhead!$D$17 -> 188000 | F17: =D17/Inputs!$D$4 -> 1447.3786
A18: Management: supervisor stipend | B18: KES | C18: =Overhead!$D$24 -> 72000 | D18: =Overhead!$D$24 -> 72000 | E18: =Overhead!$D$24 -> 72000 | F18: =D18/Inputs!$D$4 -> 554.31519
A19: Management: owner travel cash cost | B19: KES | C19: =Inputs!C294*Inputs!C296 -> 240000 | D19: =Inputs!D294*Inputs!D296 -> 96000 | E19: =Inputs!E294*Inputs!E296 -> 48000 | F19: =D19/Inputs!$D$4 -> 739.08692
A20: Set-up / years | B20: KES | C20: =Inputs!C300/Inputs!C301 -> 15000 | D20: =Inputs!D300/Inputs!D301 -> 15000 | E20: =Inputs!E300/Inputs!E301 -> 15000 | F20: =D20/Inputs!$D$4 -> 115.48233
A21: VALUE: owner-operator, lorry kept | B21: KES | C21: =C4-C17-C18-C19-C16*Inputs!C8-C20-C8+C7 -> -6152352.1 | D21: =D4-D17-D18-D19-D16*Inputs!D8-D20-D8+D7 -> -2378189 | E21: =E4-E17-E18-E19-E16*Inputs!E8-E20-E8+E7 -> 1196353.8 | F21: =D21/Inputs!$D$4 -> -18309.254
A22: Option 2b: Owner-operator, lorry sold (proceeds earn the declared real return)
A23: OMBM without lorry | B23: KES | C23: =Farm_PnL!C48 -> -3296893.6 | D23: =Farm_PnL!D48 -> -583375.19 | E23: =Farm_PnL!E48 -> 2281734.8 | F23: =D23/Inputs!$D$4 -> -4491.3018
A24: Risk charge r x K (K without lorry) | B24: KES | C24: =Inputs!C7*Farm_PnL!C64 -> 330983.49 | D24: =Inputs!D7*Farm_PnL!D64 -> 242580.45 | E24: =Inputs!E7*Farm_PnL!E64 -> 171258.28 | F24: =D24/Inputs!$D$4 -> 1867.5837
A25: Return on net lorry proceeds | B25: KES | C25: =Lorry!C40 -> 85500 | D25: =Lorry!D40 -> 85500 | E25: =Lorry!E40 -> 85500 | F25: =D25/Inputs!$D$4 -> 658.24929
A26: VALUE: owner-operator, lorry sold | B26: KES | C26: =C23-C17-C18-C19-C16*Inputs!C8-C20-C24+C7+C25 -> -4457377.1 | D26: =D23-D17-D18-D19-D16*Inputs!D8-D20-D24+D7+D25 -> -1163255.6 | E26: =E23-E17-E18-E19-E16*Inputs!E8-E20-E24+E7+E25 -> 2108476.6 | F26: =D26/Inputs!$D$4 -> -8955.6982
A27: Option 3: Lease (land and structures; stock, lorry and staff exit)
A28: Rent (acres x rent per acre) | B28: KES | C28: =Inputs!C11*Inputs!C304 -> 138000 | D28: =Inputs!D11*Inputs!D304 -> 184000 | E28: =Inputs!E11*Inputs!E304 -> 230000 | F28: =D28/Inputs!$D$4 -> 1416.5833
A29: Net proceeds of stock and lorry | B29: KES | C29: =(Farm_PnL!C41+Inputs!C273)*(1-Inputs!C9) -> 6360250 | D29: =(Farm_PnL!D41+Inputs!D273)*(1-Inputs!D9) -> 6360250 | E29: =(Farm_PnL!E41+Inputs!E273)*(1-Inputs!E9) -> 6360250 | F29: =D29/Inputs!$D$4 -> 48966.433
A30: Return on those proceeds | B30: KES | C30: =C29*Inputs!C5 -> 127205 | D30: =D29*Inputs!D5 -> 127205 | E30: =E29*Inputs!E5 -> 127205 | F30: =D30/Inputs!$D$4 -> 979.32866
A31: Owner hours | B31: h/yr | C31: =Inputs!C298 -> 40 | D31: =Inputs!D298 -> 30 | E31: =Inputs!E298 -> 20
A32: Transition per year | B32: KES | C32: =(Inputs!C302+(Farm_PnL!C41+Inputs!C273)*Inputs!C9+Labour!C20*Inputs!C303)/Inputs!C301 -> 128437.5 | D32: =(Inputs!D302+(Farm_PnL!D41+Inputs!D273)*Inputs!D9+Labour!D20*Inputs!D303)/Inputs!D301 -> 128437.5 | E32: =(Inputs!E302+(Farm_PnL!E41+Inputs!E273)*Inputs!E9+Labour!E20*Inputs!E303)/Inputs!E301 -> 128437.5 | F32: =D32/Inputs!$D$4 -> 988.81746
A33: VALUE: lease | B33: KES | C33: =C28+C30-Inputs!C305-C31*Inputs!C8-C32+C7 -> 100767.5 | D33: =D28+D30-Inputs!D305-D31*Inputs!D8-D32+D7 -> 268767.5 | E33: =E28+E30-Inputs!E305-E31*Inputs!E8-E32+E7 -> 525767.5 | F33: =D33/Inputs!$D$4 -> 2069.1932
A34: Option 4: Sale of land, structures, stock and lorry
A35: Net proceeds after selling cost/tax | B35: KES | C35: =Farm_PnL!C66*(1-Inputs!C9) -> 15907750 | D35: =Farm_PnL!D66*(1-Inputs!D9) -> 19185250 | E35: =Farm_PnL!E66*(1-Inputs!E9) -> 23555250 | F35: =D35/Inputs!$D$4 -> 147703.83
A36: VALUE: sale (return on proceeds) | B36: KES | C36: =C35*Inputs!C5 -> 318155 | D36: =D35*Inputs!D5 -> 383705 | E36: =E35*Inputs!E5 -> 471105 | F36: =D36/Inputs!$D$4 -> 2954.0765
A37: Stress test (single-factor; worst of price -20%, inputs +25%, disease -10% output and stock)
A38: OMBM after price -20% | B38: KES | C38: =C4-0.2*C5 -> -5331235.8 | D38: =D4-0.2*D5 -> -2503634.5 | E38: =E4-0.2*E5 -> 190859.55 | F38: =D38/Inputs!$D$4 -> -19275.037
A39: OMBM after inputs +25% | B39: KES | C39: =C4-0.25*Farm_PnL!C31 -> -5934254.9 | D39: =D4-0.25*Farm_PnL!D31 -> -2541634.8 | E39: =E4-0.25*Farm_PnL!E31 -> 738905.12 | F39: =D39/Inputs!$D$4 -> -19567.594
A40: OMBM after disease (-10% output and stock value) | B40: KES | C40: =C4-0.1*C5-0.1*Farm_PnL!C41 -> -5225802.2 | D40: =D4-0.1*D5-0.1*Farm_PnL!D41 -> -2237721.5 | E40: =E4-0.1*E5-0.1*Farm_PnL!E41 -> 670985.83 | F40: =D40/Inputs!$D$4 -> -17227.82
A41: Worst scenario OMBM | B41: KES | C41: =MIN(C38,C39,C40) -> -5934254.9 | D41: =MIN(D38,D39,D40) -> -2541634.8 | E41: =MIN(E38,E39,E40) -> 190859.55 | F41: =D41/Inputs!$D$4 -> -19567.594
A42: Stress limit: -10% of K | B42: KES | C42: =-0.1*C6 -> -1111967 | D42: =-0.1*D6 -> -1056451.1 | E42: =-0.1*E6 -> -1020860.9 | F42: =D42/Inputs!$D$4 -> -8133.4293
A43: Stress limit: -10% of K without lorry | B43: KES | C43: =-0.1*Farm_PnL!C64 -> -661966.98 | D43: =-0.1*Farm_PnL!D64 -> -606451.13 | E43: =-0.1*Farm_PnL!E64 -> -570860.93 | F43: =D43/Inputs!$D$4 -> -4668.9594
A44: Non-cash depreciation added back (structures + lorry) | B44: KES | C44: =Farm_PnL!C40+Lorry!C5 -> 621875 | D44: =Farm_PnL!D40+Lorry!D5 -> 537500 | E44: =Farm_PnL!E40+Lorry!E5 -> 481250 | F44: =D44/Inputs!$D$4 -> 4138.1169
A45: Net cash flow, option 1, worst scenario (literal B12: cash basis) | B45: KES | C45: =C41+C44-C11-C12 -> -6966379.9 | D45: =D41+D44-D11-D12 -> -3658134.8 | E45: =E41+E44-E11-E12 -> -981890.45 | F45: =D45/Inputs!$D$4 -> -28163.329
A46: Net cash flow, option 2, worst scenario (cash basis) | B46: KES | C46: =C41+C44-C17-C18-C19 -> -5812379.9 | D46: =D41+D44-D17-D18-D19 -> -2360134.8 | E46: =E41+E44-E17-E18-E19 -> 364109.55 | F46: =D46/Inputs!$D$4 -> -18170.258
A47: Net cash flow, option 2b, worst scenario (cash basis; lorry costs removed) | B47: KES | C47: =C41+Lorry!C24+Farm_PnL!C40-C17-C18-C19 -> -4849779.9 | D47: =D41+Lorry!D24+Farm_PnL!D40-D17-D18-D19 -> -1748201.5 | E47: =E41+Lorry!E24+Farm_PnL!E40-E17-E18-E19 -> 774482.28 | F47: =D47/Inputs!$D$4 -> -13459.092
A48: Memo: option 2 worst case on the v1 basis (OMBM, depreciation not added back) | B48: KES | C48: =C41-C17-C18-C19 -> -6434254.9 | D48: =D41-D17-D18-D19 -> -2897634.8 | E48: =E41-E17-E18-E19 -> -117140.45 | F48: =D48/Inputs!$D$4 -> -22308.375
A49: Option 1 passes stress limit (1/0) | B49: flag | C49: =IF(C45>=C42,1,0) -> 0 | D49: =IF(D45>=D42,1,0) -> 0 | E49: =IF(E45>=E42,1,0) -> 1
A50: Option 2 passes stress limit (1/0) | B50: flag | C50: =IF(C46>=C42,1,0) -> 0 | D50: =IF(D46>=D42,1,0) -> 0 | E50: =IF(E46>=E42,1,0) -> 1
A51: Option 2b passes stress limit (1/0) | B51: flag | C51: =IF(C47>=C43,1,0) -> 0 | D51: =IF(D47>=D43,1,0) -> 0 | E51: =IF(E47>=E43,1,0) -> 1
A52: Memo: option 2 passes on v1 basis (1/0) | B52: flag | C52: =IF(C48>=C42,1,0) -> 0 | D52: =IF(D48>=D42,1,0) -> 0 | E52: =IF(E48>=E42,1,0) -> 1
A53: Ranking A: all options (if lease and sale were legally available now)
A54: Score option 1 | B54: KES | C54: =IF(AND(C14>0,C49=1),C14,-1000000000000) -> -1000000000000 | D54: =IF(AND(D14>0,D49=1),D14,-1000000000000) -> -1000000000000 | E54: =IF(AND(E14>0,E49=1),E14,-1000000000000) -> -1000000000000 | F54: =D54/Inputs!$D$4 -> -7.6988221e+09
A55: Score option 2 | B55: KES | C55: =IF(AND(C21>0,C50=1),C21,-1000000000000) -> -1000000000000 | D55: =IF(AND(D21>0,D50=1),D21,-1000000000000) -> -1000000000000 | E55: =IF(AND(E21>0,E50=1),E21,-1000000000000) -> 1196353.8 | F55: =D55/Inputs!$D$4 -> -7.6988221e+09
A56: Score option 2b | B56: KES | C56: =IF(AND(C26>0,C51=1),C26,-1000000000000) -> -1000000000000 | D56: =IF(AND(D26>0,D51=1),D26,-1000000000000) -> -1000000000000 | E56: =IF(AND(E26>0,E51=1),E26,-1000000000000) -> 2108476.6 | F56: =D56/Inputs!$D$4 -> -7.6988221e+09
A57: Score option 3 | B57: KES | C57: =IF(C33>0,C33,-1000000000000) -> 100767.5 | D57: =IF(D33>0,D33,-1000000000000) -> 268767.5 | E57: =IF(E33>0,E33,-1000000000000) -> 525767.5 | F57: =D57/Inputs!$D$4 -> 2069.1932
A58: Score option 4 | B58: KES | C58: =IF(C36>0,C36,-1000000000000) -> 318155 | D58: =IF(D36>0,D36,-1000000000000) -> 383705 | E58: =IF(E36>0,E36,-1000000000000) -> 471105 | F58: =D58/Inputs!$D$4 -> 2954.0765
A59: Top score | B59: KES | C59: =MAX(C54,C55,C56,C57,C58) -> 318155 | D59: =MAX(D54,D55,D56,D57,D58) -> 383705 | E59: =MAX(E54,E55,E56,E57,E58) -> 2108476.6 | F59: =D59/Inputs!$D$4 -> 2954.0765
A60: WINNER (ranking A) | B60: text | C60: =IF(C59<=0,"No viable option",IF(C54=C59,"Self-run (PLAN generic)",IF(C55=C59,"Owner-operator, lorry kept",IF(C56=C59,"Owner-operator, sell lorry",IF(C57=C59,"Lease","Sale (conditional exit)"))))) -> Sale (conditional exit) | D60: =IF(D59<=0,"No viable option",IF(D54=D59,"Self-run (PLAN generic)",IF(D55=D59,"Owner-operator, lorry kept",IF(D56=D59,"Owner-operator, sell lorry",IF(D57=D59,"Lease","Sale (conditional exit)"))))) -> Sale (conditional exit) | E60: =IF(E59<=0,"No viable option",IF(E54=E59,"Self-run (PLAN generic)",IF(E55=E59,"Owner-operator, lorry kept",IF(E56=E59,"Owner-operator, sell lorry",IF(E57=E59,"Lease","Sale (conditional exit)"))))) -> Owner-operator, sell lorry
A61: Ranking B: executable now (lease/sale excluded unless Inputs title_ok = 1)
A62: Score lease (executable) | B62: KES | C62: =IF(AND(C33>0,Inputs!C18=1),C33,-1000000000000) -> -1000000000000 | D62: =IF(AND(D33>0,Inputs!D18=1),D33,-1000000000000) -> -1000000000000 | E62: =IF(AND(E33>0,Inputs!E18=1),E33,-1000000000000) -> -1000000000000 | F62: =D62/Inputs!$D$4 -> -7.6988221e+09
A63: Score sale (executable) | B63: KES | C63: =IF(AND(C36>0,Inputs!C18=1),C36,-1000000000000) -> -1000000000000 | D63: =IF(AND(D36>0,Inputs!D18=1),D36,-1000000000000) -> -1000000000000 | E63: =IF(AND(E36>0,Inputs!E18=1),E36,-1000000000000) -> -1000000000000 | F63: =D63/Inputs!$D$4 -> -7.6988221e+09
A64: Top score | B64: KES | C64: =MAX(C54,C55,C56,C62,C63) -> -1000000000000 | D64: =MAX(D54,D55,D56,D62,D63) -> -1000000000000 | E64: =MAX(E54,E55,E56,E62,E63) -> 2108476.6 | F64: =D64/Inputs!$D$4 -> -7.6988221e+09
A65: WINNER (ranking B) | B65: text | C65: =IF(C64<=0,"No viable option (hold, simplify or fix title first)",IF(C54=C64,"Self-run (PLAN generic)",IF(C55=C64,"Owner-operator, lorry kept",IF(C56=C64,"Owner-operator, sell lorry",IF(C62=C64,"Lease","Sale (conditional exit)"))))) -> No viable option (hold, simplify or fix title first) | D65: =IF(D64<=0,"No viable option (hold, simplify or fix title first)",IF(D54=D64,"Self-run (PLAN generic)",IF(D55=D64,"Owner-operator, lorry kept",IF(D56=D64,"Owner-operator, sell lorry",IF(D62=D64,"Lease","Sale (conditional exit)"))))) -> No viable option (hold, simplify or fix title first) | E65: =IF(E64<=0,"No viable option (hold, simplify or fix title first)",IF(E54=E64,"Self-run (PLAN generic)",IF(E55=E64,"Owner-operator, lorry kept",IF(E56=E64,"Owner-operator, sell lorry",IF(E62=E64,"Lease","Sale (conditional exit)"))))) -> Owner-operator, sell lorry
A66: B12 outcome (ranking B; PLAN step 4/5/6 wording) | B66: text | C66: =IF(C64<=0,"No viable option: do not proceed as designed",IF(OR(C55=C64,C56=C64),IF(C64<0.1*C4,"Proceed: conditional pass","Proceed"),IF(C54=C64,"Proceed (generic)","Restructure / exit"))) -> No viable option: do not proceed as designed | D66: =IF(D64<=0,"No viable option: do not proceed as designed",IF(OR(D55=D64,D56=D64),IF(D64<0.1*D4,"Proceed: conditional pass","Proceed"),IF(D54=D64,"Proceed (generic)","Restructure / exit"))) -> No viable option: do not proceed as designed | E66: =IF(E64<=0,"No viable option: do not proceed as designed",IF(OR(E55=E64,E56=E64),IF(E64<0.1*E4,"Proceed: conditional pass","Proceed"),IF(E54=E64,"Proceed (generic)","Restructure / exit"))) -> Proceed
A67: Diagnostics
A68: Option 2 value as % of asset base | B68: % | C68: =C21/Farm_PnL!C66 -> -0.36741428 | D68: =D21/Farm_PnL!D66 -> -0.11776128 | E68: =E21/Farm_PnL!E66 -> 0.048249802
A69: Lease value as % of asset base | B69: % | C69: =C33/Farm_PnL!C66 -> 0.0060177665 | D69: =D33/Farm_PnL!D66 -> 0.013308616 | E69: =E33/Farm_PnL!E66 -> 0.021204578
A70: Sale value as % of asset base | B70: % | C70: =C36/Farm_PnL!C66 -> 0.019 | D70: =D36/Farm_PnL!D66 -> 0.019 | E70: =E36/Farm_PnL!E66 -> 0.019
A71: Flip point g*: real land-value growth at which lease beats sale | B71: % | C71: =(C36-(C33-C7))/Farm_PnL!C65 -> 0.027004658 | D71: =(D36-(D33-D7))/Farm_PnL!D65 -> 0.019994565 | E71: =(E36-(E33-E7))/Farm_PnL!E65 -> 0.016604814
A72: PLAN band cap: 7% of revenue (small band) | B72: KES | C72: =0.07*C5 -> 227453.52 | D72: =0.07*D5 -> 339789.1 | E72: =0.07*E5 -> 489738.4 | F72: =D72/Inputs!$D$4 -> 2615.9758
A73: Simplified controls as % of revenue | B73: % | C73: =C17/C5 -> 0.057857975 | D73: =D17/D5 -> 0.038729906 | E73: =E17/E5 -> 0.026871489
A74: Simplified controls fit one-third-of-OMBM test (1/0) | B74: flag | C74: =IF(AND(C4>0,C17<=C4/3),1,0) -> 0 | D74: =IF(AND(D4>0,D17<=D4/3),1,0) -> 0 | E74: =IF(AND(E4>0,E17<=E4/3),1,0) -> 1
A75: Simplified controls fit 7% band cap (1/0) | B75: flag | C75: =IF(C17<=C72,1,0) -> 1 | D75: =IF(D17<=D72,1,0) -> 1 | E75: =IF(E17<=E72,1,0) -> 1
A76: Generic controls + manager/deputy as % of revenue | B76: % | C76: =(C11+C12)/C5 -> 0.50902708 | D76: =(D11+D12)/D5 -> 0.34074077 | E76: =(E11+E12)/E5 -> 0.23641193
A77: Break-even (variable costs scale with revenue: contribution ratio held)
A78: Option 2: OMBM needed to pay controls + stipend + travel in cash | B78: KES | C78: =C17+C18+C19 -> 500000 | D78: =D17+D18+D19 -> 356000 | E78: =E17+E18+E19 -> 308000 | F78: =D78/Inputs!$D$4 -> 2740.7807
A79: Option 2: OMBM needed for value = 0 | B79: KES | C79: =C18+C17+C19+C16*Inputs!C8+C20+C8-C7 -> 1470983.5 | D79: =D18+D17+D19+D16*Inputs!D8+D20+D8-D7 -> 845380.45 | E79: =E18+E17+E19+E16*Inputs!E8+E20+E8-E7 -> 393758.28 | F79: =D79/Inputs!$D$4 -> 6508.4337
A80: Option 2b: OMBM (ex-lorry) needed for value = 0 | B80: KES | C80: =C18+C17+C19+C16*Inputs!C8+C20+C24-C7-C25 -> 1160483.5 | D80: =D18+D17+D19+D16*Inputs!D8+D20+D24-D7-D25 -> 579880.45 | E80: =E18+E17+E19+E16*Inputs!E8+E20+E24-E7-E25 -> 173258.28 | F80: =D80/Inputs!$D$4 -> 4464.3964
A81: Option 2: revenue for value = 0 | B81: KES | C81: =IF(Farm_PnL!C50<=0.02,"n/a",(Farm_PnL!C44+C79)/Farm_PnL!C50) -> n/a | D81: =IF(Farm_PnL!D50<=0.02,"n/a",(Farm_PnL!D44+D79)/Farm_PnL!D50) -> 18952431 | E81: =IF(Farm_PnL!E50<=0.02,"n/a",(Farm_PnL!E44+E79)/Farm_PnL!E50) -> 4665716.3 | F81: =D81/Inputs!$D$4 -> 145911.39
A82: Option 2: break-even revenue as multiple of current | B82: x | C82: =IF(ISNUMBER(C81),C81/C5,"n/a") -> n/a | D82: =IF(ISNUMBER(D81),D81/D5,"n/a") -> 3.9043929 | E82: =IF(ISNUMBER(E81),E81/E5,"n/a") -> 0.66688694
A83: Option 2: OMBM needed to match lease value | B83: KES | C83: =C79+C33 -> 1571751 | D83: =D79+D33 -> 1114148 | E83: =E79+E33 -> 919525.78 | F83: =D83/Inputs!$D$4 -> 8577.6269
A84: Gap: OMBM to cash break-even | B84: KES | C84: =C78-C4 -> 5181368.6 | D84: =D78-D4 -> 1888808.5 | E84: =E78-E4 -> -1282112.1 | F84: =D84/Inputs!$D$4 -> 14541.601
A85: Gap: OMBM to B12 value = 0 | B85: KES | C85: =C79-C4 -> 6152352.1 | D85: =D79-D4 -> 2378189 | E85: =E79-E4 -> -1196353.8 | F85: =D85/Inputs!$D$4 -> 18309.254
A86: Gap: OMBM to match lease | B86: KES | C86: =C83-C4 -> 6253119.6 | D86: =D83-D4 -> 2646956.5 | E86: =E83-E4 -> -670586.33 | F86: =D86/Inputs!$D$4 -> 20378.447
A87: Gap: OMBM (ex-lorry) to B12 value = 0 | B87: KES | C87: =C80-C23 -> 4457377.1 | D87: =D80-D23 -> 1163255.6 | E87: =E80-E23 -> -2108476.6 | F87: =D87/Inputs!$D$4 -> 8955.6982

Sheet Breakeven
A1: Breakeven (annual, KES). All cells are live formulas from Inputs.
A2: Line | B2: Unit | C2: Low (adverse) | D2: Base | E2: High (favourable) | F2: Base in USD | G2: Note
A3: How far from viable (owner-operator, lorry kept, B12 value = 0)
A4: OMBM shortfall to B12 value = 0 | B4: KES | C4: =MAX(0,B12!C85) -> 6152352.1 | D4: =MAX(0,B12!D85) -> 2378189 | E4: =MAX(0,B12!E85) -> 0 | F4: =D4/Inputs!$D$4 -> 18309.254
A5: OMBM shortfall to cash break-even | B5: KES | C5: =MAX(0,B12!C84) -> 5181368.6 | D5: =MAX(0,B12!D84) -> 1888808.5 | E5: =MAX(0,B12!E84) -> 0 | F5: =D5/Inputs!$D$4 -> 14541.601
A6: One lever at a time (all else at scenario values)
A7: Average egg farm-gate price now | B7: KES/egg | C7: =IF(Poultry!C247=0,0,Poultry!C251/Poultry!C247) -> 12 | D7: =IF(Poultry!D247=0,0,Poultry!D251/Poultry!D247) -> 15 | E7: =IF(Poultry!E247=0,0,Poultry!E251/Poultry!E247) -> 18
A8: Egg price needed | B8: KES/egg | C8: =C7+C4/(Poultry!C247*(1-Inputs!C63)) -> 87.86056 | D8: =D7+D4/(Poultry!D247*(1-Inputs!D63)) -> 36.063069 | E8: =E7+E4/(Poultry!E247*(1-Inputs!E63)) -> 18
A9: Egg price needed per tray of 30 | B9: KES/tray | C9: =C8*30 -> 2635.8168 | D9: =D8*30 -> 1081.8921 | E9: =E8*30 -> 540
A10: Average live-bird farm-gate price now (growers + spent hens) | B10: KES/bird | C10: =Poultry!C252/Poultry!C249 -> 623.1275 | D10: =Poultry!D252/Poultry!D249 -> 761.01043 | E10: =Poultry!E252/Poultry!E249 -> 920.41287
A11: Live-bird price needed | B11: KES/bird | C11: =C10+C4/(Poultry!C249*(1-Inputs!C65)) -> 2937.3642 | D11: =D10+D4/(Poultry!D249*(1-Inputs!D65)) -> 1555.6472 | E11: =E10+E4/(Poultry!E249*(1-Inputs!E65)) -> 920.41287
A12: Live-bird price rise needed | B12: % | C12: =C11/C10-1 -> 3.7139056 | D12: =D11/D10-1 -> 1.0441865 | E12: =E11/E10-1 -> 0
A13: Purchased feed/forage price cut needed | B13: % | C13: =C4/Farm_PnL!C59 -> 1.6694856 | D13: =D4/Farm_PnL!D59 -> 0.84313488 | E13: =E4/Farm_PnL!E59 -> 0
A14: Feed price cut needed for cash break-even | B14: % | C14: =C5/Farm_PnL!C59 -> 1.4060022 | D14: =D5/Farm_PnL!D59 -> 0.66963574 | E14: =E5/Farm_PnL!E59 -> 0
A15: Staff pay now (each) | B15: KES/month | C15: =Inputs!C248 -> 22000 | D15: =Inputs!D248 -> 22000 | E15: =Inputs!E248 -> 22000
A16: Staff pay (each) at which B12 value = 0, 3 staff | B16: KES/month | C16: =Inputs!C248-C4/(36*(1+Inputs!C251+Inputs!C252)) -> -136975.51 | D16: =Inputs!D248-D4/(36*(1+Inputs!D251+Inputs!D252)) -> -39451.911 | E16: =Inputs!E248-E4/(36*(1+Inputs!E251+Inputs!E252)) -> 22000 | G16: Negative means pay cuts alone cannot close the gap
A17: Legal stockman minimum | B17: KES/month | C17: =Inputs!C246 -> 9235.78 | D17: =Inputs!D246 -> 9235.78 | E17: =Inputs!E246 -> 9235.78
A18: Poultry scale multiple needed (poultry margin per bird constant, labour fixed) | B18: x | C18: =IF(Poultry!C255<=0,"n/a",1+C4/Poultry!C255) -> n/a | D18: =IF(Poultry!D255<=0,"n/a",1+D4/Poultry!D255) -> 5.3084694 | E18: =IF(Poultry!E255<=0,"n/a",1+E4/Poultry!E255) -> 1 | G18: Ignores egg/bird market depth and extra labour
A19: Gain from selling the lorry (option 2b minus option 2) | B19: KES | C19: =B12!C26-B12!C21 -> 1694975 | D19: =B12!D26-B12!D21 -> 1214933.3 | E19: =B12!E26-B12!E21 -> 912122.73 | F19: =D19/Inputs!$D$4 -> 9353.5556
A20: Lorry hire days needed to cover its own cost (illustrative rate) | B20: days | C20: =Lorry!C29 -> 317.35817 | D20: =Lorry!D29 -> 73.033333 | E20: =Lorry!E29 -> 31.456895
A21: Illustrative stack of restructuring levers, cumulative B12 owner-operator value (not a forecast; each step needs its own evidence)
A22: Start: owner-operator, lorry kept | B22: KES | C22: =B12!C21 -> -6152352.1 | D22: =B12!D21 -> -2378189 | E22: =B12!E21 -> 1196353.8 | F22: =D22/Inputs!$D$4 -> -18309.254
A23: + sell the lorry (cost saved, proceeds at 2% real) | B23: KES | C23: =C22+C19 -> -4457377.1 | D23: =D22+D19 -> -1163255.6 | E23: =E22+E19 -> 2108476.6 | F23: =D23/Inputs!$D$4 -> -8955.6982
A24: + purchased feed/forage 20% cheaper (own fodder on 23 acres, bulk buying) | B24: KES | C24: =C23+0.2*Farm_PnL!C59 -> -3720341.4 | D24: =D23+0.2*Farm_PnL!D59 -> -599125.5 | E24: =E23+0.2*Farm_PnL!E59 -> 2559517.3 | F24: =D24/Inputs!$D$4 -> -4612.5607
A25: + run with 2 staff plus extra casuals for the hours gap | B25: KES | C25: =C24+(Inputs!C248*12*(1+Inputs!C251+Inputs!C252)+12*Inputs!C253)-(MAX(0,Labour!C13-2*Labour!C14)-MAX(0,Labour!C13-3*Labour!C14))/8*Inputs!C255 -> -3570941.4 | D25: =D24+(Inputs!D248*12*(1+Inputs!D251+Inputs!D252)+12*Inputs!D253)-(MAX(0,Labour!D13-2*Labour!D14)-MAX(0,Labour!D13-3*Labour!D14))/8*Inputs!D255 -> -411550.5 | E25: =E24+(Inputs!E248*12*(1+Inputs!E251+Inputs!E252)+12*Inputs!E253)-(MAX(0,Labour!E13-2*Labour!E14)-MAX(0,Labour!E13-3*Labour!E14))/8*Inputs!E255 -> 2800450.7 | F25: =D25/Inputs!$D$4 -> -3168.4541
A26: + egg and live-bird prices both 10% higher | B26: KES | C26: =C25+0.1*(Poultry!C251*(1-Inputs!C63)+Poultry!C252*(1-Inputs!C65)) -> -3307963.3 | D26: =D25+0.1*(Poultry!D251*(1-Inputs!D63)+Poultry!D252*(1-Inputs!D65)) -> -14433.304 | E26: =E25+0.1*(Poultry!E251*(1-Inputs!E63)+Poultry!E252*(1-Inputs!E65)) -> 3373345.7 | F26: =D26/Inputs!$D$4 -> -111.11944
A27: + drop supervisor stipend and halve owner visits | B27: KES | C27: =C26+B12!C18+0.5*B12!C19+0.5*Inputs!C294*Inputs!C295*Inputs!C8 -> -3019963.3 | D27: =D26+B12!D18+0.5*B12!D19+0.5*Inputs!D294*Inputs!D295*Inputs!D8 -> 134366.7 | E27: =E26+B12!E18+0.5*B12!E19+0.5*Inputs!E294*Inputs!E295*Inputs!E8 -> 3483345.7 | F27: =D27/Inputs!$D$4 -> 1034.4653
A28: Egg price (rows) x live-bird price (columns) shifts: B12 owner-operator value, KES (selected scenario column)
A29: Egg -3.0 KES/egg, bird -150 KES/bird | B29: KES | C29: =B12!C21+(-3)*Poultry!C247*(1-Inputs!C63)+(-150)*Poultry!C249*(1-Inputs!C65) -> -6794426.5 | D29: =B12!D21+(-3)*Poultry!D247*(1-Inputs!D63)+(-150)*Poultry!D249*(1-Inputs!D65) -> -3165833 | E29: =B12!E21+(-3)*Poultry!E247*(1-Inputs!E63)+(-150)*Poultry!E249*(1-Inputs!E65) -> 253550.43 | F29: =D29/Inputs!$D$4 -> -24373.185
A30: Egg -3.0 KES/egg, bird -75 KES/bird | B30: KES | C30: =B12!C21+(-3)*Poultry!C247*(1-Inputs!C63)+(-75)*Poultry!C249*(1-Inputs!C65) -> -6595040.5 | D30: =B12!D21+(-3)*Poultry!D247*(1-Inputs!D63)+(-75)*Poultry!D249*(1-Inputs!D65) -> -2941373 | E30: =B12!E21+(-3)*Poultry!E247*(1-Inputs!E63)+(-75)*Poultry!E249*(1-Inputs!E65) -> 518564.13 | F30: =D30/Inputs!$D$4 -> -22645.107
A31: Egg -3.0 KES/egg, bird +0 KES/bird | B31: KES | C31: =B12!C21+(-3)*Poultry!C247*(1-Inputs!C63)+(0)*Poultry!C249*(1-Inputs!C65) -> -6395654.5 | D31: =B12!D21+(-3)*Poultry!D247*(1-Inputs!D63)+(0)*Poultry!D249*(1-Inputs!D65) -> -2716913 | E31: =B12!E21+(-3)*Poultry!E247*(1-Inputs!E63)+(0)*Poultry!E249*(1-Inputs!E65) -> 783577.83 | F31: =D31/Inputs!$D$4 -> -20917.03
A32: Egg -3.0 KES/egg, bird +75 KES/bird | B32: KES | C32: =B12!C21+(-3)*Poultry!C247*(1-Inputs!C63)+(75)*Poultry!C249*(1-Inputs!C65) -> -6196268.5 | D32: =B12!D21+(-3)*Poultry!D247*(1-Inputs!D63)+(75)*Poultry!D249*(1-Inputs!D65) -> -2492453 | E32: =B12!E21+(-3)*Poultry!E247*(1-Inputs!E63)+(75)*Poultry!E249*(1-Inputs!E65) -> 1048591.5 | F32: =D32/Inputs!$D$4 -> -19188.952
A33: Egg -3.0 KES/egg, bird +150 KES/bird | B33: KES | C33: =B12!C21+(-3)*Poultry!C247*(1-Inputs!C63)+(150)*Poultry!C249*(1-Inputs!C65) -> -5996882.5 | D33: =B12!D21+(-3)*Poultry!D247*(1-Inputs!D63)+(150)*Poultry!D249*(1-Inputs!D65) -> -2267993 | E33: =B12!E21+(-3)*Poultry!E247*(1-Inputs!E63)+(150)*Poultry!E249*(1-Inputs!E65) -> 1313605.2 | F33: =D33/Inputs!$D$4 -> -17460.874
A34: Egg -1.5 KES/egg, bird -150 KES/bird | B34: KES | C34: =B12!C21+(-1.5)*Poultry!C247*(1-Inputs!C63)+(-150)*Poultry!C249*(1-Inputs!C65) -> -6672775.3 | D34: =B12!D21+(-1.5)*Poultry!D247*(1-Inputs!D63)+(-150)*Poultry!D249*(1-Inputs!D65) -> -2996471 | E34: =B12!E21+(-1.5)*Poultry!E247*(1-Inputs!E63)+(-150)*Poultry!E249*(1-Inputs!E65) -> 459938.43 | F34: =D34/Inputs!$D$4 -> -23069.297
A35: Egg -1.5 KES/egg, bird -75 KES/bird | B35: KES | C35: =B12!C21+(-1.5)*Poultry!C247*(1-Inputs!C63)+(-75)*Poultry!C249*(1-Inputs!C65) -> -6473389.3 | D35: =B12!D21+(-1.5)*Poultry!D247*(1-Inputs!D63)+(-75)*Poultry!D249*(1-Inputs!D65) -> -2772011 | E35: =B12!E21+(-1.5)*Poultry!E247*(1-Inputs!E63)+(-75)*Poultry!E249*(1-Inputs!E65) -> 724952.13 | F35: =D35/Inputs!$D$4 -> -21341.219
A36: Egg -1.5 KES/egg, bird +0 KES/bird | B36: KES | C36: =B12!C21+(-1.5)*Poultry!C247*(1-Inputs!C63)+(0)*Poultry!C249*(1-Inputs!C65) -> -6274003.3 | D36: =B12!D21+(-1.5)*Poultry!D247*(1-Inputs!D63)+(0)*Poultry!D249*(1-Inputs!D65) -> -2547551 | E36: =B12!E21+(-1.5)*Poultry!E247*(1-Inputs!E63)+(0)*Poultry!E249*(1-Inputs!E65) -> 989965.83 | F36: =D36/Inputs!$D$4 -> -19613.142
A37: Egg -1.5 KES/egg, bird +75 KES/bird | B37: KES | C37: =B12!C21+(-1.5)*Poultry!C247*(1-Inputs!C63)+(75)*Poultry!C249*(1-Inputs!C65) -> -6074617.3 | D37: =B12!D21+(-1.5)*Poultry!D247*(1-Inputs!D63)+(75)*Poultry!D249*(1-Inputs!D65) -> -2323091 | E37: =B12!E21+(-1.5)*Poultry!E247*(1-Inputs!E63)+(75)*Poultry!E249*(1-Inputs!E65) -> 1254979.5 | F37: =D37/Inputs!$D$4 -> -17885.064
A38: Egg -1.5 KES/egg, bird +150 KES/bird | B38: KES | C38: =B12!C21+(-1.5)*Poultry!C247*(1-Inputs!C63)+(150)*Poultry!C249*(1-Inputs!C65) -> -5875231.3 | D38: =B12!D21+(-1.5)*Poultry!D247*(1-Inputs!D63)+(150)*Poultry!D249*(1-Inputs!D65) -> -2098631 | E38: =B12!E21+(-1.5)*Poultry!E247*(1-Inputs!E63)+(150)*Poultry!E249*(1-Inputs!E65) -> 1519993.2 | F38: =D38/Inputs!$D$4 -> -16156.986
A39: Egg +0.0 KES/egg, bird -150 KES/bird | B39: KES | C39: =B12!C21+(0)*Poultry!C247*(1-Inputs!C63)+(-150)*Poultry!C249*(1-Inputs!C65) -> -6551124.1 | D39: =B12!D21+(0)*Poultry!D247*(1-Inputs!D63)+(-150)*Poultry!D249*(1-Inputs!D65) -> -2827109 | E39: =B12!E21+(0)*Poultry!E247*(1-Inputs!E63)+(-150)*Poultry!E249*(1-Inputs!E65) -> 666326.43 | F39: =D39/Inputs!$D$4 -> -21765.409
A40: Egg +0.0 KES/egg, bird -75 KES/bird | B40: KES | C40: =B12!C21+(0)*Poultry!C247*(1-Inputs!C63)+(-75)*Poultry!C249*(1-Inputs!C65) -> -6351738.1 | D40: =B12!D21+(0)*Poultry!D247*(1-Inputs!D63)+(-75)*Poultry!D249*(1-Inputs!D65) -> -2602649 | E40: =B12!E21+(0)*Poultry!E247*(1-Inputs!E63)+(-75)*Poultry!E249*(1-Inputs!E65) -> 931340.13 | F40: =D40/Inputs!$D$4 -> -20037.331
A41: Egg +0.0 KES/egg, bird +0 KES/bird | B41: KES | C41: =B12!C21+(0)*Poultry!C247*(1-Inputs!C63)+(0)*Poultry!C249*(1-Inputs!C65) -> -6152352.1 | D41: =B12!D21+(0)*Poultry!D247*(1-Inputs!D63)+(0)*Poultry!D249*(1-Inputs!D65) -> -2378189 | E41: =B12!E21+(0)*Poultry!E247*(1-Inputs!E63)+(0)*Poultry!E249*(1-Inputs!E65) -> 1196353.8 | F41: =D41/Inputs!$D$4 -> -18309.254
A42: Egg +0.0 KES/egg, bird +75 KES/bird | B42: KES | C42: =B12!C21+(0)*Poultry!C247*(1-Inputs!C63)+(75)*Poultry!C249*(1-Inputs!C65) -> -5952966.1 | D42: =B12!D21+(0)*Poultry!D247*(1-Inputs!D63)+(75)*Poultry!D249*(1-Inputs!D65) -> -2153729 | E42: =B12!E21+(0)*Poultry!E247*(1-Inputs!E63)+(75)*Poultry!E249*(1-Inputs!E65) -> 1461367.5 | F42: =D42/Inputs!$D$4 -> -16581.176
A43: Egg +0.0 KES/egg, bird +150 KES/bird | B43: KES | C43: =B12!C21+(0)*Poultry!C247*(1-Inputs!C63)+(150)*Poultry!C249*(1-Inputs!C65) -> -5753580.1 | D43: =B12!D21+(0)*Poultry!D247*(1-Inputs!D63)+(150)*Poultry!D249*(1-Inputs!D65) -> -1929269 | E43: =B12!E21+(0)*Poultry!E247*(1-Inputs!E63)+(150)*Poultry!E249*(1-Inputs!E65) -> 1726381.2 | F43: =D43/Inputs!$D$4 -> -14853.099
A44: Egg +1.5 KES/egg, bird -150 KES/bird | B44: KES | C44: =B12!C21+(1.5)*Poultry!C247*(1-Inputs!C63)+(-150)*Poultry!C249*(1-Inputs!C65) -> -6429472.9 | D44: =B12!D21+(1.5)*Poultry!D247*(1-Inputs!D63)+(-150)*Poultry!D249*(1-Inputs!D65) -> -2657747 | E44: =B12!E21+(1.5)*Poultry!E247*(1-Inputs!E63)+(-150)*Poultry!E249*(1-Inputs!E65) -> 872714.43 | F44: =D44/Inputs!$D$4 -> -20461.521
A45: Egg +1.5 KES/egg, bird -75 KES/bird | B45: KES | C45: =B12!C21+(1.5)*Poultry!C247*(1-Inputs!C63)+(-75)*Poultry!C249*(1-Inputs!C65) -> -6230086.9 | D45: =B12!D21+(1.5)*Poultry!D247*(1-Inputs!D63)+(-75)*Poultry!D249*(1-Inputs!D65) -> -2433287 | E45: =B12!E21+(1.5)*Poultry!E247*(1-Inputs!E63)+(-75)*Poultry!E249*(1-Inputs!E65) -> 1137728.1 | F45: =D45/Inputs!$D$4 -> -18733.443
A46: Egg +1.5 KES/egg, bird +0 KES/bird | B46: KES | C46: =B12!C21+(1.5)*Poultry!C247*(1-Inputs!C63)+(0)*Poultry!C249*(1-Inputs!C65) -> -6030700.9 | D46: =B12!D21+(1.5)*Poultry!D247*(1-Inputs!D63)+(0)*Poultry!D249*(1-Inputs!D65) -> -2208827 | E46: =B12!E21+(1.5)*Poultry!E247*(1-Inputs!E63)+(0)*Poultry!E249*(1-Inputs!E65) -> 1402741.8 | F46: =D46/Inputs!$D$4 -> -17005.366
A47: Egg +1.5 KES/egg, bird +75 KES/bird | B47: KES | C47: =B12!C21+(1.5)*Poultry!C247*(1-Inputs!C63)+(75)*Poultry!C249*(1-Inputs!C65) -> -5831314.9 | D47: =B12!D21+(1.5)*Poultry!D247*(1-Inputs!D63)+(75)*Poultry!D249*(1-Inputs!D65) -> -1984367 | E47: =B12!E21+(1.5)*Poultry!E247*(1-Inputs!E63)+(75)*Poultry!E249*(1-Inputs!E65) -> 1667755.5 | F47: =D47/Inputs!$D$4 -> -15277.288
A48: Egg +1.5 KES/egg, bird +150 KES/bird | B48: KES | C48: =B12!C21+(1.5)*Poultry!C247*(1-Inputs!C63)+(150)*Poultry!C249*(1-Inputs!C65) -> -5631928.9 | D48: =B12!D21+(1.5)*Poultry!D247*(1-Inputs!D63)+(150)*Poultry!D249*(1-Inputs!D65) -> -1759907 | E48: =B12!E21+(1.5)*Poultry!E247*(1-Inputs!E63)+(150)*Poultry!E249*(1-Inputs!E65) -> 1932769.2 | F48: =D48/Inputs!$D$4 -> -13549.211
A49: Egg +3.0 KES/egg, bird -150 KES/bird | B49: KES | C49: =B12!C21+(3)*Poultry!C247*(1-Inputs!C63)+(-150)*Poultry!C249*(1-Inputs!C65) -> -6307821.7 | D49: =B12!D21+(3)*Poultry!D247*(1-Inputs!D63)+(-150)*Poultry!D249*(1-Inputs!D65) -> -2488385 | E49: =B12!E21+(3)*Poultry!E247*(1-Inputs!E63)+(-150)*Poultry!E249*(1-Inputs!E65) -> 1079102.4 | F49: =D49/Inputs!$D$4 -> -19157.633
A50: Egg +3.0 KES/egg, bird -75 KES/bird | B50: KES | C50: =B12!C21+(3)*Poultry!C247*(1-Inputs!C63)+(-75)*Poultry!C249*(1-Inputs!C65) -> -6108435.7 | D50: =B12!D21+(3)*Poultry!D247*(1-Inputs!D63)+(-75)*Poultry!D249*(1-Inputs!D65) -> -2263925 | E50: =B12!E21+(3)*Poultry!E247*(1-Inputs!E63)+(-75)*Poultry!E249*(1-Inputs!E65) -> 1344116.1 | F50: =D50/Inputs!$D$4 -> -17429.556
A51: Egg +3.0 KES/egg, bird +0 KES/bird | B51: KES | C51: =B12!C21+(3)*Poultry!C247*(1-Inputs!C63)+(0)*Poultry!C249*(1-Inputs!C65) -> -5909049.7 | D51: =B12!D21+(3)*Poultry!D247*(1-Inputs!D63)+(0)*Poultry!D249*(1-Inputs!D65) -> -2039465 | E51: =B12!E21+(3)*Poultry!E247*(1-Inputs!E63)+(0)*Poultry!E249*(1-Inputs!E65) -> 1609129.8 | F51: =D51/Inputs!$D$4 -> -15701.478
A52: Egg +3.0 KES/egg, bird +75 KES/bird | B52: KES | C52: =B12!C21+(3)*Poultry!C247*(1-Inputs!C63)+(75)*Poultry!C249*(1-Inputs!C65) -> -5709663.7 | D52: =B12!D21+(3)*Poultry!D247*(1-Inputs!D63)+(75)*Poultry!D249*(1-Inputs!D65) -> -1815005 | E52: =B12!E21+(3)*Poultry!E247*(1-Inputs!E63)+(75)*Poultry!E249*(1-Inputs!E65) -> 1874143.5 | F52: =D52/Inputs!$D$4 -> -13973.4
A53: Egg +3.0 KES/egg, bird +150 KES/bird | B53: KES | C53: =B12!C21+(3)*Poultry!C247*(1-Inputs!C63)+(150)*Poultry!C249*(1-Inputs!C65) -> -5510277.7 | D53: =B12!D21+(3)*Poultry!D247*(1-Inputs!D63)+(150)*Poultry!D249*(1-Inputs!D65) -> -1590545 | E53: =B12!E21+(3)*Poultry!E247*(1-Inputs!E63)+(150)*Poultry!E249*(1-Inputs!E65) -> 2139157.2 | F53: =D53/Inputs!$D$4 -> -12245.323
A54: Purchased feed price change: B12 owner-operator value
A55: Feed price -20% | B55: KES | C55: =B12!C21-(-20/100)*Farm_PnL!C59 -> -5415316.4 | D55: =B12!D21-(-20/100)*Farm_PnL!D59 -> -1814058.8 | E55: =B12!E21-(-20/100)*Farm_PnL!E59 -> 1647394.6 | F55: =D55/Inputs!$D$4 -> -13966.116
A56: Feed price -10% | B56: KES | C56: =B12!C21-(-10/100)*Farm_PnL!C59 -> -5783834.3 | D56: =B12!D21-(-10/100)*Farm_PnL!D59 -> -2096123.9 | E56: =B12!E21-(-10/100)*Farm_PnL!E59 -> 1421874.2 | F56: =D56/Inputs!$D$4 -> -16137.685
A57: Feed price +0% | B57: KES | C57: =B12!C21-(0/100)*Farm_PnL!C59 -> -6152352.1 | D57: =B12!D21-(0/100)*Farm_PnL!D59 -> -2378189 | E57: =B12!E21-(0/100)*Farm_PnL!E59 -> 1196353.8 | F57: =D57/Inputs!$D$4 -> -18309.254
A58: Feed price +10% | B58: KES | C58: =B12!C21-(10/100)*Farm_PnL!C59 -> -6520869.9 | D58: =B12!D21-(10/100)*Farm_PnL!D59 -> -2660254 | E58: =B12!E21-(10/100)*Farm_PnL!E59 -> 970833.46 | F58: =D58/Inputs!$D$4 -> -20480.823
A59: Feed price +20% | B59: KES | C59: =B12!C21-(20/100)*Farm_PnL!C59 -> -6889387.7 | D59: =B12!D21-(20/100)*Farm_PnL!D59 -> -2942319.1 | E59: =B12!E21-(20/100)*Farm_PnL!E59 -> 745313.1 | F59: =D59/Inputs!$D$4 -> -22652.391
A60: Staff pay: B12 owner-operator value
A61: Each of 3 staff at KES 12,000/month | B61: KES | C61: =B12!C21+(Inputs!C248-12000)*36*(1+Inputs!C251+Inputs!C252) -> -5765352.1 | D61: =B12!D21+(Inputs!D248-12000)*36*(1+Inputs!D251+Inputs!D252) -> -1991189 | E61: =B12!E21+(Inputs!E248-12000)*36*(1+Inputs!E251+Inputs!E252) -> 1583353.8 | F61: =D61/Inputs!$D$4 -> -15329.81
A62: Each of 3 staff at KES 15,000/month | B62: KES | C62: =B12!C21+(Inputs!C248-15000)*36*(1+Inputs!C251+Inputs!C252) -> -5881452.1 | D62: =B12!D21+(Inputs!D248-15000)*36*(1+Inputs!D251+Inputs!D252) -> -2107289 | E62: =B12!E21+(Inputs!E248-15000)*36*(1+Inputs!E251+Inputs!E252) -> 1467253.8 | F62: =D62/Inputs!$D$4 -> -16223.643
A63: Each of 3 staff at KES 18,000/month | B63: KES | C63: =B12!C21+(Inputs!C248-18000)*36*(1+Inputs!C251+Inputs!C252) -> -5997552.1 | D63: =B12!D21+(Inputs!D248-18000)*36*(1+Inputs!D251+Inputs!D252) -> -2223389 | E63: =B12!E21+(Inputs!E248-18000)*36*(1+Inputs!E251+Inputs!E252) -> 1351153.8 | F63: =D63/Inputs!$D$4 -> -17117.476
A64: Each of 3 staff at KES 22,000/month | B64: KES | C64: =B12!C21+(Inputs!C248-22000)*36*(1+Inputs!C251+Inputs!C252) -> -6152352.1 | D64: =B12!D21+(Inputs!D248-22000)*36*(1+Inputs!D251+Inputs!D252) -> -2378189 | E64: =B12!E21+(Inputs!E248-22000)*36*(1+Inputs!E251+Inputs!E252) -> 1196353.8 | F64: =D64/Inputs!$D$4 -> -18309.254
A65: Each of 3 staff at KES 26,000/month | B65: KES | C65: =B12!C21+(Inputs!C248-26000)*36*(1+Inputs!C251+Inputs!C252) -> -6307152.1 | D65: =B12!D21+(Inputs!D248-26000)*36*(1+Inputs!D251+Inputs!D252) -> -2532989 | E65: =B12!E21+(Inputs!E248-26000)*36*(1+Inputs!E251+Inputs!E252) -> 1041553.8 | F65: =D65/Inputs!$D$4 -> -19501.031

Sheet Collect_8wk
A1: Data the owner must collect in the first 8 weeks (replaces ASSUMED inputs). Updated for v2: lorry, poultry stage/breed data, vet, vault.
A2: No. | B2: Measure | C2: Method | D2: Replaces Inputs rows | E2: Week
A3: 1 | B3: Independent count by breed/species with age band (chick/grower/pullet/laying/spent) and sex for every house; cattle by class; sheep tags | C3: Representative or vet counts with photos; signed tally; reconcile to the 2,270 poultry | D3: *_n, *_h, cows | E3: 1
A4: 2 | B4: Title: copy of title deed or allotment/share certificate, official search, any Land Control Board consent | C4: Lawyer, registry search | D4: title_ok, land_p | E4: 1
A5: 3 | B5: Lorry file: logbook, purchase price/year/make/GVW and payload, NTSA inspection, insurance cover note, driver and driver-licence class, GPS tracker, fuel receipts, who holds the keys | C5: Copies of documents; daily odometer and fuel photo; tracker report | D5: lor_val, lor_ins, lor_km, lor_dd | E5: 1
A6: 4 | B6: Vault: cash held, who holds keys, count and bank deposit log | C6: Dual-custody count by representative; weekly deposit | D6: open_cash, controls | E6: 1
A7: 5 | B7: Acreage by use; grazing, fodder, crops; pan volumes and refill record; pump hours and fuel | C7: GPS phone app; photos; meter/fuel log | D7: acres, forage, water | E7: 2
A8: 6 | B8: Staff: contracts, tasks, who is the relative, actual pay, deductions, hours worked | C8: Interview; payslips; time log | D8: pay1-3, h_pou, h_cat | E8: 2
A9: 7 | B9: Daily eggs by breed, feed bags opened by type, deaths by breed and age | C9: Tally sheet at 17:00; photo of bags and trays | D9: *_eggs, *_hfeed, *_hmort, hen share | E9: 8
A10: 8 | B10: Egg sales: buyer, trays, price per tray, payment method | C10: Sales book + M-Pesa statement | D10: *_eggp, egg_mkt | E10: 8
A11: 9 | B11: Live-bird, duck, goose, turkey, guinea-fowl sales: count, live weight, price, buyer | C11: Sales book + M-Pesa statement | D11: *_price, *_bat, *_gmort | E11: 8
A12: 10 | B12: Feed: bags, price, supplier; three written quotes; stock count of stores against the 6-month claim | C12: Receipts; supplier quotes; physical count | D12: lay_bag, gro_bag, stores_m | E12: 4
A13: 11 | B13: Chicks/poults/keets bought or hatched: source, price, mortality to 4 weeks | C13: Receipts; mortality tally | D13: *_chick, *_rmort | E13: 8
A14: 12 | B14: Milk per cow and buyer price; cattle and small-stock sales | C14: Daily tally; buyer receipts | D14: mlk_l, milk_p, c_price, sh_price | E14: 8
... A21: 19 | B21: Re-run the model with measured data; apply the week-8 rule in G1-economics-v2.md | C21: This workbook | D21: all | E21: 8
