Workbook

Sheet README
A1: G1 economics model - Borut, Bomet. Built 2026-10-15. All amounts KES; USD at CBK rate on Inputs.
A2: Low = adverse case, Base, High = favourable. Every calculated cell is a live formula; change blue cells on Inputs (or Overhead).
A3: Tags: SOURCED (published figure with URL on Inputs/doc), BENCHMARK (published figure of uncertain date/area, or standard convention), ASSUMED (no source; replace with measured data).
A4: Sheets: Inputs > Cattle, Sheep, Goats, Layers, OtherPoultry > Labour > Overhead > Farm_PnL > B12 > Scenarios > Collect_8wk.
A5: No farm accounts exist, so the PLAN's 'last year's revenue' screen is replaced by this benchmark-based screen. It is a screen, not a forecast.
A6: Land: freehold title unclear. Lease and sale are excluded from the executable ranking unless Inputs 'title_ok' = 1 (lawyer to confirm).
A7: Crops are not modelled (no data); purchased feed may be overstated if the farm grows its own fodder, understated if grazing is short.

Sheet Scenarios
A1: Scenario summary: Low (adverse) / Base / High (favourable). KES with USD for base
A2: Line | B2: Unit | C2: Low (adverse) | D2: Base | E2: High (favourable) | F2: Base in USD | G2: Note
A3: Revenue and margin
A4: Revenue | B4: KES | C4: =Farm_PnL!C9 -> 2158161.9 | D4: =Farm_PnL!D9 -> 2776511.8 | E4: =Farm_PnL!E9 -> 3568790 | F4: =D4/Inputs!$D$4 -> 21375.87
A5: Variable costs | B5: KES | C5: =Farm_PnL!C17 -> 2545497.2 | D5: =Farm_PnL!D17 -> 2249279.5 | E5: =Farm_PnL!E17 -> 2051700.2 | F5: =D5/Inputs!$D$4 -> 17316.803
A6: Gross margin | B6: KES | C6: =Farm_PnL!C16 -> -387335.25 | D6: =Farm_PnL!D16 -> 527232.23 | E6: =Farm_PnL!E16 -> 1517089.9 | F6: =D6/Inputs!$D$4 -> 4059.0672
A7: Hired labour | B7: KES | C7: =Farm_PnL!C19 -> 535300 | D7: =Farm_PnL!D19 -> 532800 | E7: =Farm_PnL!E19 -> 530300 | F7: =D7/Inputs!$D$4 -> 4101.9324
A8: Labour + fixed costs | B8: KES | C8: =Farm_PnL!C28 -> 788300 | D8: =Farm_PnL!D28 -> 760800 | E8: =Farm_PnL!E28 -> 732300 | F8: =D8/Inputs!$D$4 -> 5857.2638
A9: OMBM | B9: KES | C9: =Farm_PnL!C30 -> -1175635.2 | D9: =Farm_PnL!D30 -> -233567.77 | E9: =Farm_PnL!E30 -> 784789.85 | F9: =D9/Inputs!$D$4 -> -1798.1967
A10: Cash margin (OMBM + depreciation) | B10: KES | C10: =Farm_PnL!C32 -> -1095635.2 | D10: =Farm_PnL!D32 -> -153567.77 | E10: =Farm_PnL!E32 -> 864789.85 | F10: =D10/Inputs!$D$4 -> -1182.2909
A11: OMBM % of revenue | B11: % | C11: =Farm_PnL!C31 -> -0.54473913 | D11: =Farm_PnL!D31 -> -0.084122736 | E11: =Farm_PnL!E31 -> 0.21990362
A12: Gross margin by enterprise
A13: Cattle and dairy | B13: KES | C13: =Farm_PnL!C11 -> -63160 | D13: =Farm_PnL!D11 -> 107600 | E13: =Farm_PnL!E11 -> 329400 | F13: =D13/Inputs!$D$4 -> 828.39326
A14: Sheep | B14: KES | C14: =Farm_PnL!C12 -> 17179.04 | D14: =Farm_PnL!D12 -> 119340.8 | E14: =Farm_PnL!E12 -> 255260.48 | F14: =D14/Inputs!$D$4 -> 918.78359
A15: Goats | B15: KES | C15: =Farm_PnL!C13 -> 17532.8 | D15: =Farm_PnL!D13 -> 39904 | E15: =Farm_PnL!E13 -> 69280.336 | F15: =D15/Inputs!$D$4 -> 307.2138
A16: Layers | B16: KES | C16: =Farm_PnL!C14 -> -283031.37 | D16: =Farm_PnL!D14 -> 19600.235 | E16: =Farm_PnL!E14 -> 328980.89 | F16: =D16/Inputs!$D$4 -> 150.89872
A17: Kienyeji, ducks, guinea fowl, geese | B17: KES | C17: =Farm_PnL!C15 -> -75855.714 | D17: =Farm_PnL!D15 -> 240787.2 | E17: =Farm_PnL!E15 -> 534168.14 | F17: =D17/Inputs!$D$4 -> 1853.7778
A18: Gross margin per task hour
A19: Cattle and dairy | B19: KES/h | C19: =Farm_PnL!C35 -> -43.260274 | D19: =Farm_PnL!D35 -> 84.227006 | E19: =Farm_PnL!E35 -> 282.02055 | F19: =D19/Inputs!$D$4 -> 0.64844873
A20: Sheep | B20: KES/h | C20: =Farm_PnL!C36 -> 26.147702 | D20: =Farm_PnL!D36 -> 217.97406 | E20: =Farm_PnL!E36 -> 537.95675 | F20: =D20/Inputs!$D$4 -> 1.6781435
A21: Goats | B21: KES/h | C21: =Farm_PnL!C37 -> 80.058447 | D21: =Farm_PnL!D37 -> 218.65205 | E21: =Farm_PnL!E37 -> 421.79809 | F21: =D21/Inputs!$D$4 -> 1.6833633
A22: Layers | B22: KES/h | C22: =Farm_PnL!C38 -> -430.79357 | D22: =Farm_PnL!D38 -> 35.799515 | E22: =Farm_PnL!E38 -> 693.32116 | F22: =D22/Inputs!$D$4 -> 0.2756141
A23: Other poultry | B23: KES/h | C23: =Farm_PnL!C39 -> -74.222812 | D23: =Farm_PnL!D39 -> 263.87638 | E23: =Farm_PnL!E39 -> 665.21562 | F23: =D23/Inputs!$D$4 -> 2.0315373
A24: Overhead structure
A25: PLAN generic controls | B25: KES | C25: =B12!C11 -> 994000 | D25: =B12!D11 -> 994000 | E25: =B12!E11 -> 994000 | F25: =D25/Inputs!$D$4 -> 7652.6291
A26: PLAN manager + deputy | B26: KES | C26: =B12!C12 -> 660000 | D26: =B12!D12 -> 660000 | E26: =B12!E12 -> 660000 | F26: =D26/Inputs!$D$4 -> 5081.2226
A27: Generic controls + management as multiple of OMBM | B27: x | C27: =B12!C75 -> OMBM<=0 | D27: =B12!D75 -> OMBM<=0 | E27: =B12!E75 -> 2.1075706
A28: Right-sized controls | B28: KES | C28: =B12!C17 -> 188000 | D28: =B12!D17 -> 188000 | E28: =B12!E17 -> 188000 | F28: =D28/Inputs!$D$4 -> 1447.3786
A29: Supervisor stipend | B29: KES | C29: =B12!C18 -> 72000 | D29: =B12!D18 -> 72000 | E29: =B12!E18 -> 72000 | F29: =D29/Inputs!$D$4 -> 554.31519
A30: B12 values (annual after-risk income)
A31: Self-run (PLAN generic) | B31: KES | C31: =B12!C14 -> -3281095.2 | D31: =B12!D14 -> -2181248.6 | E31: =B12!E14 -> -987845.15 | F31: =D31/Inputs!$D$4 -> -16793.045
A32: Owner-operator, simplified controls | B32: KES | C32: =B12!C20 -> -1894395.2 | D32: =B12!D20 -> -710748.56 | E32: =B12!E20 -> 511654.85 | F32: =D32/Inputs!$D$4 -> -5471.9267
A33: Lease | B33: KES | C33: =B12!C27 -> 11458.5 | D33: =B12!D27 -> 102458.5 | E33: =B12!E27 -> 238458.5 | F33: =D33/Inputs!$D$4 -> 788.80976
A34: Sale | B34: KES | C34: =B12!C30 -> 125571 | D34: =B12!D30 -> 159771 | E34: =B12!E30 -> 205371 | F34: =D34/Inputs!$D$4 -> 1230.0485
A35: Winner, ranking A (all options) | C35: =B12!C55 -> Sale | D35: =B12!D55 -> Sale | E35: =B12!E55 -> Owner-operator, simplified
A36: Winner, ranking B (executable pre-title) | C36: =B12!C64 -> No viable option (hold, simplify or fix title first) | D36: =B12!D64 -> No viable option (hold, simplify or fix title first) | E36: =B12!E64 -> Owner-operator, simplified
A37: Break-even
A38: Option 2 break-even revenue (value = 0) | B38: KES | C38: =B12!C84 -> n/a | D38: =B12!D84 -> 6519457.6 | E38: =B12!E84 -> 2365177.2 | F38: =D38/Inputs!$D$4 -> 50192.144
A39: Option 2 cash-only break-even revenue | B39: KES | C39: =B12!C88 -> n/a | D39: =B12!D88 -> 5375739.6 | E39: =B12!E88 -> 2334278.6 | F39: =D39/Inputs!$D$4 -> 41386.863
A40: Option 1 break-even revenue | B40: KES | C40: =B12!C90 -> n/a | D40: =B12!D90 -> 14263409 | E40: =B12!E90 -> 5892589 | F40: =D40/Inputs!$D$4 -> 109811.44
A41: Owner hours/yr, option 2 | B41: h | C41: =B12!C16 -> 712 | D41: =B12!D16 -> 460 | E41: =B12!E16 -> 298
A42: Owner hours per week, option 2 | B42: h/wk | C42: =B12!C16/52 -> 13.692308 | D42: =B12!D16/52 -> 8.8461538 | E42: =B12!E16/52 -> 5.7307692

Sheet Inputs
A1: INPUTS - KES unless stated. Columns: Low = adverse case, Base, High = favourable case. Blue = editable input. Tag: SOURCED / BENCHMARK / ASSUMED.
A2: Parameter | B2: Unit | C2: Low (adverse) | D2: Base | E2: High (favourable) | F2: Tag | G2: Source / note (accessed 2026-10-15 unless stated)
A3: General
A4: Exchange rate | B4: KES per USD | C4: 129.89 | D4: 129.89 | E4: 129.89 | F4: SOURCED | G4: CBK indicative rate posted 7 Oct 2026 (centralbank.go.ke via web search; confirm daily rate)
A5: Declared real return on cash proceeds | B5: % p.a. | C5: 0.02 | D5: 0.02 | E5: 0.02 | F5: ASSUMED | G5: B12 default 2%
A6: Real change in land value g | B6: % p.a. | C6: 0 | D6: 0.01 | E6: 0.02 | F6: ASSUMED | G6: B12 default +1%; no local land-value series found
A7: Risk charge on capital at risk | B7: % | C7: 0.05 | D7: 0.04 | E7: 0.03 | F7: BENCHMARK | G7: B12 default 3-5%
A8: Owner hourly shadow price p | B8: KES/h | C8: 400 | D8: 300 | E8: 250 | F8: ASSUMED | G8: Owner's occupation unknown; PLAN uses 50 (units unstated). Test sensitivity
A9: Selling cost + tax on sale | B9: % | C9: 0.05 | D9: 0.05 | E9: 0.05 | F9: BENCHMARK | G9: B12 default 5%; accountant to quantify (capital gains tax etc.)
A10: Herd / flock (counts from owner intake; species split of poultry ASSUMED)
A11: Cattle (head) | B11: head | C11: 10 | D11: 10 | E11: 10 | F11: SOURCED | G11: Owner intake 2026-10-15
A12: Sheep (head) | B12: head | C12: 50 | D12: 50 | E12: 50 | F12: SOURCED | G12: Owner intake
A13: Goats (head) | B13: head | C13: 10 | D13: 10 | E13: 10 | F13: SOURCED | G13: Owner intake
A14: Layers | B14: birds | C14: 300 | D14: 300 | E14: 300 | F14: ASSUMED | G14: Total ~1,000 birds known; split unknown
A15: Improved kienyeji (standing flock) | B15: birds | C15: 400 | D15: 400 | E15: 400 | F15: ASSUMED | G15: Split unknown
A16: Ducks | B16: birds | C16: 120 | D16: 120 | E16: 120 | F16: ASSUMED | G16: Split unknown
A17: Guinea fowl | B17: birds | C17: 120 | D17: 120 | E17: 120 | F17: ASSUMED | G17: Split unknown
A18: Geese | B18: birds | C18: 60 | D18: 60 | E18: 60 | F18: ASSUMED | G18: Split unknown
A19: TLU factor cattle | B19: TLU/head | C19: 0.7 | D19: 0.7 | E19: 0.7 | F19: BENCHMARK | G19: Standard TLU convention (not re-verified this session)
A20: TLU factor sheep/goat | B20: TLU/head | C20: 0.1 | D20: 0.1 | E20: 0.1 | F20: BENCHMARK | G20: Standard TLU convention
A21: TLU factor poultry | B21: TLU/bird | C21: 0.01 | D21: 0.01 | E21: 0.01 | F21: BENCHMARK | G21: Standard TLU convention
A22: Land and buildings (acreage NOT given in intake)
A23: Farm area | B23: acres | C23: 12 | D23: 12 | E23: 12 | F23: ASSUMED | G23: Unknown. 12 acres is a guess sized to carry ~13 ruminant TLU
A24: Land value per acre | B24: KES/acre | C24: 350000 | D24: 500000 | E24: 700000 | F24: ASSUMED | G24: No Bomet price found in search; get a valuer's figure. Title status unclear
A25: Buildings, fencing, equipment (replacement value) | B25: KES | C25: 800000 | D25: 800000 | E25: 800000 | F25: ASSUMED | G25: Unknown; inspect
A26: Depreciation life | B26: years | C26: 10 | D26: 10 | E26: 10 | F26: ASSUMED
A27: Repairs and maintenance | B27: % of capex | C27: 0.04 | D27: 0.03 | E27: 0.02 | F27: ASSUMED
A28: Cattle (assumed dairy-type, 4 cows in milk of 10 head)
A29: Cows in milk | B29: head | C29: 4 | D29: 4 | E29: 5 | F29: ASSUMED | G29: Herd structure unknown
A30: Milk per cow per day | B30: L | C30: 7 | D30: 8 | E30: 9 | F30: ASSUMED | G30: Typical smallholder crossbred; measure
A31: Days in milk per year per cow | B31: days | C31: 290 | D31: 300 | E31: 305 | F31: ASSUMED
A32: Farm-gate milk price | B32: KES/L | C32: 34 | D32: 38 | E32: 42 | F32: BENCHMARK | G32: Brookside/New KCC ~Sh37 (Business Daily, undated); KCC Sotik Sh41-43 for volume (KNA). Dates unconfirmed
A33: Cooling, transport, levies | B33: KES/L | C33: 3 | D33: 2.5 | E33: 2 | F33: ASSUMED
A34: Dairy meal per cow in milk per day | B34: kg | C34: 3 | D34: 3 | E34: 3 | F34: ASSUMED
A35: Dairy meal price | B35: KES/kg | C35: 56 | D35: 52 | E35: 48 | F35: BENCHMARK | G35: Layers mash ~Sh3,900/70kg, chick mash up to Sh4,600 (Capital FM, 'Nov 25'); dairy meal assumed similar per kg
A36: Purchased hay/forage per head | B36: KES/head/yr | C36: 4000 | D36: 3000 | E36: 2000 | F36: ASSUMED | G36: Depends on own fodder; crops unknown
A37: Minerals and salt per head | B37: KES/head/yr | C37: 1800 | D37: 1800 | E37: 1800 | F37: ASSUMED
A38: Vet, AI, acaricide, drugs per head | B38: KES/head/yr | C38: 7000 | D38: 6000 | E38: 5000 | F38: ASSUMED | G38: Replace with vet quote
A39: Cattle sold per year (steers/surplus/culls) | B39: head | C39: 1 | D39: 2 | E39: 2 | F39: ASSUMED
A40: Price per head sold | B40: KES | C40: 32000 | D40: 40000 | E40: 50000 | F40: BENCHMARK | G40: KMC 140-180 KES/kg live (Garissa programme, kenyanews.go.ke Feb 2026) x ~250 kg; Kajiado/Turkana press ranges 20k-120k
A41: Mortality/loss | B41: % of herd value | C41: 0.04 | D41: 0.03 | E41: 0.02 | F41: ASSUMED
A42: Value per head (capital) | B42: KES | C42: 60000 | D42: 60000 | E42: 60000 | F42: ASSUMED
A43: Sheep (40 breeding ewes of 50)
A44: Breeding ewes | B44: head | C44: 40 | D44: 40 | E44: 40 | F44: ASSUMED
A45: Lambs weaned per ewe per year | B45: no. | C45: 0.8 | D45: 1 | E45: 1.2 | F45: ASSUMED | G45: Smallholder hair sheep; measure
A46: Replacement rate of ewes | B46: % | C46: 0.18 | D46: 0.15 | E46: 0.12 | F46: ASSUMED
A47: Sale weight | B47: kg live | C47: 27 | D47: 28 | E47: 29 | F47: BENCHMARK | G47: ~30 kg avg (Springer Pastoralism study); older data
A48: Price | B48: KES/kg live | C48: 210 | D48: 240 | E48: 280 | F48: BENCHMARK | G48: KMC buyer offer 200-210/kg (Garissa, Feb 2026); Selina Wamucii aggregated est. ~280/kg (not farm-gate data)
A49: Supplement/feed purchases per head | B49: KES/head/yr | C49: 1200 | D49: 1000 | E49: 800 | F49: ASSUMED
A50: Vet, deworm, dip, vaccines per head (sheep and goats) | B50: KES/head/yr | C50: 900 | D50: 800 | E50: 700 | F50: ASSUMED
A51: Minerals per head | B51: KES/head/yr | C51: 200 | D51: 200 | E51: 200 | F51: ASSUMED
A52: Selling cost (transport, commission) | B52: % of revenue | C52: 0.06 | D52: 0.04 | E52: 0.03 | F52: ASSUMED
A53: Value per head | B53: KES | C53: 6000 | D53: 6000 | E53: 6000 | F53: ASSUMED
A54: Goats (8 does of 10)
A55: Breeding does | B55: head | C55: 8 | D55: 8 | E55: 8 | F55: ASSUMED
A56: Kids weaned per doe per year | B56: no. | C56: 1.2 | D56: 1.4 | E56: 1.6 | F56: ASSUMED
A57: Replacement rate | B57: % | C57: 0.22 | D57: 0.2 | E57: 0.18 | F57: ASSUMED
A58: Sale weight | B58: kg live | C58: 25 | D58: 26 | E58: 27 | F58: BENCHMARK | G58: ~30 kg adult avg (Springer); younger animals sold
A59: Price | B59: KES/kg live | C59: 220 | D59: 250 | E59: 290 | F59: BENCHMARK | G59: KMC 210-220/kg (Feb 2026 Garissa offer)
A60: Supplement per head | B60: KES/head/yr | C60: 1200 | D60: 1000 | E60: 800 | F60: ASSUMED
A61: Value per head | B61: KES | C61: 6500 | D61: 6500 | E61: 6500 | F61: ASSUMED
A62: Layers (300)
A63: Hen-day production | B63: % | C63: 0.7 | D63: 0.75 | E63: 0.8 | F63: BENCHMARK | G63: Typical commercial layer range; measure
A64: Laying days in 12 months | B64: days | C64: 345 | D64: 345 | E64: 345 | F64: ASSUMED
A65: Breakage/rejects | B65: % | C65: 0.04 | D65: 0.03 | E65: 0.025 | F65: ASSUMED
A66: Egg price per tray of 30 (farm gate) | B66: KES/tray | C66: 360 | D66: 400 | E66: 450 | F66: BENCHMARK | G66: Farm gate ~Sh400 (Nation, undated); retail Sh400-600 exotic, Sh540-750 indigenous (Business Daily)
A67: Feed per hen per day | B67: g | C67: 120 | D67: 115 | E67: 112 | F67: BENCHMARK | G67: Standard layer intake
A68: Layers mash price per 70 kg bag | B68: KES/bag | C68: 4300 | D68: 3900 | E68: 3600 | F68: BENCHMARK | G68: Sh3,900-4,000 (Kenyan Wall Street/Capital FM); Sh4,500 in 2023. Dates uncertain
A69: Laying cycle before cull | B69: months | C69: 14 | D69: 14 | E69: 14 | F69: ASSUMED
A70: Point-of-lay pullet cost | B70: KES | C70: 850 | D70: 800 | E70: 750 | F70: ASSUMED | G70: Get hatchery quote
A71: Mortality in lay | B71: % per year | C71: 0.09 | D71: 0.07 | E71: 0.06 | F71: ASSUMED
A72: Spent hen price | B72: KES/bird | C72: 320 | D72: 350 | E72: 400 | F72: ASSUMED
A73: Vaccines and drugs per hen | B73: KES/yr | C73: 140 | D73: 120 | E73: 100 | F73: ASSUMED
A74: Packaging and handling per tray | B74: KES | C74: 25 | D74: 25 | E74: 25 | F74: ASSUMED
A75: Transport and marketing | B75: % of egg revenue | C75: 0.04 | D75: 0.03 | E75: 0.02 | F75: ASSUMED
A76: Value per hen (capital) | B76: KES | C76: 800 | D76: 800 | E76: 800 | F76: ASSUMED
A77: Meat and dual-purpose poultry (feed bag price)
A78: Chick/grower feed price per 70 kg bag | B78: KES/bag | C78: 4500 | D78: 4200 | E78: 3900 | F78: BENCHMARK | G78: Chick mash Sh3,900 -> 4,600 (Capital FM 'Nov 25'); growers assumed in between
A79: Improved kienyeji
A80: Improved kienyeji: batches per year | B80: no. | C80: 2 | D80: 2 | E80: 2 | F80: ASSUMED
A81: Improved kienyeji: mortality to sale | B81: % | C81: 0.16 | D81: 0.12 | E81: 0.09 | F81: ASSUMED
A82: Improved kienyeji: farm-gate price per bird | B82: KES/bird | C82: 650 | D82: 750 | E82: 850 | F82: BENCHMARK | G82: Mature kienyeji Sh900-1,500 retail (BeyondForest 2026), Sh600-1,200 dressed (Huduma 2026); farm gate haircut applied
A83: Improved kienyeji: chick/duckling/keet/gosling cost | B83: KES | C83: 190 | D83: 170 | E83: 155 | F83: ASSUMED | G83: Hatchery quote needed
A84: Improved kienyeji: purchased feed per bird started | B84: kg | C84: 5.5 | D84: 5 | E84: 4.5 | F84: ASSUMED | G84: Depends on free-range access
A85: Improved kienyeji: vet/drugs per bird started | B85: KES | C85: 60 | D85: 40 | E85: 30 | F85: ASSUMED
A86: Improved kienyeji: value per bird (capital) | B86: KES | C86: 500 | D86: 500 | E86: 500 | F86: ASSUMED
A87: Ducks
A88: Ducks: batches per year | B88: no. | C88: 2 | D88: 2 | E88: 2 | F88: ASSUMED
A89: Ducks: mortality to sale | B89: % | C89: 0.16 | D89: 0.12 | E89: 0.09 | F89: ASSUMED
A90: Ducks: farm-gate price per bird | B90: KES/bird | C90: 750 | D90: 900 | E90: 1050 | F90: ASSUMED | G90: No Kenyan duck price found; thin market, verify buyers
A91: Ducks: chick/duckling/keet/gosling cost | B91: KES | C91: 240 | D91: 220 | E91: 205 | F91: ASSUMED | G91: Hatchery quote needed
A92: Ducks: purchased feed per bird started | B92: kg | C92: 6.5 | D92: 6 | E92: 5.5 | F92: ASSUMED | G92: Depends on free-range access
A93: Ducks: vet/drugs per bird started | B93: KES | C93: 60 | D93: 40 | E93: 30 | F93: ASSUMED
A94: Ducks: value per bird (capital) | B94: KES | C94: 500 | D94: 500 | E94: 500 | F94: ASSUMED
A95: Guinea fowl
A96: Guinea fowl: batches per year | B96: no. | C96: 1.5 | D96: 1.5 | E96: 1.5 | F96: ASSUMED
A97: Guinea fowl: mortality to sale | B97: % | C97: 0.26 | D97: 0.2 | E97: 0.15 | F97: ASSUMED
A98: Guinea fowl: farm-gate price per bird | B98: KES/bird | C98: 700 | D98: 850 | E98: 1000 | F98: ASSUMED | G98: No price found; keets fragile, thin market
A99: Guinea fowl: chick/duckling/keet/gosling cost | B99: KES | C99: 280 | D99: 250 | E99: 230 | F99: ASSUMED | G99: Hatchery quote needed
A100: Guinea fowl: purchased feed per bird started | B100: kg | C100: 3.75 | D100: 3.5 | E100: 3.25 | F100: ASSUMED | G100: Depends on free-range access
...

Sheet Cattle
A1: Cattle / dairy enterprise budget (annual, KES) - ASSUMED herd structure; replace with measured data
A2: Line | B2: Unit | C2: Low (adverse) | D2: Base | E2: High (favourable) | F2: Base in USD | G2: Note
A3: Production
A4: Milk sold | B4: L/yr | C4: =Inputs!C$29*Inputs!C$30*Inputs!C$31 -> 8120 | D4: =Inputs!D$29*Inputs!D$30*Inputs!D$31 -> 9600 | E4: =Inputs!E$29*Inputs!E$30*Inputs!E$31 -> 13725
A5: Revenue
A6: Milk revenue | B6: KES | C6: =C4*Inputs!C$32 -> 276080 | D6: =D4*Inputs!D$32 -> 364800 | E6: =E4*Inputs!E$32 -> 576450 | F6: =D6/Inputs!$D$4 -> 2808.5303
A7: Cattle sales | B7: KES | C7: =Inputs!C$39*Inputs!C$40 -> 32000 | D7: =Inputs!D$39*Inputs!D$40 -> 80000 | E7: =Inputs!E$39*Inputs!E$40 -> 100000 | F7: =D7/Inputs!$D$4 -> 615.90577
A8: Total revenue | B8: KES | C8: =C6+C7 -> 308080 | D8: =D6+D7 -> 444800 | E8: =E6+E7 -> 676450 | F8: =D8/Inputs!$D$4 -> 3424.4361
A9: Variable costs
A10: Dairy meal | B10: KES | C10: =Inputs!C$29*Inputs!C$34*Inputs!C$31*Inputs!C$35 -> 194880 | D10: =Inputs!D$29*Inputs!D$34*Inputs!D$31*Inputs!D$35 -> 187200 | E10: =Inputs!E$29*Inputs!E$34*Inputs!E$31*Inputs!E$35 -> 219600 | F10: =D10/Inputs!$D$4 -> 1441.2195
A11: Purchased forage | B11: KES | C11: =Inputs!C$11*Inputs!C$36 -> 40000 | D11: =Inputs!D$11*Inputs!D$36 -> 30000 | E11: =Inputs!E$11*Inputs!E$36 -> 20000 | F11: =D11/Inputs!$D$4 -> 230.96466
A12: Minerals | B12: KES | C12: =Inputs!C$11*Inputs!C$37 -> 18000 | D12: =Inputs!D$11*Inputs!D$37 -> 18000 | E12: =Inputs!E$11*Inputs!E$37 -> 18000 | F12: =D12/Inputs!$D$4 -> 138.5788
A13: Vet, AI, acaricide | B13: KES | C13: =Inputs!C$11*Inputs!C$38 -> 70000 | D13: =Inputs!D$11*Inputs!D$38 -> 60000 | E13: =Inputs!E$11*Inputs!E$38 -> 50000 | F13: =D13/Inputs!$D$4 -> 461.92932
A14: Milk cooling, transport, levies | B14: KES | C14: =C4*Inputs!C$33 -> 24360 | D14: =D4*Inputs!D$33 -> 24000 | E14: =E4*Inputs!E$33 -> 27450 | F14: =D14/Inputs!$D$4 -> 184.77173
A15: Mortality/loss allowance | B15: KES | C15: =Inputs!C$11*Inputs!C$42*Inputs!C$41 -> 24000 | D15: =Inputs!D$11*Inputs!D$42*Inputs!D$41 -> 18000 | E15: =Inputs!E$11*Inputs!E$42*Inputs!E$41 -> 12000 | F15: =D15/Inputs!$D$4 -> 138.5788
A16: Total variable costs | B16: KES | C16: =SUM(C10:C15) -> 371240 | D16: =SUM(D10:D15) -> 337200 | E16: =SUM(E10:E15) -> 347050 | F16: =D16/Inputs!$D$4 -> 2596.0428
A17: Gross margin (before labour and fixed costs) | B17: KES | C17: =C8-C16 -> -63160 | D17: =D8-D16 -> 107600 | E17: =E8-E16 -> 329400 | F17: =D17/Inputs!$D$4 -> 828.39326
A18: Gross margin per head | B18: KES/head | C18: =C17/Inputs!C$11 -> -6316 | D18: =D17/Inputs!D$11 -> 10760 | E18: =E17/Inputs!E$11 -> 32940 | F18: =D18/Inputs!$D$4 -> 82.839326
A19: Stock capital | B19: KES | C19: =Inputs!C$11*Inputs!C$42 -> 600000 | D19: =Inputs!D$11*Inputs!D$42 -> 600000 | E19: =Inputs!E$11*Inputs!E$42 -> 600000 | F19: =D19/Inputs!$D$4 -> 4619.2932
A20: Memo: purchased feed and forage | B20: KES | C20: =C10+C11 -> 234880 | D20: =D10+D11 -> 217200 | E20: =E10+E11 -> 239600 | F20: =D20/Inputs!$D$4 -> 1672.1842

Sheet Sheep
A1: Sheep enterprise budget (annual, KES) - 50 head, 40 breeding ewes assumed
A2: Line | B2: Unit | C2: Low (adverse) | D2: Base | E2: High (favourable) | F2: Base in USD | G2: Note
A3: Production
A4: Lambs/hoggets sold (weaned less replacements) | B4: head | C4: =MAX(0,Inputs!C$44*(Inputs!C$45-Inputs!C$46)) -> 24.8 | D4: =MAX(0,Inputs!D$44*(Inputs!D$45-Inputs!D$46)) -> 34 | E4: =MAX(0,Inputs!E$44*(Inputs!E$45-Inputs!E$46)) -> 43.2
A5: Sale price per head | B5: KES | C5: =Inputs!C$47*Inputs!C$48 -> 5670 | D5: =Inputs!D$47*Inputs!D$48 -> 6720 | E5: =Inputs!E$47*Inputs!E$48 -> 8120 | F5: =D5/Inputs!$D$4 -> 51.736084
A6: Revenue
A7: Sales revenue | B7: KES | C7: =C4*C5 -> 140616 | D7: =D4*D5 -> 228480 | E7: =E4*E5 -> 350784 | F7: =D7/Inputs!$D$4 -> 1759.0269
A8: Variable costs
A9: Supplement/feed | B9: KES | C9: =Inputs!C$12*Inputs!C$49 -> 60000 | D9: =Inputs!D$12*Inputs!D$49 -> 50000 | E9: =Inputs!E$12*Inputs!E$49 -> 40000 | F9: =D9/Inputs!$D$4 -> 384.9411
A10: Vet, deworm, dip, vaccines | B10: KES | C10: =Inputs!C$12*Inputs!C$50 -> 45000 | D10: =Inputs!D$12*Inputs!D$50 -> 40000 | E10: =Inputs!E$12*Inputs!E$50 -> 35000 | F10: =D10/Inputs!$D$4 -> 307.95288
A11: Minerals | B11: KES | C11: =Inputs!C$12*Inputs!C$51 -> 10000 | D11: =Inputs!D$12*Inputs!D$51 -> 10000 | E11: =Inputs!E$12*Inputs!E$51 -> 10000 | F11: =D11/Inputs!$D$4 -> 76.988221
A12: Selling cost | B12: KES | C12: =C7*Inputs!C$52 -> 8436.96 | D12: =D7*Inputs!D$52 -> 9139.2 | E12: =E7*Inputs!E$52 -> 10523.52 | F12: =D12/Inputs!$D$4 -> 70.361075
A13: Total variable costs | B13: KES | C13: =SUM(C9:C12) -> 123436.96 | D13: =SUM(D9:D12) -> 109139.2 | E13: =SUM(E9:E12) -> 95523.52 | F13: =D13/Inputs!$D$4 -> 840.24328
A14: Gross margin | B14: KES | C14: =C7-C13 -> 17179.04 | D14: =D7-D13 -> 119340.8 | E14: =E7-E13 -> 255260.48 | F14: =D14/Inputs!$D$4 -> 918.78359
A15: Gross margin per head | B15: KES/head | C15: =C14/Inputs!C$12 -> 343.5808 | D15: =D14/Inputs!D$12 -> 2386.816 | E15: =E14/Inputs!E$12 -> 5105.2096 | F15: =D15/Inputs!$D$4 -> 18.375672
A16: Stock capital | B16: KES | C16: =Inputs!C$12*Inputs!C$53 -> 300000 | D16: =Inputs!D$12*Inputs!D$53 -> 300000 | E16: =Inputs!E$12*Inputs!E$53 -> 300000 | F16: =D16/Inputs!$D$4 -> 2309.6466
A17: Memo: purchased feed | B17: KES | C17: =C9 -> 60000 | D17: =D9 -> 50000 | E17: =E9 -> 40000 | F17: =D17/Inputs!$D$4 -> 384.9411

Sheet Goats
A1: Goat enterprise budget (annual, KES) - 10 head, 8 does assumed
A2: Line | B2: Unit | C2: Low (adverse) | D2: Base | E2: High (favourable) | F2: Base in USD | G2: Note
A3: Production
A4: Kids sold (weaned less replacements) | B4: head | C4: =MAX(0,Inputs!C$55*(Inputs!C$56-Inputs!C$57)) -> 7.84 | D4: =MAX(0,Inputs!D$55*(Inputs!D$56-Inputs!D$57)) -> 9.6 | E4: =MAX(0,Inputs!E$55*(Inputs!E$56-Inputs!E$57)) -> 11.36
A5: Sale price per head | B5: KES | C5: =Inputs!C$58*Inputs!C$59 -> 5500 | D5: =Inputs!D$58*Inputs!D$59 -> 6500 | E5: =Inputs!E$58*Inputs!E$59 -> 7830 | F5: =D5/Inputs!$D$4 -> 50.042344
A6: Revenue
A7: Sales revenue | B7: KES | C7: =C4*C5 -> 43120 | D7: =D4*D5 -> 62400 | E7: =E4*E5 -> 88948.8 | F7: =D7/Inputs!$D$4 -> 480.4065
A8: Variable costs
A9: Supplement/feed | B9: KES | C9: =Inputs!C$13*Inputs!C$60 -> 12000 | D9: =Inputs!D$13*Inputs!D$60 -> 10000 | E9: =Inputs!E$13*Inputs!E$60 -> 8000 | F9: =D9/Inputs!$D$4 -> 76.988221
A10: Vet, deworm, vaccines | B10: KES | C10: =Inputs!C$13*Inputs!C$50 -> 9000 | D10: =Inputs!D$13*Inputs!D$50 -> 8000 | E10: =Inputs!E$13*Inputs!E$50 -> 7000 | F10: =D10/Inputs!$D$4 -> 61.590577
A11: Minerals | B11: KES | C11: =Inputs!C$13*Inputs!C$51 -> 2000 | D11: =Inputs!D$13*Inputs!D$51 -> 2000 | E11: =Inputs!E$13*Inputs!E$51 -> 2000 | F11: =D11/Inputs!$D$4 -> 15.397644
A12: Selling cost | B12: KES | C12: =C7*Inputs!C$52 -> 2587.2 | D12: =D7*Inputs!D$52 -> 2496 | E12: =E7*Inputs!E$52 -> 2668.464 | F12: =D12/Inputs!$D$4 -> 19.21626
A13: Total variable costs | B13: KES | C13: =SUM(C9:C12) -> 25587.2 | D13: =SUM(D9:D12) -> 22496 | E13: =SUM(E9:E12) -> 19668.464 | F13: =D13/Inputs!$D$4 -> 173.1927
A14: Gross margin | B14: KES | C14: =C7-C13 -> 17532.8 | D14: =D7-D13 -> 39904 | E14: =E7-E13 -> 69280.336 | F14: =D14/Inputs!$D$4 -> 307.2138
A15: Gross margin per head | B15: KES/head | C15: =C14/Inputs!C$13 -> 1753.28 | D15: =D14/Inputs!D$13 -> 3990.4 | E15: =E14/Inputs!E$13 -> 6928.0336 | F15: =D15/Inputs!$D$4 -> 30.72138
A16: Stock capital | B16: KES | C16: =Inputs!C$13*Inputs!C$61 -> 65000 | D16: =Inputs!D$13*Inputs!D$61 -> 65000 | E16: =Inputs!E$13*Inputs!E$61 -> 65000 | F16: =D16/Inputs!$D$4 -> 500.42344
A17: Memo: purchased feed | B17: KES | C17: =C9 -> 12000 | D17: =D9 -> 10000 | E17: =E9 -> 8000 | F17: =D17/Inputs!$D$4 -> 76.988221

Sheet Layers
A1: Layer enterprise budget (annual, KES) - 300 hens assumed, bought-in feed and point-of-lay pullets
A2: Line | B2: Unit | C2: Low (adverse) | D2: Base | E2: High (favourable) | F2: Base in USD | G2: Note
A3: Production
A4: Saleable eggs | B4: eggs/yr | C4: =Inputs!C$14*Inputs!C$63*Inputs!C$64*(1-Inputs!C$65)*(1-Inputs!C$71/2) -> 66422.16 | D4: =Inputs!D$14*Inputs!D$63*Inputs!D$64*(1-Inputs!D$65)*(1-Inputs!D$71/2) -> 72660.881 | E4: =Inputs!E$14*Inputs!E$63*Inputs!E$64*(1-Inputs!E$65)*(1-Inputs!E$71/2) -> 78308.1
A5: Trays of 30 | B5: trays/yr | C5: =C4/30 -> 2214.072 | D5: =D4/30 -> 2422.0294 | E5: =E4/30 -> 2610.27
A6: Flock turnover per year | B6: ratio | C6: =12/Inputs!C$69 -> 0.85714286 | D6: =12/Inputs!D$69 -> 0.85714286 | E6: =12/Inputs!E$69 -> 0.85714286
A7: Revenue
A8: Egg revenue | B8: KES | C8: =C5*Inputs!C$66 -> 797065.92 | D8: =D5*Inputs!D$66 -> 968811.75 | E8: =E5*Inputs!E$66 -> 1174621.5 | F8: =D8/Inputs!$D$4 -> 7458.7093
A9: Spent hen sales | B9: KES | C9: =Inputs!C$14*C6*(1-Inputs!C$71)*Inputs!C$72 -> 74880 | D9: =Inputs!D$14*D6*(1-Inputs!D$71)*Inputs!D$72 -> 83700 | E9: =Inputs!E$14*E6*(1-Inputs!E$71)*Inputs!E$72 -> 96685.714 | F9: =D9/Inputs!$D$4 -> 644.39141
A10: Total revenue | B10: KES | C10: =C8+C9 -> 871945.92 | D10: =D8+D9 -> 1052511.8 | E10: =E8+E9 -> 1271307.2 | F10: =D10/Inputs!$D$4 -> 8103.1007
A11: Variable costs
A12: Layers mash | B12: KES | C12: =Inputs!C$14*Inputs!C$67/1000*365*Inputs!C$68/70 -> 807171.43 | D12: =Inputs!D$14*Inputs!D$67/1000*365*Inputs!D$68/70 -> 701582.14 | E12: =Inputs!E$14*Inputs!E$67/1000*365*Inputs!E$68/70 -> 630720 | F12: =D12/Inputs!$D$4 -> 5401.3561
A13: Replacement pullets | B13: KES | C13: =Inputs!C$14*C6*Inputs!C$70 -> 218571.43 | D13: =Inputs!D$14*D6*Inputs!D$70 -> 205714.29 | E13: =Inputs!E$14*E6*Inputs!E$70 -> 192857.14 | F13: =D13/Inputs!$D$4 -> 1583.7577
A14: Vaccines and drugs | B14: KES | C14: =Inputs!C$14*Inputs!C$73 -> 42000 | D14: =Inputs!D$14*Inputs!D$73 -> 36000 | E14: =Inputs!E$14*Inputs!E$73 -> 30000 | F14: =D14/Inputs!$D$4 -> 277.15759
A15: Packaging and handling | B15: KES | C15: =C5*Inputs!C$74 -> 55351.8 | D15: =D5*Inputs!D$74 -> 60550.734 | E15: =E5*Inputs!E$74 -> 65256.75 | F15: =D15/Inputs!$D$4 -> 466.16933
A16: Transport and marketing | B16: KES | C16: =C8*Inputs!C$75 -> 31882.637 | D16: =D8*Inputs!D$75 -> 29064.353 | E16: =E8*Inputs!E$75 -> 23492.43 | F16: =D16/Inputs!$D$4 -> 223.76128
A17: Total variable costs | B17: KES | C17: =SUM(C12:C16) -> 1154977.3 | D17: =SUM(D12:D16) -> 1032911.5 | E17: =SUM(E12:E16) -> 942326.32 | F17: =D17/Inputs!$D$4 -> 7952.202
A18: Gross margin | B18: KES | C18: =C10-C17 -> -283031.37 | D18: =D10-D17 -> 19600.235 | E18: =E10-E17 -> 328980.89 | F18: =D18/Inputs!$D$4 -> 150.89872
A19: Gross margin per hen | B19: KES/hen | C19: =C18/Inputs!C$14 -> -943.43791 | D19: =D18/Inputs!D$14 -> 65.334115 | E19: =E18/Inputs!E$14 -> 1096.603 | F19: =D19/Inputs!$D$4 -> 0.50299573
A20: Feed cost per tray | B20: KES/tray | C20: =C12/C5 -> 364.56422 | D20: =D12/D5 -> 289.66707 | E20: =E12/E5 -> 241.63018 | F20: =D20/Inputs!$D$4 -> 2.2300952
A21: Stock capital | B21: KES | C21: =Inputs!C$14*Inputs!C$76 -> 240000 | D21: =Inputs!D$14*Inputs!D$76 -> 240000 | E21: =Inputs!E$14*Inputs!E$76 -> 240000 | F21: =D21/Inputs!$D$4 -> 1847.7173
A22: Memo: purchased feed | B22: KES | C22: =C12 -> 807171.43 | D22: =D12 -> 701582.14 | E22: =E12 -> 630720 | F22: =D22/Inputs!$D$4 -> 5401.3561

Sheet OtherPoultry
A1: Improved kienyeji, ducks, guinea fowl, geese (annual, KES) - split of ~1,000 birds ASSUMED; prices for ducks/guinea/geese are ASSUMED
A2: Line | B2: Unit | C2: Low (adverse) | D2: Base | E2: High (favourable) | F2: Base in USD | G2: Note
A3: Improved kienyeji
A4: Birds started per year | B4: birds | C4: =Inputs!C$15*Inputs!C$80 -> 800 | D4: =Inputs!D$15*Inputs!D$80 -> 800 | E4: =Inputs!E$15*Inputs!E$80 -> 800
A5: Birds sold | B5: birds | C5: =C4*(1-Inputs!C$81) -> 672 | D5: =D4*(1-Inputs!D$81) -> 704 | E5: =E4*(1-Inputs!E$81) -> 728
A6: Revenue | B6: KES | C6: =C5*Inputs!C$82 -> 436800 | D6: =D5*Inputs!D$82 -> 528000 | E6: =E5*Inputs!E$82 -> 618800 | F6: =D6/Inputs!$D$4 -> 4064.9781
A7: Chicks/ducklings/keets/goslings | B7: KES | C7: =C4*Inputs!C$83 -> 152000 | D7: =D4*Inputs!D$83 -> 136000 | E7: =E4*Inputs!E$83 -> 124000 | F7: =D7/Inputs!$D$4 -> 1047.0398
A8: Purchased feed | B8: KES | C8: =C4*Inputs!C$84*Inputs!C$78/70 -> 282857.14 | D8: =D4*Inputs!D$84*Inputs!D$78/70 -> 240000 | E8: =E4*Inputs!E$84*Inputs!E$78/70 -> 200571.43 | F8: =D8/Inputs!$D$4 -> 1847.7173
A9: Vet/drugs | B9: KES | C9: =C4*Inputs!C$85 -> 48000 | D9: =D4*Inputs!D$85 -> 32000 | E9: =E4*Inputs!E$85 -> 24000 | F9: =D9/Inputs!$D$4 -> 246.36231
A10: Selling cost | B10: KES | C10: =C6*Inputs!C$111 -> 21840 | D10: =D6*Inputs!D$111 -> 21120 | E10: =E6*Inputs!E$111 -> 18564 | F10: =D10/Inputs!$D$4 -> 162.59912
A11: Gross margin | B11: KES | C11: =C6-C7-C8-C9-C10 -> -67897.143 | D11: =D6-D7-D8-D9-D10 -> 98880 | E11: =E6-E7-E8-E9-E10 -> 251664.57 | F11: =D11/Inputs!$D$4 -> 761.25953
A12: Gross margin per standing bird | B12: KES/bird | C12: =C11/Inputs!C$15 -> -169.74286 | D12: =D11/Inputs!D$15 -> 247.2 | E12: =E11/Inputs!E$15 -> 629.16143 | F12: =D12/Inputs!$D$4 -> 1.9031488
A13: Ducks
A14: Birds started per year | B14: birds | C14: =Inputs!C$16*Inputs!C$88 -> 240 | D14: =Inputs!D$16*Inputs!D$88 -> 240 | E14: =Inputs!E$16*Inputs!E$88 -> 240
A15: Birds sold | B15: birds | C15: =C14*(1-Inputs!C$89) -> 201.6 | D15: =D14*(1-Inputs!D$89) -> 211.2 | E15: =E14*(1-Inputs!E$89) -> 218.4
A16: Revenue | B16: KES | C16: =C15*Inputs!C$90 -> 151200 | D16: =D15*Inputs!D$90 -> 190080 | E16: =E15*Inputs!E$90 -> 229320 | F16: =D16/Inputs!$D$4 -> 1463.3921
A17: Chicks/ducklings/keets/goslings | B17: KES | C17: =C14*Inputs!C$91 -> 57600 | D17: =D14*Inputs!D$91 -> 52800 | E17: =E14*Inputs!E$91 -> 49200 | F17: =D17/Inputs!$D$4 -> 406.49781
A18: Purchased feed | B18: KES | C18: =C14*Inputs!C$92*Inputs!C$78/70 -> 100285.71 | D18: =D14*Inputs!D$92*Inputs!D$78/70 -> 86400 | E18: =E14*Inputs!E$92*Inputs!E$78/70 -> 73542.857 | F18: =D18/Inputs!$D$4 -> 665.17823
A19: Vet/drugs | B19: KES | C19: =C14*Inputs!C$93 -> 14400 | D19: =D14*Inputs!D$93 -> 9600 | E19: =E14*Inputs!E$93 -> 7200 | F19: =D19/Inputs!$D$4 -> 73.908692
A20: Selling cost | B20: KES | C20: =C16*Inputs!C$111 -> 7560 | D20: =D16*Inputs!D$111 -> 7603.2 | E20: =E16*Inputs!E$111 -> 6879.6 | F20: =D20/Inputs!$D$4 -> 58.535684
A21: Gross margin | B21: KES | C21: =C16-C17-C18-C19-C20 -> -28645.714 | D21: =D16-D17-D18-D19-D20 -> 33676.8 | E21: =E16-E17-E18-E19-E20 -> 92497.543 | F21: =D21/Inputs!$D$4 -> 259.27169
A22: Gross margin per standing bird | B22: KES/bird | C22: =C21/Inputs!C$16 -> -238.71429 | D22: =D21/Inputs!D$16 -> 280.64 | E22: =E21/Inputs!E$16 -> 770.81286 | F22: =D22/Inputs!$D$4 -> 2.1605974
A23: Guinea fowl
A24: Birds started per year | B24: birds | C24: =Inputs!C$17*Inputs!C$96 -> 180 | D24: =Inputs!D$17*Inputs!D$96 -> 180 | E24: =Inputs!E$17*Inputs!E$96 -> 180
A25: Birds sold | B25: birds | C25: =C24*(1-Inputs!C$97) -> 133.2 | D25: =D24*(1-Inputs!D$97) -> 144 | E25: =E24*(1-Inputs!E$97) -> 153
A26: Revenue | B26: KES | C26: =C25*Inputs!C$98 -> 93240 | D26: =D25*Inputs!D$98 -> 122400 | E26: =E25*Inputs!E$98 -> 153000 | F26: =D26/Inputs!$D$4 -> 942.33582
A27: Chicks/ducklings/keets/goslings | B27: KES | C27: =C24*Inputs!C$99 -> 50400 | D27: =D24*Inputs!D$99 -> 45000 | E27: =E24*Inputs!E$99 -> 41400 | F27: =D27/Inputs!$D$4 -> 346.44699
A28: Purchased feed | B28: KES | C28: =C24*Inputs!C$100*Inputs!C$78/70 -> 43392.857 | D28: =D24*Inputs!D$100*Inputs!D$78/70 -> 37800 | E28: =E24*Inputs!E$100*Inputs!E$78/70 -> 32592.857 | F28: =D28/Inputs!$D$4 -> 291.01547
A29: Vet/drugs | B29: KES | C29: =C24*Inputs!C$101 -> 10800 | D29: =D24*Inputs!D$101 -> 7200 | E29: =E24*Inputs!E$101 -> 5400 | F29: =D29/Inputs!$D$4 -> 55.431519
A30: Selling cost | B30: KES | C30: =C26*Inputs!C$111 -> 4662 | D30: =D26*Inputs!D$111 -> 4896 | E30: =E26*Inputs!E$111 -> 4590 | F30: =D30/Inputs!$D$4 -> 37.693433
A31: Gross margin | B31: KES | C31: =C26-C27-C28-C29-C30 -> -16014.857 | D31: =D26-D27-D28-D29-D30 -> 27504 | E31: =E26-E27-E28-E29-E30 -> 69017.143 | F31: =D31/Inputs!$D$4 -> 211.7484
A32: Gross margin per standing bird | B32: KES/bird | C32: =C31/Inputs!C$17 -> -133.45714 | D32: =D31/Inputs!D$17 -> 229.2 | E32: =E31/Inputs!E$17 -> 575.14286 | F32: =D32/Inputs!$D$4 -> 1.76457
A33: Geese
A34: Birds started per year | B34: birds | C34: =Inputs!C$18*Inputs!C$104 -> 60 | D34: =Inputs!D$18*Inputs!D$104 -> 60 | E34: =Inputs!E$18*Inputs!E$104 -> 60
A35: Birds sold | B35: birds | C35: =C34*(1-Inputs!C$105) -> 49.2 | D35: =D34*(1-Inputs!D$105) -> 52.8 | E35: =E34*(1-Inputs!E$105) -> 54.6
A36: Revenue | B36: KES | C36: =C35*Inputs!C$106 -> 113160 | D36: =D35*Inputs!D$106 -> 147840 | E36: =E35*Inputs!E$106 -> 180180 | F36: =D36/Inputs!$D$4 -> 1138.1939
A37: Chicks/ducklings/keets/goslings | B37: KES | C37: =C34*Inputs!C$107 -> 39000 | D37: =D34*Inputs!D$107 -> 36000 | E37: =E34*Inputs!E$107 -> 33000 | F37: =D37/Inputs!$D$4 -> 277.15759
A38: Purchased feed | B38: KES | C38: =C34*Inputs!C$108*Inputs!C$78/70 -> 27000 | D38: =D34*Inputs!D$108*Inputs!D$78/70 -> 21600 | E38: =E34*Inputs!E$108*Inputs!E$78/70 -> 18385.714 | F38: =D38/Inputs!$D$4 -> 166.29456
A39: Vet/drugs | B39: KES | C39: =C34*Inputs!C$109 -> 4800 | D39: =D34*Inputs!D$109 -> 3600 | E39: =E34*Inputs!E$109 -> 2400 | F39: =D39/Inputs!$D$4 -> 27.715759
A40: Selling cost | B40: KES | C40: =C36*Inputs!C$111 -> 5658 | D40: =D36*Inputs!D$111 -> 5913.6 | E40: =E36*Inputs!E$111 -> 5405.4 | F40: =D40/Inputs!$D$4 -> 45.527754
A41: Gross margin | B41: KES | C41: =C36-C37-C38-C39-C40 -> 36702 | D41: =D36-D37-D38-D39-D40 -> 80726.4 | E41: =E36-E37-E38-E39-E40 -> 120988.89 | F41: =D41/Inputs!$D$4 -> 621.49819
A42: Gross margin per standing bird | B42: KES/bird | C42: =C41/Inputs!C$18 -> 611.7 | D42: =D41/Inputs!D$18 -> 1345.44 | E42: =E41/Inputs!E$18 -> 2016.4814 | F42: =D42/Inputs!$D$4 -> 10.358303
A43: Total other poultry
A44: Total revenue | B44: KES | C44: =C6+C16+C26+C36 -> 794400 | D44: =D6+D16+D26+D36 -> 988320 | E44: =E6+E16+E26+E36 -> 1181300 | F44: =D44/Inputs!$D$4 -> 7608.8998
A45: Total variable costs | B45: KES | C45: =C7+C8+C9+C10+C17+C18+C19+C20+C27+C28+C29+C30+C37+C38+C39+C40 -> 870255.71 | D45: =D7+D8+D9+D10+D17+D18+D19+D20+D27+D28+D29+D30+D37+D38+D39+D40 -> 747532.8 | E45: =E7+E8+E9+E10+E17+E18+E19+E20+E27+E28+E29+E30+E37+E38+E39+E40 -> 647131.86 | F45: =D45/Inputs!$D$4 -> 5755.122
A46: Gross margin | B46: KES | C46: =C44-C45 -> -75855.714 | D46: =D44-D45 -> 240787.2 | E46: =E44-E45 -> 534168.14 | F46: =D46/Inputs!$D$4 -> 1853.7778
A47: Stock capital | B47: KES | C47: =Inputs!C$15*Inputs!C$86+Inputs!C$16*Inputs!C$94+Inputs!C$17*Inputs!C$102+Inputs!C$18*Inputs!C$110 -> 404000 | D47: =Inputs!D$15*Inputs!D$86+Inputs!D$16*Inputs!D$94+Inputs!D$17*Inputs!D$102+Inputs!D$18*Inputs!D$110 -> 404000 | E47: =Inputs!E$15*Inputs!E$86+Inputs!E$16*Inputs!E$94+Inputs!E$17*Inputs!E$102+Inputs!E$18*Inputs!E$110 -> 404000 | F47: =D47/Inputs!$D$4 -> 3110.3241
A48: Memo: purchased feed | B48: KES | C48: =C8+C18+C28+C38 -> 453535.71 | D48: =D8+D18+D28+D38 -> 385800 | E48: =E8+E18+E28+E38 -> 325092.86 | F48: =D48/Inputs!$D$4 -> 2970.2056
A49: Birds (all other poultry) | B49: birds | C49: =Inputs!C$15+Inputs!C$16+Inputs!C$17+Inputs!C$18 -> 700 | D49: =Inputs!D$15+Inputs!D$16+Inputs!D$17+Inputs!D$18 -> 700 | E49: =Inputs!E$15+Inputs!E$16+Inputs!E$17+Inputs!E$18 -> 700

Sheet Labour
A1: Staffing and labour (KES) - 3 existing staff, roles proposed (currently undefined)
A2: Line | B2: Unit | C2: Low (adverse) | D2: Base | E2: High (favourable) | F2: Base in USD | G2: Note
A3: Roles and pay
A4: Staff 1: working supervisor (cattle/dairy, daily tally, key-holder) | B4: KES/month | C4: =Inputs!C$116 -> 18000 | D4: =Inputs!D$116 -> 18000 | E4: =Inputs!E$116 -> 18000 | F4: =D4/Inputs!$D$4 -> 138.5788
A5: Staff 2: poultry lead (layers, eggs, brooding, feed store) | B5: KES/month | C5: =Inputs!C$117 -> 11500 | D5: =Inputs!D$117 -> 11500 | E5: =Inputs!E$117 -> 11500 | F5: =D5/Inputs!$D$4 -> 88.536454
A6: Staff 3: small-stock and general hand (sheep, goats, fodder, relief) | B6: KES/month | C6: =Inputs!C$118 -> 10500 | D6: =Inputs!D$118 -> 10500 | E6: =Inputs!E$118 -> 10500 | F6: =D6/Inputs!$D$4 -> 80.837632
A7: Premium over legal minimum, staff 1 | B7: % | C7: =C4/Inputs!C$115-1 -> 0.24764939 | D7: =D4/Inputs!D$115-1 -> 0.24764939 | E7: =E4/Inputs!E$115-1 -> 0.24764939
A8: Premium over legal minimum, staff 2 | B8: % | C8: =C5/Inputs!C$114-1 -> 0.24515742 | D8: =D5/Inputs!D$114-1 -> 0.24515742 | E8: =E5/Inputs!E$114-1 -> 0.24515742
A9: Premium over legal minimum, staff 3 | B9: % | C9: =C6/Inputs!C$114-1 -> 0.13688286 | D9: =D6/Inputs!D$114-1 -> 0.13688286 | E9: =E6/Inputs!E$114-1 -> 0.13688286
A10: Annual cost
A11: Basic pay | B11: KES | C11: =(C4+C5+C6)*12 -> 480000 | D11: =(D4+D5+D6)*12 -> 480000 | E11: =(E4+E5+E6)*12 -> 480000 | F11: =D11/Inputs!$D$4 -> 3695.4346
A12: Employer NSSF + housing levy + NITA | B12: KES | C12: =(C4+C5+C6)*12*(Inputs!C$119+Inputs!C$120)+3*12*Inputs!C$121 -> 37800 | D12: =(D4+D5+D6)*12*(Inputs!D$119+Inputs!D$120)+3*12*Inputs!D$121 -> 37800 | E12: =(E4+E5+E6)*12*(Inputs!E$119+Inputs!E$120)+3*12*Inputs!E$121 -> 37800 | F12: =D12/Inputs!$D$4 -> 291.01547
A13: Casual relief labour | B13: KES | C13: =Inputs!C$122*Inputs!C$123 -> 17500 | D13: =Inputs!D$122*Inputs!D$123 -> 15000 | E13: =Inputs!E$122*Inputs!E$123 -> 12500 | F13: =D13/Inputs!$D$4 -> 115.48233
A14: Total hired labour cost | B14: KES | C14: =C11+C12+C13 -> 535300 | D14: =D11+D12+D13 -> 532800 | E14: =E11+E12+E13 -> 530300 | F14: =D14/Inputs!$D$4 -> 4101.9324
A15: Monthly pay bill (basic) | B15: KES/month | C15: =C4+C5+C6 -> 40000 | D15: =D4+D5+D6 -> 40000 | E15: =E4+E5+E6 -> 40000 | F15: =D15/Inputs!$D$4 -> 307.95288
A16: Hours test
A17: Task hours required per year | B17: h | C17: =(Inputs!C$126+Inputs!C$127+Inputs!C$128+Inputs!C$129+Inputs!C$130+Inputs!C$131)*365 -> 4672 | D17: =(Inputs!D$126+Inputs!D$127+Inputs!D$128+Inputs!D$129+Inputs!D$130+Inputs!D$131)*365 -> 4015 | E17: =(Inputs!E$126+Inputs!E$127+Inputs!E$128+Inputs!E$129+Inputs!E$130+Inputs!E$131)*365 -> 3558.75
A18: Productive hours per person per year | B18: h | C18: =Inputs!C$124*Inputs!C$125 -> 2160 | D18: =Inputs!D$124*Inputs!D$125 -> 2160 | E18: =Inputs!E$124*Inputs!E$125 -> 2160
A19: FTE required | B19: FTE | C19: =C17/C18 -> 2.162963 | D19: =D17/D18 -> 1.8587963 | E19: =E17/E18 -> 1.6475694
A20: Utilisation of 3 staff | B20: % | C20: =C19/3 -> 0.72098765 | D20: =D19/3 -> 0.61959877 | E20: =E19/3 -> 0.54918981
A21: Minimum people for 7-day cover (1 on site, 5.5-day weeks) | B21: FTE | C21: =365/(5.5*52*(1-3/52)) -> 1.3543599 | D21: =365/(5.5*52*(1-3/52)) -> 1.3543599 | E21: =365/(5.5*52*(1-3/52)) -> 1.3543599 | G21: One person on site every day needs ~1.4 people before leave; 2 for resilience

Sheet Overhead
A1: Control and management overhead: PLAN generic structure vs right-sized for this farm (KES/yr). All ASSUMED quotes; replace with real quotes.
A2: Item | B2: Class | C2: PLAN generic KES/yr | D2: Right-sized KES/yr | E2: Treatment | F2: Generic USD | G2: Right-sized USD | H2: Note
A3: External bookkeeper (remote, monthly) | B3: Control | C3: 72000 | D3: 48000 | E3: KEEP (non-waivable) | F3: =C3/Inputs!$D$4 -> 554.31519 | G3: =D3/Inputs!$D$4 -> 369.54346 | H3: KES 6k vs 4k per month; owner-only vendor creation, M-Pesa/bank feeds go to owner
A4: Randomised spot-counts | B4: Control | C4: 60000 | D4: 18000 | E4: KEEP, cheaper | F4: =C4/Inputs!$D$4 -> 461.92932 | G4: =D4/Inputs!$D$4 -> 138.5788 | H4: 4 audited counts vs 6 neighbour/para-vet/representative counts, randomised, photo + tally
A5: Quarterly non-preparer reconciliation + annual accountant review | B5: Control | C5: 80000 | D5: 36000 | E5: KEEP, scaled | F5: =C5/Inputs!$D$4 -> 615.90577 | G5: =D5/Inputs!$D$4 -> 277.15759 | H5: Accountant reviews bookkeeper's M-Pesa/bank reconciliation once a quarter, short annual review
A6: Consultant agronomist and stockman backstop | B6: Control | C6: 120000 | D6: 24000 | E6: BUY BY THE HOUR | F6: =C6/Inputs!$D$4 -> 923.85865 | G6: =D6/Inputs!$D$4 -> 184.77173 | H6: ~6 visits/yr at ~KES 4k, on call, instead of a retainer
A7: Farm Model upkeep | B7: Control | C7: 60000 | D7: 0 | E7: DROP | F7: =C7/Inputs!$D$4 -> 461.92932 | G7: =D7/Inputs!$D$4 -> 0 | H7: Owner or bookkeeper maintains this workbook
A8: Representative / steward | B8: Control | C8: 120000 | D8: 36000 | E8: KEEP, cheaper | F8: =C8/Inputs!$D$4 -> 923.85865 | G8: =D8/Inputs!$D$4 -> 277.15759 | H8: Trusted unrelated local person with second mandate, KES 3k/month stipend
A9: Hotline | B9: Control | C9: 12000 | D9: 0 | E9: DROP | F9: =C9/Inputs!$D$4 -> 92.385865 | G9: =D9/Inputs!$D$4 -> 0 | H9: WhatsApp/SMS to owner and representative
A10: Fidelity premium | B10: Control | C10: 20000 | D10: 0 | E10: DROP | F10: =C10/Inputs!$D$4 -> 153.97644 | G10: =D10/Inputs!$D$4 -> 0 | H10: Staff do not handle cash; sales proceeds paid to owner till/M-Pesa
A11: Entity and legal (amortised 3 yrs) | B11: Control | C11: 50000 | D11: 15000 | E11: KEEP, scaled | F11: =C11/Inputs!$D$4 -> 384.9411 | G11: =D11/Inputs!$D$4 -> 115.48233 | H11: Lawyer hours: staff contracts, fraud-response one-pager, title/lease advice (separate)
A12: GSM alarms and sensors (amortised) | B12: Control | C12: 20000 | D12: 0 | E12: DROP | F12: =C12/Inputs!$D$4 -> 153.97644 | G12: =D12/Inputs!$D$4 -> 0 | H12: Revisit if layers move to a closed brooder/house
A13: Data store, geotag/camera tooling (amortised) | B13: Control | C13: 20000 | D13: 11000 | E13: KEEP, cheap | F13: =C13/Inputs!$D$4 -> 153.97644 | G13: =D13/Inputs!$D$4 -> 84.687043 | H13: Smartphone camera + shared sheet + bundles
A14: Coordinator | B14: Control | C14: 180000 | D14: 0 | E14: DROP | F14: =C14/Inputs!$D$4 -> 1385.788 | G14: =D14/Inputs!$D$4 -> 0 | H14: Owner is coordinator at this scale
... A16: Ad hoc consultants | B16: Control | C16: 80000 | D16: 0 | E16: DROP | F16: =C16/Inputs!$D$4 -> 615.90577 | G16: =D16/Inputs!$D$4 -> 0 | H16: Covered by hourly consultant line above
A17: Total control-and-oversight cost | C17: =SUM(C3:C16) -> 994000 | D17: =SUM(D3:D16) -> 188000 | F17: =C17/Inputs!$D$4 -> 7652.6291 | G17: =D17/Inputs!$D$4 -> 1447.3786
A18: Memo: only the core items (bookkeeper, spot-counts, reconciliation/review, representative, legal) | C18: =C3+C4+C5+C8+C11 -> 382000 | D18: =D3+D4+D5+D8+D11 -> 153000 | F18: =C18/Inputs!$D$4 -> 2940.95 | G18: =D18/Inputs!$D$4 -> 1177.9198
A20: Management cost (reported separately, B10)
A21: Manager (KES 35k/month) | B21: Management | C21: 420000 | D21: 0 | E21: DROP | F21: =C21/Inputs!$D$4 -> 3233.5053 | G21: =D21/Inputs!$D$4 -> 0 | H21: Local livestock manager pay assumed; no source. Existing 3 staff + owner replace this
A22: Deputy (KES 20k/month) | B22: Management | C22: 240000 | D22: 0 | E22: DROP | F22: =C22/Inputs!$D$4 -> 1847.7173 | G22: =D22/Inputs!$D$4 -> 0 | H22: Assumed
A23: Supervisor stipend uplift (working supervisor accountable for daily tallies) | B23: Management | C23: 0 | D23: 72000 | E23: ADD | F23: =C23/Inputs!$D$4 -> 0 | G23: =D23/Inputs!$D$4 -> 554.31519 | H23: KES 6k/month on top of staff 1 pay on Labour sheet, tied to tally completeness
A24: Total management cost | C24: =SUM(C21:C23) -> 660000 | D24: =SUM(D21:D23) -> 72000 | F24: =C24/Inputs!$D$4 -> 5081.2226 | G24: =D24/Inputs!$D$4 -> 554.31519
A25: TOTAL overhead (controls + management) | C25: =C17+C24 -> 1654000 | D25: =D17+D24 -> 260000 | F25: =C25/Inputs!$D$4 -> 12733.852 | G25: =D25/Inputs!$D$4 -> 2001.6937

Sheet Farm_PnL
A1: Consolidated farm P&L before management and controls (KES per year)
A2: Line | B2: Unit | C2: Low (adverse) | D2: Base | E2: High (favourable) | F2: Base in USD | G2: Note
A3: Revenue
A4: Cattle and dairy | B4: KES | C4: =Cattle!C8 -> 308080 | D4: =Cattle!D8 -> 444800 | E4: =Cattle!E8 -> 676450 | F4: =D4/Inputs!$D$4 -> 3424.4361
A5: Sheep | B5: KES | C5: =Sheep!C7 -> 140616 | D5: =Sheep!D7 -> 228480 | E5: =Sheep!E7 -> 350784 | F5: =D5/Inputs!$D$4 -> 1759.0269
A6: Goats | B6: KES | C6: =Goats!C7 -> 43120 | D6: =Goats!D7 -> 62400 | E6: =Goats!E7 -> 88948.8 | F6: =D6/Inputs!$D$4 -> 480.4065
A7: Layers | B7: KES | C7: =Layers!C10 -> 871945.92 | D7: =Layers!D10 -> 1052511.8 | E7: =Layers!E10 -> 1271307.2 | F7: =D7/Inputs!$D$4 -> 8103.1007
A8: Kienyeji, ducks, guinea fowl, geese | B8: KES | C8: =OtherPoultry!C44 -> 794400 | D8: =OtherPoultry!D44 -> 988320 | E8: =OtherPoultry!E44 -> 1181300 | F8: =D8/Inputs!$D$4 -> 7608.8998
A9: Total revenue | B9: KES | C9: =C4+C5+C6+C7+C8 -> 2158161.9 | D9: =D4+D5+D6+D7+D8 -> 2776511.8 | E9: =E4+E5+E6+E7+E8 -> 3568790 | F9: =D9/Inputs!$D$4 -> 21375.87
A10: Gross margin by enterprise
A11: Cattle and dairy | B11: KES | C11: =Cattle!C17 -> -63160 | D11: =Cattle!D17 -> 107600 | E11: =Cattle!E17 -> 329400 | F11: =D11/Inputs!$D$4 -> 828.39326
A12: Sheep | B12: KES | C12: =Sheep!C14 -> 17179.04 | D12: =Sheep!D14 -> 119340.8 | E12: =Sheep!E14 -> 255260.48 | F12: =D12/Inputs!$D$4 -> 918.78359
A13: Goats | B13: KES | C13: =Goats!C14 -> 17532.8 | D13: =Goats!D14 -> 39904 | E13: =Goats!E14 -> 69280.336 | F13: =D13/Inputs!$D$4 -> 307.2138
A14: Layers | B14: KES | C14: =Layers!C18 -> -283031.37 | D14: =Layers!D18 -> 19600.235 | E14: =Layers!E18 -> 328980.89 | F14: =D14/Inputs!$D$4 -> 150.89872
A15: Kienyeji, ducks, guinea fowl, geese | B15: KES | C15: =OtherPoultry!C46 -> -75855.714 | D15: =OtherPoultry!D46 -> 240787.2 | E15: =OtherPoultry!E46 -> 534168.14 | F15: =D15/Inputs!$D$4 -> 1853.7778
A16: Total gross margin | B16: KES | C16: =C11+C12+C13+C14+C15 -> -387335.25 | D16: =D11+D12+D13+D14+D15 -> 527232.23 | E16: =E11+E12+E13+E14+E15 -> 1517089.9 | F16: =D16/Inputs!$D$4 -> 4059.0672
A17: Total variable costs | B17: KES | C17: =Cattle!C16+Sheep!C13+Goats!C13+Layers!C17+OtherPoultry!C45 -> 2545497.2 | D17: =Cattle!D16+Sheep!D13+Goats!D13+Layers!D17+OtherPoultry!D45 -> 2249279.5 | E17: =Cattle!E16+Sheep!E13+Goats!E13+Layers!E17+OtherPoultry!E45 -> 2051700.2 | F17: =D17/Inputs!$D$4 -> 17316.803
A18: Labour and fixed costs
A19: Hired labour (3 staff + relief + statutory) | B19: KES | C19: =Labour!C14 -> 535300 | D19: =Labour!D14 -> 532800 | E19: =Labour!E14 -> 530300 | F19: =D19/Inputs!$D$4 -> 4101.9324
A20: Water and power | B20: KES | C20: =Inputs!C$133 -> 70000 | D20: =Inputs!D$133 -> 60000 | E20: =Inputs!E$133 -> 50000 | F20: =D20/Inputs!$D$4 -> 461.92932
A21: Transport and communications | B21: KES | C21: =Inputs!C$134 -> 55000 | D21: =Inputs!D$134 -> 48000 | E21: =Inputs!E$134 -> 40000 | F21: =D21/Inputs!$D$4 -> 369.54346
A22: Licences, permits, cess | B22: KES | C22: =Inputs!C$135 -> 10000 | D22: =Inputs!D$135 -> 10000 | E22: =Inputs!E$135 -> 10000 | F22: =D22/Inputs!$D$4 -> 76.988221
A23: Land rates | B23: KES | C23: =Inputs!C$136 -> 6000 | D23: =Inputs!D$136 -> 6000 | E23: =Inputs!E$136 -> 6000 | F23: =D23/Inputs!$D$4 -> 46.192932
A24: Repairs and maintenance | B24: KES | C24: =Inputs!C$25*Inputs!C$27 -> 32000 | D24: =Inputs!D$25*Inputs!D$27 -> 24000 | E24: =Inputs!E$25*Inputs!E$27 -> 16000 | F24: =D24/Inputs!$D$4 -> 184.77173
A25: Depreciation of buildings and equipment | B25: KES | C25: =Inputs!C$25/Inputs!C$26 -> 80000 | D25: =Inputs!D$25/Inputs!D$26 -> 80000 | E25: =Inputs!E$25/Inputs!E$26 -> 80000 | F25: =D25/Inputs!$D$4 -> 615.90577
A26: Stock capital (all species) | B26: KES | C26: =Cattle!C19+Sheep!C16+Goats!C16+Layers!C21+OtherPoultry!C47 -> 1609000 | D26: =Cattle!D19+Sheep!D16+Goats!D16+Layers!D21+OtherPoultry!D47 -> 1609000 | E26: =Cattle!E19+Sheep!E16+Goats!E16+Layers!E21+OtherPoultry!E47 -> 1609000 | F26: =D26/Inputs!$D$4 -> 12387.405
A27: Insurance on stock | B27: KES | C27: =C26*Inputs!C$137 -> 0 | D27: =D26*Inputs!D$137 -> 0 | E27: =E26*Inputs!E$137 -> 0 | F27: =D27/Inputs!$D$4 -> 0
A28: Total labour + fixed costs | B28: KES | C28: =C19+C20+C21+C22+C23+C24+C25+C27 -> 788300 | D28: =D19+D20+D21+D22+D23+D24+D25+D27 -> 760800 | E28: =E19+E20+E21+E22+E23+E24+E25+E27 -> 732300 | F28: =D28/Inputs!$D$4 -> 5857.2638
A29: Result
A30: OMBM: operating margin before management and controls | B30: KES | C30: =C16-C28 -> -1175635.2 | D30: =D16-D28 -> -233567.77 | E30: =E16-E28 -> 784789.85 | F30: =D30/Inputs!$D$4 -> -1798.1967 | G30: B10 definition; owner time excluded here (priced separately in B12 via p); no land rent charged
A31: OMBM as % of revenue | B31: % | C31: =IF(C9=0,0,C30/C9) -> -0.54473913 | D31: =IF(D9=0,0,D30/D9) -> -0.084122736 | E31: =IF(E9=0,0,E30/E9) -> 0.21990362
A32: Cash margin (OMBM + depreciation) | B32: KES | C32: =C30+C25 -> -1095635.2 | D32: =D30+D25 -> -153567.77 | E32: =E30+E25 -> 864789.85 | F32: =D32/Inputs!$D$4 -> -1182.2909
A33: Contribution ratio (1 - variable cost / revenue) | B33: ratio | C33: =1-C17/C9 -> -0.1794746 | D33: =1-D17/D9 -> 0.18989015 | E33: =1-E17/E9 -> 0.42509922
A34: Gross margin per task hour (before fixed costs)
A35: Cattle and dairy | B35: KES/h | C35: =C11/(Inputs!C$126*365) -> -43.260274 | D35: =D11/(Inputs!D$126*365) -> 84.227006 | E35: =E11/(Inputs!E$126*365) -> 282.02055 | F35: =D35/Inputs!$D$4 -> 0.64844873
A36: Sheep | B36: KES/h | C36: =C12/(Inputs!C$127*365) -> 26.147702 | D36: =D12/(Inputs!D$127*365) -> 217.97406 | E36: =E12/(Inputs!E$127*365) -> 537.95675 | F36: =D36/Inputs!$D$4 -> 1.6781435
A37: Goats | B37: KES/h | C37: =C13/(Inputs!C$128*365) -> 80.058447 | D37: =D13/(Inputs!D$128*365) -> 218.65205 | E37: =E13/(Inputs!E$128*365) -> 421.79809 | F37: =D37/Inputs!$D$4 -> 1.6833633
A38: Layers | B38: KES/h | C38: =C14/(Inputs!C$129*365) -> -430.79357 | D38: =D14/(Inputs!D$129*365) -> 35.799515 | E38: =E14/(Inputs!E$129*365) -> 693.32116 | F38: =D38/Inputs!$D$4 -> 0.2756141
A39: Other poultry | B39: KES/h | C39: =C15/(Inputs!C$130*365) -> -74.222812 | D39: =D15/(Inputs!D$130*365) -> 263.87638 | E39: =E15/(Inputs!E$130*365) -> 665.21562 | F39: =D39/Inputs!$D$4 -> 2.0315373
A40: Scale and capital
A41: Livestock units | B41: TLU | C41: =Inputs!C$11*Inputs!C$19+(Inputs!C$12+Inputs!C$13)*Inputs!C$20+(Inputs!C$14+OtherPoultry!C49)*Inputs!C$21 -> 23 | D41: =Inputs!D$11*Inputs!D$19+(Inputs!D$12+Inputs!D$13)*Inputs!D$20+(Inputs!D$14+OtherPoultry!D49)*Inputs!D$21 -> 23 | E41: =Inputs!E$11*Inputs!E$19+(Inputs!E$12+Inputs!E$13)*Inputs!E$20+(Inputs!E$14+OtherPoultry!E49)*Inputs!E$21 -> 23 | G41: Ruminants alone ~13 TLU
A42: Purchased feed and forage | B42: KES | C42: =Cattle!C20+Sheep!C17+Goats!C17+Layers!C22+OtherPoultry!C48 -> 1567587.1 | D42: =Cattle!D20+Sheep!D17+Goats!D17+Layers!D22+OtherPoultry!D48 -> 1364582.1 | E42: =Cattle!E20+Sheep!E17+Goats!E17+Layers!E22+OtherPoultry!E48 -> 1243412.9 | F42: =D42/Inputs!$D$4 -> 10505.675
A43: Purchased feed as % of revenue | B43: % | C43: =C42/C9 -> 0.72635289 | D43: =D42/D9 -> 0.49147357 | E43: =E42/E9 -> 0.34841301
A44: Working capital (3 months of variable costs + labour) | B44: KES | C44: =(C17+C19)/4 -> 770199.29 | D44: =(D17+D19)/4 -> 695519.88 | E44: =(E17+E19)/4 -> 645500.04 | F44: =D44/Inputs!$D$4 -> 5354.6838
A45: K: operating capital at risk (stock + buildings + working capital) | B45: KES | C45: =C26+Inputs!C$25+C44 -> 3179199.3 | D45: =D26+Inputs!D$25+D44 -> 3104519.9 | E45: =E26+Inputs!E$25+E44 -> 3054500 | F45: =D45/Inputs!$D$4 -> 23901.146
A46: Land value L | B46: KES | C46: =Inputs!C$23*Inputs!C$24 -> 4200000 | D46: =Inputs!D$23*Inputs!D$24 -> 6000000 | E46: =Inputs!E$23*Inputs!E$24 -> 8400000 | F46: =D46/Inputs!$D$4 -> 46192.932
A47: Asset base (land + buildings + stock) | B47: KES | C47: =C46+Inputs!C$25+C26 -> 6609000 | D47: =D46+Inputs!D$25+D26 -> 8409000 | E47: =E46+Inputs!E$25+E26 -> 10809000 | F47: =D47/Inputs!$D$4 -> 64739.395
A48: Revenue in USD | B48: USD | C48: =C9/Inputs!C$4 -> 16615.305 | D48: =D9/Inputs!D$4 -> 21375.87 | E48: =E9/Inputs!E$4 -> 27475.479
A49: Revenue per acre | B49: KES/acre | C49: =C9/Inputs!C$23 -> 179846.83 | D49: =D9/Inputs!D$23 -> 231375.98 | E49: =E9/Inputs!E$23 -> 297399.17 | F49: =D49/Inputs!$D$4 -> 1781.3225

Sheet B12
A1: B12 hurdle procedure and ranking (annual after-risk income to owner, real KES)
A2: Line | B2: Unit | C2: Low (adverse) | D2: Base | E2: High (favourable) | F2: Base in USD | G2: Note
A3: Common terms
A4: OMBM | B4: KES | C4: =Farm_PnL!C30 -> -1175635.2 | D4: =Farm_PnL!D30 -> -233567.77 | E4: =Farm_PnL!E30 -> 784789.85 | F4: =D4/Inputs!$D$4 -> -1798.1967
A5: Revenue | B5: KES | C5: =Farm_PnL!C9 -> 2158161.9 | D5: =Farm_PnL!D9 -> 2776511.8 | E5: =Farm_PnL!E9 -> 3568790 | F5: =D5/Inputs!$D$4 -> 21375.87
A6: K | B6: KES | C6: =Farm_PnL!C45 -> 3179199.3 | D6: =Farm_PnL!D45 -> 3104519.9 | E6: =Farm_PnL!E45 -> 3054500 | F6: =D6/Inputs!$D$4 -> 23901.146
A7: g x L (land value change) | B7: KES | C7: =Inputs!C$6*Farm_PnL!C46 -> 0 | D7: =Inputs!D$6*Farm_PnL!D46 -> 60000 | E7: =Inputs!E$6*Farm_PnL!E46 -> 168000 | F7: =D7/Inputs!$D$4 -> 461.92932
A8: Risk charge r x K | B8: KES | C8: =Inputs!C$7*Farm_PnL!C45 -> 158959.96 | D8: =Inputs!D$7*Farm_PnL!D45 -> 124180.8 | E8: =Inputs!E$7*Farm_PnL!E45 -> 91635.001 | F8: =D8/Inputs!$D$4 -> 956.04585
A9: Option 1: Self-run, PLAN generic structure (manager + deputy + full controls)
A10: Owner hours | B10: h/yr | C10: =Inputs!C$139 -> 450 | D10: =Inputs!D$139 -> 390 | E10: =Inputs!E$139 -> 330
A11: Controls | B11: KES | C11: =Overhead!$C$17 -> 994000 | D11: =Overhead!$C$17 -> 994000 | E11: =Overhead!$C$17 -> 994000 | F11: =D11/Inputs!$D$4 -> 7652.6291
A12: Manager + deputy | B12: KES | C12: =Overhead!$C$24 -> 660000 | D12: =Overhead!$C$24 -> 660000 | E12: =Overhead!$C$24 -> 660000 | F12: =D12/Inputs!$D$4 -> 5081.2226
A13: Set-up / years | B13: KES | C13: =Inputs!C$145/Inputs!C$147 -> 112500 | D13: =Inputs!D$145/Inputs!D$147 -> 112500 | E13: =Inputs!E$145/Inputs!E$147 -> 112500 | F13: =D13/Inputs!$D$4 -> 866.11748
A14: VALUE: self-run generic | B14: KES | C14: =C4-C11-C12-C10*Inputs!C$8-C13-C8+C7 -> -3281095.2 | D14: =D4-D11-D12-D10*Inputs!D$8-D13-D8+D7 -> -2181248.6 | E14: =E4-E11-E12-E10*Inputs!E$8-E13-E8+E7 -> -987845.15 | F14: =D14/Inputs!$D$4 -> -16793.045
A15: Option 2: Owner-operator with simplified controls (3 staff, working supervisor, remote checks)
A16: Owner hours | B16: h/yr | C16: =Inputs!C$140*52+Inputs!C$141*Inputs!C$142+Inputs!C$143*52 -> 712 | D16: =Inputs!D$140*52+Inputs!D$141*Inputs!D$142+Inputs!D$143*52 -> 460 | E16: =Inputs!E$140*52+Inputs!E$141*Inputs!E$142+Inputs!E$143*52 -> 298
A17: Controls (right-sized) | B17: KES | C17: =Overhead!$D$17 -> 188000 | D17: =Overhead!$D$17 -> 188000 | E17: =Overhead!$D$17 -> 188000 | F17: =D17/Inputs!$D$4 -> 1447.3786
A18: Management (supervisor stipend) | B18: KES | C18: =Overhead!$D$24 -> 72000 | D18: =Overhead!$D$24 -> 72000 | E18: =Overhead!$D$24 -> 72000 | F18: =D18/Inputs!$D$4 -> 554.31519
A19: Set-up / years | B19: KES | C19: =Inputs!C$146/Inputs!C$147 -> 15000 | D19: =Inputs!D$146/Inputs!D$147 -> 15000 | E19: =Inputs!E$146/Inputs!E$147 -> 15000 | F19: =D19/Inputs!$D$4 -> 115.48233
A20: VALUE: owner-operator simplified | B20: KES | C20: =C4-C17-C18-C16*Inputs!C$8-C19-C8+C7 -> -1894395.2 | D20: =D4-D17-D18-D16*Inputs!D$8-D19-D8+D7 -> -710748.56 | E20: =E4-E17-E18-E16*Inputs!E$8-E19-E8+E7 -> 511654.85 | F20: =D20/Inputs!$D$4 -> -5471.9267
A21: Option 3: Lease (land and buildings; stock and staff exit)
A22: Rent | B22: KES | C22: =Inputs!C$23*Inputs!C$150 -> 72000 | D22: =Inputs!D$23*Inputs!D$150 -> 96000 | E22: =Inputs!E$23*Inputs!E$150 -> 120000 | F22: =D22/Inputs!$D$4 -> 739.08692
A23: Net stock proceeds | B23: KES | C23: =Farm_PnL!C26*(1-Inputs!C$9) -> 1528550 | D23: =Farm_PnL!D26*(1-Inputs!D$9) -> 1528550 | E23: =Farm_PnL!E26*(1-Inputs!E$9) -> 1528550 | F23: =D23/Inputs!$D$4 -> 11768.034
A24: Return on stock proceeds | B24: KES | C24: =C23*Inputs!C$5 -> 30571 | D24: =D23*Inputs!D$5 -> 30571 | E24: =E23*Inputs!E$5 -> 30571 | F24: =D24/Inputs!$D$4 -> 235.36069
A25: Owner hours | B25: h/yr | C25: =Inputs!C$144 -> 40 | D25: =Inputs!D$144 -> 30 | E25: =Inputs!E$144 -> 20
A26: Transition per year | B26: KES | C26: =(Inputs!C$148+Farm_PnL!C26*Inputs!C$9+Labour!C15*Inputs!C$149)/Inputs!C$147 -> 55112.5 | D26: =(Inputs!D$148+Farm_PnL!D26*Inputs!D$9+Labour!D15*Inputs!D$149)/Inputs!D$147 -> 55112.5 | E26: =(Inputs!E$148+Farm_PnL!E26*Inputs!E$9+Labour!E15*Inputs!E$149)/Inputs!E$147 -> 55112.5 | F26: =D26/Inputs!$D$4 -> 424.30133
A27: VALUE: lease | B27: KES | C27: =C22+C24-Inputs!C$151-C25*Inputs!C$8-C26+C7 -> 11458.5 | D27: =D22+D24-Inputs!D$151-D25*Inputs!D$8-D26+D7 -> 102458.5 | E27: =E22+E24-Inputs!E$151-E25*Inputs!E$8-E26+E7 -> 238458.5 | F27: =D27/Inputs!$D$4 -> 788.80976
A28: Option 4: Sale of land, buildings and stock
A29: Net proceeds after selling cost/tax | B29: KES | C29: =(Farm_PnL!C47)*(1-Inputs!C$9) -> 6278550 | D29: =(Farm_PnL!D47)*(1-Inputs!D$9) -> 7988550 | E29: =(Farm_PnL!E47)*(1-Inputs!E$9) -> 10268550 | F29: =D29/Inputs!$D$4 -> 61502.425
A30: VALUE: sale (return on proceeds) | B30: KES | C30: =C29*Inputs!C$5 -> 125571 | D30: =D29*Inputs!D$5 -> 159771 | E30: =E29*Inputs!E$5 -> 205371 | F30: =D30/Inputs!$D$4 -> 1230.0485 | G30: Sale cost, no staff transition, owner time ~0 after completion
A31: Stress test (single-factor, worst of: price -20%, inputs +25%, disease -10% stock)
A32: OMBM after price -20% | B32: KES | C32: =C4-0.2*C5 -> -1607267.6 | D32: =D4-0.2*D5 -> -788870.12 | E32: =E4-0.2*E5 -> 71031.847 | F32: =D32/Inputs!$D$4 -> -6073.3707
A33: OMBM after inputs +25% | B33: KES | C33: =C4-0.25*Farm_PnL!C17 -> -1812009.5 | D33: =D4-0.25*Farm_PnL!D17 -> -795887.64 | E33: =E4-0.25*Farm_PnL!E17 -> 271864.81 | F33: =D33/Inputs!$D$4 -> -6127.3974
A34: OMBM after disease (-10% output and stock value) | B34: KES | C34: =C4-0.1*C5-0.1*Farm_PnL!C26 -> -1552351.4 | D34: =D4-0.1*D5-0.1*Farm_PnL!D26 -> -672118.94 | E34: =E4-0.1*E5-0.1*Farm_PnL!E26 -> 267010.85 | F34: =D34/Inputs!$D$4 -> -5174.5241
A35: Worst scenario OMBM | B35: KES | C35: =MIN(C32,C33,C34) -> -1812009.5 | D35: =MIN(D32,D33,D34) -> -795887.64 | E35: =MIN(E32,E33,E34) -> 71031.847 | F35: =D35/Inputs!$D$4 -> -6127.3974
A36: Stress limit: -10% of K | B36: KES | C36: =-0.1*C6 -> -317919.93 | D36: =-0.1*D6 -> -310451.99 | E36: =-0.1*E6 -> -305450 | F36: =D36/Inputs!$D$4 -> -2390.1146
A37: Net cash flow, option 1, worst scenario | B37: KES | C37: =C35-C11-C12 -> -3466009.5 | D37: =D35-D11-D12 -> -2449887.6 | E37: =E35-E11-E12 -> -1582968.2 | F37: =D37/Inputs!$D$4 -> -18861.249
A38: Net cash flow, option 2, worst scenario | B38: KES | C38: =C35-C17-C18 -> -2072009.5 | D38: =D35-D17-D18 -> -1055887.6 | E38: =E35-E17-E18 -> -188968.15 | F38: =D38/Inputs!$D$4 -> -8129.0911
A39: Option 1 passes stress limit (1/0) | B39: flag | C39: =IF(C37>=C36,1,0) -> 0 | D39: =IF(D37>=D36,1,0) -> 0 | E39: =IF(E37>=E36,1,0) -> 0
A40: Option 2 passes stress limit (1/0) | B40: flag | C40: =IF(C38>=C36,1,0) -> 0 | D40: =IF(D38>=D36,1,0) -> 0 | E40: =IF(E38>=E36,1,0) -> 1
A41: Ranking A: all options (if lease and sale were legally available now)
A42: Eligible: self-run generic | B42: flag | C42: =IF(AND(C14>0,C39=1),1,0) -> 0 | D42: =IF(AND(D14>0,D39=1),1,0) -> 0 | E42: =IF(AND(E14>0,E39=1),1,0) -> 0
A43: Eligible: owner-operator simplified | B43: flag | C43: =IF(AND(C20>0,C40=1),1,0) -> 0 | D43: =IF(AND(D20>0,D40=1),1,0) -> 0 | E43: =IF(AND(E20>0,E40=1),1,0) -> 1
A44: Eligible: lease | B44: flag | C44: =IF(C27>0,1,0) -> 1 | D44: =IF(D27>0,1,0) -> 1 | E44: =IF(E27>0,1,0) -> 1
A45: Eligible: sale | B45: flag | C45: =IF(C30>0,1,0) -> 1 | D45: =IF(D30>0,1,0) -> 1 | E45: =IF(E30>0,1,0) -> 1
A46: Score option 1 | B46: KES | C46: =IF(C42=1,C14,-1000000000000) -> -1000000000000 | D46: =IF(D42=1,D14,-1000000000000) -> -1000000000000 | E46: =IF(E42=1,E14,-1000000000000) -> -1000000000000
A47: Score option 2 | B47: KES | C47: =IF(C43=1,C20,-1000000000000) -> -1000000000000 | D47: =IF(D43=1,D20,-1000000000000) -> -1000000000000 | E47: =IF(E43=1,E20,-1000000000000) -> 511654.85
A48: Score option 3 | B48: KES | C48: =IF(C44=1,C27,-1000000000000) -> 11458.5 | D48: =IF(D44=1,D27,-1000000000000) -> 102458.5 | E48: =IF(E44=1,E27,-1000000000000) -> 238458.5
A49: Score option 4 | B49: KES | C49: =IF(C45=1,C30,-1000000000000) -> 125571 | D49: =IF(D45=1,D30,-1000000000000) -> 159771 | E49: =IF(E45=1,E30,-1000000000000) -> 205371
A50: Rank option 1 | B50: rank | C50: =RANK(C46,C46:C49) -> 3 | D50: =RANK(D46,D46:D49) -> 3 | E50: =RANK(E46,E46:E49) -> 4
A51: Rank option 2 | B51: rank | C51: =RANK(C47,C46:C49) -> 3 | D51: =RANK(D47,D46:D49) -> 3 | E51: =RANK(E47,E46:E49) -> 1
A52: Rank option 3 | B52: rank | C52: =RANK(C48,C46:C49) -> 2 | D52: =RANK(D48,D46:D49) -> 2 | E52: =RANK(E48,E46:E49) -> 2
A53: Rank option 4 | B53: rank | C53: =RANK(C49,C46:C49) -> 1 | D53: =RANK(D49,D46:D49) -> 1 | E53: =RANK(E49,E46:E49) -> 3
A54: Top score | B54: KES | C54: =MAX(C46,C47,C48,C49) -> 125571 | D54: =MAX(D46,D47,D48,D49) -> 159771 | E54: =MAX(E46,E47,E48,E49) -> 511654.85
A55: WINNER (ranking A) | B55: text | C55: =IF(C54<=0,"No viable option",IF(C46=C54,"Self-run (PLAN generic)",IF(C47=C54,"Owner-operator, simplified",IF(C48=C54,"Lease","Sale")))) -> Sale | D55: =IF(D54<=0,"No viable option",IF(D46=D54,"Self-run (PLAN generic)",IF(D47=D54,"Owner-operator, simplified",IF(D48=D54,"Lease","Sale")))) -> Sale | E55: =IF(E54<=0,"No viable option",IF(E46=E54,"Self-run (PLAN generic)",IF(E47=E54,"Owner-operator, simplified",IF(E48=E54,"Lease","Sale")))) -> Owner-operator, simplified
A56: Ranking B: executable pre-title (lease/sale excluded unless Inputs title_ok = 1)
A57: Eligible: lease (executable) | B57: flag | C57: =IF(AND(C44=1,Inputs!C$152=1),1,0) -> 0 | D57: =IF(AND(D44=1,Inputs!D$152=1),1,0) -> 0 | E57: =IF(AND(E44=1,Inputs!E$152=1),1,0) -> 0
A58: Eligible: sale (executable) | B58: flag | C58: =IF(AND(C45=1,Inputs!C$152=1),1,0) -> 0 | D58: =IF(AND(D45=1,Inputs!D$152=1),1,0) -> 0 | E58: =IF(AND(E45=1,Inputs!E$152=1),1,0) -> 0
A59: Score: self-run generic | B59: KES | C59: =IF(C42=1,C14,-1000000000000) -> -1000000000000 | D59: =IF(D42=1,D14,-1000000000000) -> -1000000000000 | E59: =IF(E42=1,E14,-1000000000000) -> -1000000000000
A60: Score: owner-operator simplified | B60: KES | C60: =IF(C43=1,C20,-1000000000000) -> -1000000000000 | D60: =IF(D43=1,D20,-1000000000000) -> -1000000000000 | E60: =IF(E43=1,E20,-1000000000000) -> 511654.85
A61: Score: lease | B61: KES | C61: =IF(C57=1,C27,-1000000000000) -> -1000000000000 | D61: =IF(D57=1,D27,-1000000000000) -> -1000000000000 | E61: =IF(E57=1,E27,-1000000000000) -> -1000000000000
A62: Score: sale | B62: KES | C62: =IF(C58=1,C30,-1000000000000) -> -1000000000000 | D62: =IF(D58=1,D30,-1000000000000) -> -1000000000000 | E62: =IF(E58=1,E30,-1000000000000) -> -1000000000000
A63: Top score | B63: KES | C63: =MAX(C59,C60,C61,C62) -> -1000000000000 | D63: =MAX(D59,D60,D61,D62) -> -1000000000000 | E63: =MAX(E59,E60,E61,E62) -> 511654.85
A64: WINNER (ranking B, executable now) | B64: text | C64: =IF(C63<=0,"No viable option (hold, simplify or fix title first)",IF(C59=C63,"Self-run (PLAN generic)",IF(C60=C63,"Owner-operator, simplified",IF(C61=C63,"Lease","Sale")))) -> No viable option (hold, simplify or fix title first) | D64: =IF(D63<=0,"No viable option (hold, simplify or fix title first)",IF(D59=D63,"Self-run (PLAN generic)",IF(D60=D63,"Owner-operator, simplified",IF(D61=D63,"Lease","Sale")))) -> No viable option (hold, simplify or fix title first) | E64: =IF(E63<=0,"No viable option (hold, simplify or fix title first)",IF(E59=E63,"Self-run (PLAN generic)",IF(E60=E63,"Owner-operator, simplified",IF(E61=E63,"Lease","Sale")))) -> Owner-operator, simplified
A65: Diagnostics
A66: Option 1 value as % of asset base | B66: % | C66: =C14/Farm_PnL!C47 -> -0.49645865 | D66: =D14/Farm_PnL!D47 -> -0.25939452 | E66: =E14/Farm_PnL!E47 -> -0.091390984
A67: Option 2 value as % of asset base | B67: % | C67: =C20/Farm_PnL!C47 -> -0.28663871 | D67: =D20/Farm_PnL!D47 -> -0.084522364 | E67: =E20/Farm_PnL!E47 -> 0.047336002
A68: Lease value as % of asset base | B68: % | C68: =C27/Farm_PnL!C47 -> 0.0017337721 | D68: =D27/Farm_PnL!D47 -> 0.012184386 | E68: =E27/Farm_PnL!E47 -> 0.022061106
A69: Sale value as % of asset base | B69: % | C69: =C30/Farm_PnL!C47 -> 0.019 | D69: =D30/Farm_PnL!D47 -> 0.019 | E69: =E30/Farm_PnL!E47 -> 0.019
A70: Flip point g*: real land-value growth at which lease beats sale | B70: % | C70: =(C30-(C27-C7))/Farm_PnL!C46 -> 0.027169643 | D70: =(D30-(D27-D7))/Farm_PnL!D46 -> 0.019552083 | E70: =(E30-(E27-E7))/Farm_PnL!E46 -> 0.016061012 | G70: Lease value excluding g x L, versus sale value; above g* lease wins
A71: OMBM gain if purchased feed/forage cost falls 20% (own fodder, bulk buying) | B71: KES | C71: =0.2*Farm_PnL!C42 -> 313517.43 | D71: =0.2*Farm_PnL!D42 -> 272916.43 | E71: =0.2*Farm_PnL!E42 -> 248682.57 | F71: =D71/Inputs!$D$4 -> 2101.135
A72: PLAN band cap: 7% of revenue (small band) vs generic controls | B72: KES | C72: =0.07*C5 -> 151071.33 | D72: =0.07*D5 -> 194355.82 | E72: =0.07*E5 -> 249815.3 | F72: =D72/Inputs!$D$4 -> 1496.3109
A73: Generic controls as % of revenue | B73: % | C73: =C11/C5 -> 0.46057712 | D73: =D11/D5 -> 0.35800317 | E73: =E11/E5 -> 0.27852577
A74: Generic controls + manager/deputy as % of revenue | B74: % | C74: =(C11+C12)/C5 -> 0.76639291 | D74: =(D11+D12)/D5 -> 0.59571151 | E74: =(E11+E12)/E5 -> 0.4634624
A75: Generic controls + manager/deputy as multiple of OMBM | B75: x | C75: =IF(C4<=0,"OMBM<=0",(C11+C12)/C4) -> OMBM<=0 | D75: =IF(D4<=0,"OMBM<=0",(D11+D12)/D4) -> OMBM<=0 | E75: =IF(E4<=0,"OMBM<=0",(E11+E12)/E4) -> 2.1075706
A76: PLAN core-only items at generic prices, % of revenue | B76: % | C76: =Overhead!$C$18/C5 -> 0.17700247 | D76: =Overhead!$C$18/D5 -> 0.13758271 | E76: =Overhead!$C$18/E5 -> 0.10703908
A77: Simplified controls as % of revenue | B77: % | C77: =C17/C5 -> 0.087111165 | D77: =D17/D5 -> 0.067710861 | E77: =E17/E5 -> 0.052678919
A78: One-third of OMBM (B10 limit) | B78: KES | C78: =C4/3 -> -391878.42 | D78: =D4/3 -> -77855.922 | E78: =E4/3 -> 261596.62 | F78: =D78/Inputs!$D$4 -> -599.39889
A79: Simplified controls fit one-third-of-OMBM test (1/0) | B79: flag | C79: =IF(AND(C4>0,C17<=C78),1,0) -> 0 | D79: =IF(AND(D4>0,D17<=D78),1,0) -> 0 | E79: =IF(AND(E4>0,E17<=E78),1,0) -> 1
A80: Simplified controls fit 7% band cap (1/0) | B80: flag | C80: =IF(C17<=C72,1,0) -> 0 | D80: =IF(D17<=D72,1,0) -> 1 | E80: =IF(E17<=E72,1,0) -> 1
A81: Option 2 value as % of OMBM (conditional pass if <10%) | B81: % | C81: =IF(C4<=0,0,C20/C4) -> 0 | D81: =IF(D4<=0,0,D20/D4) -> 0 | E81: =IF(E4<=0,0,E20/E4) -> 0.65196415
A82: Break-even (assumes variable costs scale with revenue: contribution ratio held)
A83: Option 2: OMBM needed for value = 0 | B83: KES | C83: =C18+C17+C16*Inputs!C$8+C19+C8-C7 -> 718759.96 | D83: =D18+D17+D16*Inputs!D$8+D19+D8-D7 -> 477180.8 | E83: =E18+E17+E16*Inputs!E$8+E19+E8-E7 -> 273135 | F83: =D83/Inputs!$D$4 -> 3673.73
A84: Option 2: revenue for value = 0 | B84: KES | C84: =IF(Farm_PnL!C33<=0.02,"n/a",(Farm_PnL!C28+C83)/Farm_PnL!C33) -> n/a | D84: =IF(Farm_PnL!D33<=0.02,"n/a",(Farm_PnL!D28+D83)/Farm_PnL!D33) -> 6519457.6 | E84: =IF(Farm_PnL!E33<=0.02,"n/a",(Farm_PnL!E28+E83)/Farm_PnL!E33) -> 2365177.2 | F84: =D84/Inputs!$D$4 -> 50192.144
A85: Option 2: revenue to match lease value | B85: KES | C85: =IF(Farm_PnL!C33<=0.02,"n/a",(Farm_PnL!C28+C83+C27)/Farm_PnL!C33) -> n/a | D85: =IF(Farm_PnL!D33<=0.02,"n/a",(Farm_PnL!D28+D83+D27)/Farm_PnL!D33) -> 7059024.9 | E85: =IF(Farm_PnL!E33<=0.02,"n/a",(Farm_PnL!E28+E83+E27)/Farm_PnL!E33) -> 2926125.1 | F85: =D85/Inputs!$D$4 -> 54346.176
A86: Option 2: break-even revenue as multiple of current | B86: x | C86: =IF(ISNUMBER(C84),C84/C5,"n/a") -> n/a | D86: =IF(ISNUMBER(D84),D84/D5,"n/a") -> 2.3480749 | E86: =IF(ISNUMBER(E84),E84/E5,"n/a") -> 0.66273926
A87: Option 2 cash-only: OMBM needed ignoring owner time, set-up, risk charge, g | B87: KES | C87: =C18+C17 -> 260000 | D87: =D18+D17 -> 260000 | E87: =E18+E17 -> 260000 | F87: =D87/Inputs!$D$4 -> 2001.6937
A88: Option 2 cash-only break-even revenue | B88: KES | C88: =IF(Farm_PnL!C33<=0.02,"n/a",(Farm_PnL!C28+C87)/Farm_PnL!C33) -> n/a | D88: =IF(Farm_PnL!D33<=0.02,"n/a",(Farm_PnL!D28+D87)/Farm_PnL!D33) -> 5375739.6 | E88: =IF(Farm_PnL!E33<=0.02,"n/a",(Farm_PnL!E28+E87)/Farm_PnL!E33) -> 2334278.6 | F88: =D88/Inputs!$D$4 -> 41386.863
A89: Option 1: OMBM needed for value = 0 | B89: KES | C89: =C12+C11+C10*Inputs!C$8+C13+C8-C7 -> 2105460 | D89: =D12+D11+D10*Inputs!D$8+D13+D8-D7 -> 1947680.8 | E89: =E12+E11+E10*Inputs!E$8+E13+E8-E7 -> 1772635 | F89: =D89/Inputs!$D$4 -> 14994.848
A90: Option 1: revenue for value = 0 | B90: KES | C90: =IF(Farm_PnL!C33<=0.02,"n/a",(Farm_PnL!C28+C89)/Farm_PnL!C33) -> n/a | D90: =IF(Farm_PnL!D33<=0.02,"n/a",(Farm_PnL!D28+D89)/Farm_PnL!D33) -> 14263409 | E90: =IF(Farm_PnL!E33<=0.02,"n/a",(Farm_PnL!E28+E89)/Farm_PnL!E33) -> 5892589 | F90: =D90/Inputs!$D$4 -> 109811.44
A91: Option 1: break-even revenue as multiple of current | B91: x | C91: =IF(ISNUMBER(C90),C90/C5,"n/a") -> n/a | D91: =IF(ISNUMBER(D90),D90/D5,"n/a") -> 5.1371684 | E91: =IF(ISNUMBER(E90),E90/E5,"n/a") -> 1.6511448
A92: Value per owner hour, option 2 (before owner-time charge) | B92: KES/h | C92: =(C20+C16*Inputs!C$8)/C16 -> -2260.6674 | D92: =(D20+D16*Inputs!D$8)/D16 -> -1245.1056 | E92: =(E20+E16*Inputs!E$8)/E16 -> 1966.9626 | F92: =D92/Inputs!$D$4 -> -9.5858462

Sheet Collect_8wk
A1: Data the owner must collect in the first 8 weeks (replaces ASSUMED inputs)
A2: No. | B2: Measure | C2: Method | D2: Replaces Inputs rows | E2: Week
A3: 1 | B3: Independent opening count: every animal by class, each bird species | C3: Owner or trusted party counts with photos; signed tally | D3: n_* counts, flock split | E3: 1
A4: 2 | B4: Title status: document in hand (title deed / allotment letter / share certificate / search at lands registry) | C4: Official search by lawyer; copy of document | D4: title_ok, land value | E4: 1
A5: 3 | B5: Acreage by use; grazing, fodder, crops; water source and reliability | C5: Walk with GPS phone app; photos | D5: acres, cat_forage, fx_water | E5: 2
A6: 4 | B6: Daily milk per cow, bulked litres and buyer price received | C6: Daily tally sheet; buyer receipts / M-Pesa | D6: cows, lpd, lact, milk_price | E6: 8
A7: 5 | B7: Daily eggs, feed bags opened, mortality (layers) | C7: Tally sheet at 17:00; photo of bags and trays | D7: hd, breakage, feed_g, ly_mort | E7: 8
A8: 6 | B8: Feed purchases: item, bags, price, supplier | C8: Keep receipts; supplier quotes x3 | D8: meal_price, lay_bag, gr_bag | E8: 4
A9: 7 | B9: Sales: every animal/egg/bird sold, weight, price, buyer | C9: Sales book + M-Pesa statement | D9: cat_price, sh_price, gt_price, tray, kien/duck/guinea/geese price | E9: 8
A10: 8 | B10: Hatch/purchase of chicks and pullets: price, supplier, mortality | C10: Receipts; mortality tally | D10: pullet, *_chick, *_mort | E10: 8
A11: 9 | B11: Vet and drug spend; vaccination dates; vet-of-record quote | C11: Vet visit notes | D11: cat_vet, sm_vet, ly_vet | E11: 6
A12: 10 | B12: Staff time log (who did what, hours) for 2 typical weeks | C12: Simple daily sheet | D12: h_cat ... h_gen | E12: 4
A13: 11 | B13: Staff terms: contracts, start dates, relationships to owner, actual pay | C13: Interview; payslips | D13: w_sup, w_pou, w_gen, severance | E13: 2
A14: 12 | B14: Owner hours actually spent and distance to farm | C14: Own log | D14: h_rem, visits, h_admin | E14: 8
... A16: 14 | B16: Lender/insurer requirements for unregistered land | C16: Phone SACCO/bank/insurer | D16: qualitative | E16: 6
